Workbook
Name Avg_Sale_Price: 'Single Project Assumptions'!$L$37
Name Base_Dates_120: Calc_Helper!$C$3:$DR$3
Name Closing_Selected_120: Calc_Helper!$C$73:$DR$73
Name Deposit_Per_Unit: 'Single Project Assumptions'!$L$42
Name DevCF_All_120: Calc_Helper!$C$57:$DR$57
Name DevCF_All_Neg_120: Calc_Helper!$C$56:$DR$56
Name DevCF_All_Pos_120: Calc_Helper!$C$55:$DR$55
Name DevCF_P1_120: Calc_Helper!$C$58:$DR$58
Name DevCF_P2Plus_120: Calc_Helper!$C$59:$DR$59
Name DevCF_Selected_120: Calc_Helper!$C$72:$DR$72
Name Model_StartDate: 'Single Project Assumptions'!$D$6
Name Sales_BrokerSelected_120: Calc_Helper!$C$74:$DR$74
Name Sales_Selected_120: Calc_Helper!$C$70:$DR$70
Name Units_Per_Project: 'Single Project Assumptions'!$D$21

Sheet Title Page
M8: EP PROJECT
M9: Platform Model | N9: Version 1
M10: Author | N10: Tom
M11: Production Date | N11: 46012
M14: Lets go back to the future and create lives people can afford to live
M16: Your future is whatever you make it. So make it a good one.
M18: -Doc Brown - Back to the Future Part III
B40: A capital-light coordination platform for building intentional communities

Sheet Dashboard
C3: THE COMMONS DASHBOARD
C5: The Commons Key Metrics (Portfolio View) | L5: Risk-Adjusted Investor Returns | U5: Single Project Key Metrics | AM5: Day 1 Yield | AN5: ='Single Project Assumptions'!D49 -> 0.02
C6: Number of Projects | E6: Successful Entitlements | G6: 10 Year Platform Revenue | I6: 10 Year EBITDA | U6: Number of Units | W6: Total Development Cost | Y6: Gross Development Value | AA6: Profit on Cost | AM6: Stabilized Yield | AN6: ='Single Project Assumptions'!D51 -> 0.15
C7: =MAX('Platform Assumptions'!B6:B15) -> 10 | E7: =COUNTIF('Platform Assumptions'!E6:E15,"Yes") -> 5 | G7: ='The Commons Platform CF'!D17/1000000 -> 17.33076 | I7: ='The Commons Platform CF'!D21/1000000 -> 12.289093 | U7: ='Single Project Assumptions'!D21 -> 150 | W7: ='Single Project Assumptions'!L31/1000000 -> 159.525 | Y7: ='Single Project Assumptions'!L38/1000000 -> 225 | AA7: =(Y7-W7)/W7 -> 0.41043724
AM8: Entitlement Investor IRR | AN8: ='Entitlement Phase'!D13 -> 0.41443852
AM9: Development Investor IRR | AN9: ='Development Phase'!D29 -> 0.22888162
C10: Day 1 Landowner Economics | U10: Sale Assumptions
C11: Day 1 Land Value | E11: Farming Yield | G11: Farming Income | I11: Farming Risk | U11: Sale Period | W11: Velocity Units / Month | Y11: Deposit Assumed | AA11: Paid On Completion | AM11: Land Stewardship Fee (Landowner) | AP11: ='Single Project Assumptions'!D53 -> 1000
C12: ='Single Project Assumptions'!D48/1000000 -> 1 | E12: ='Single Project Assumptions'!D49 -> 0.02 | G12: ='Single Project Assumptions'!D50/1000000 -> 0.02 | I12: High | U12: ='Single Project Assumptions'!P13 -> 18 | W12: ='Single Project Assumptions'!P15 -> 8.3333333 | Y12: ='Single Project Assumptions'!L41 -> 0.15 | AA12: =1-Y12 -> 0.85 | AM12: Operations Fee (Commons) | AP12: ='Single Project Assumptions'!P50 -> 1800
AM13: Service Charges (Community) | AP13: ='Single Project Assumptions'!T50 -> 2400
C14: Very poor day 1 economics with high farming risks and potential for negative yields | AM14: Total Fees | AP14: =SUM(AP11:AP13) -> 5200
C18: Stabilized Landowner Economics (The Commons Targets) | L18: Total Annual Fees Paid By End Residents | U18: KEY MODEL EXCLUSIONS TO NOTE
C19: Day 1 Land Value | E19: Target Yield | G19: Stewardship Income | I19: Operational Risk | U19: It is important to note that this is a v1 model that makes several key exclusions in the spriit of simplicity. Additional functionality can be added in at a later stage as required.
C20: =C12 -> 1 | E20: ='Single Project Assumptions'!D51 -> 0.15 | G20: ='Single Project Assumptions'!D52/1000000 -> 0.15 | I20: Low
U21: External Debt Financing | Y21: Growth and Inflation
U23: Development Phasing | Y23: Detailed Development Budgets
U25: Taxes | Y25: Developer Incentives (e.g. Carried Interest)
U28: The Commons is a capital-light coordination platform that aligns landowners, entitlement capital, developers, and residents through repeatable project structures.

Sheet Platform Cash Flow--->
M4: Description
M5: This section rolls up multiple Commons projects into a single platform-level cash flow. Some projects succeed, some fail — that’s the point. By toggling entitlement outcomes on and off, we can see how The Commons performs as a portfolio rather than a one-off development bet. Central overhead is included to reflect the reality of running the platform.

Sheet Platform Assumptions
B3: PLATFORM ASSUMPTIONS
B5: Project Number | C5: Months Lag | D5: Start Date | E5: Entitlement Success | G5: Central Overhead Costs
B6: 1 | D6: ='Single Project Assumptions'!D6 -> 46387 | E6: Yes | G6: Costs / Year | I6: 500000
B7: =B6+1 -> 2 | C7: 3 | D7: =EOMONTH(D6,C7) -> 46477 | E7: No | G7: Costs / Month | I7: =I6/12 -> 41666.667
B8: =B7+1 -> 3 | C8: =C7 -> 3 | D8: =EOMONTH(D7,C8) -> 46568 | E8: Yes
B9: =B8+1 -> 4 | C9: =C8 -> 3 | D9: =EOMONTH(D8,C9) -> 46660 | E9: No
B10: =B9+1 -> 5 | C10: =C9 -> 3 | D10: =EOMONTH(D9,C10) -> 46752 | E10: Yes
B11: =B10+1 -> 6 | C11: =C10 -> 3 | D11: =EOMONTH(D10,C11) -> 46843 | E11: No
B12: =B11+1 -> 7 | C12: =C11 -> 3 | D12: =EOMONTH(D11,C12) -> 46934 | E12: Yes
B13: =B12+1 -> 8 | C13: =C12 -> 3 | D13: =EOMONTH(D12,C13) -> 47026 | E13: No
B14: =B13+1 -> 9 | C14: =C13 -> 3 | D14: =EOMONTH(D13,C14) -> 47118 | E14: Yes
B15: =B14+1 -> 10 | C15: =C14 -> 3 | D15: =EOMONTH(D14,C15) -> 47208 | E15: No
B19: PROJECT STAGGERED CASH FLOWS
B21: Project Cash Flows
B22: Project 1 | C22: Total | D22: =D6 -> 46387 | E22: =EOMONTH(D22,1) -> 46418 | F22: =EOMONTH(E22,1) -> 46446 | G22: =EOMONTH(F22,1) -> 46477 | H22: =EOMONTH(G22,1) -> 46507 | I22: =EOMONTH(H22,1) -> 46538 | J22: =EOMONTH(I22,1) -> 46568 | K22: =EOMONTH(J22,1) -> 46599 | L22: =EOMONTH(K22,1) -> 46630 | ... DT22: =EOMONTH(DS22,1) -> 50040
B23: Cash Flow | C23: =SUM(D23:DT23) -> 3393552 | D23: =IF($E$6="Yes",'Rolled Up Cash Flows'!E$31,'Rolled Up Cash Flows'!E$53) -> 46666.667 | E23: =IF($E$6="Yes",'Rolled Up Cash Flows'!F$31,'Rolled Up Cash Flows'!F$53) -> -3333.3333 | F23: =IF($E$6="Yes",'Rolled Up Cash Flows'!G$31,'Rolled Up Cash Flows'!G$53) -> -3333.3333 | G23: =IF($E$6="Yes",'Rolled Up Cash Flows'!H$31,'Rolled Up Cash Flows'!H$53) -> -3333.3333 | H23: =IF($E$6="Yes",'Rolled Up Cash Flows'!I$31,'Rolled Up Cash Flows'!I$53) -> -3333.3333 | I23: =IF($E$6="Yes",'Rolled Up Cash Flows'!J$31,'Rolled Up Cash Flows'!J$53) -> -3333.3333 | J23: =IF($E$6="Yes",'Rolled Up Cash Flows'!K$31,'Rolled Up Cash Flows'!K$53) -> 6250 | K23: =IF($E$6="Yes",'Rolled Up Cash Flows'!L$31,'Rolled Up Cash Flows'!L$53) -> 6250 | ... DT23: =IF($E$6="Yes",'Rolled Up Cash Flows'!DU$31,'Rolled Up Cash Flows'!DU$53) -> 0
B25: Project 2 | C25: Total | D25: =D7 -> 46477 | E25: =EOMONTH(D25,1) -> 46507 | F25: =EOMONTH(E25,1) -> 46538 | G25: =EOMONTH(F25,1) -> 46568 | H25: =EOMONTH(G25,1) -> 46599 | I25: =EOMONTH(H25,1) -> 46630 | J25: =EOMONTH(I25,1) -> 46660 | K25: =EOMONTH(J25,1) -> 46691 | L25: =EOMONTH(K25,1) -> 46721 | ... DT25: =EOMONTH(DS25,1) -> 50130
B26: Cash Flow | C26: =SUM(D26:DT26) -> 105000 | D26: =IF($E$7="Yes",'Rolled Up Cash Flows'!E$31,'Rolled Up Cash Flows'!E$53) -> 46666.667 | E26: =IF($E$7="Yes",'Rolled Up Cash Flows'!F$31,'Rolled Up Cash Flows'!F$53) -> -3333.3333 | F26: =IF($E$7="Yes",'Rolled Up Cash Flows'!G$31,'Rolled Up Cash Flows'!G$53) -> -3333.3333 | G26: =IF($E$7="Yes",'Rolled Up Cash Flows'!H$31,'Rolled Up Cash Flows'!H$53) -> -3333.3333 | H26: =IF($E$7="Yes",'Rolled Up Cash Flows'!I$31,'Rolled Up Cash Flows'!I$53) -> -3333.3333 | I26: =IF($E$7="Yes",'Rolled Up Cash Flows'!J$31,'Rolled Up Cash Flows'!J$53) -> -3333.3333 | J26: =IF($E$7="Yes",'Rolled Up Cash Flows'!K$31,'Rolled Up Cash Flows'!K$53) -> 6250 | K26: =IF($E$7="Yes",'Rolled Up Cash Flows'!L$31,'Rolled Up Cash Flows'!L$53) -> 6250 | ... DT26: =IF($E$7="Yes",'Rolled Up Cash Flows'!DU$31,'Rolled Up Cash Flows'!DU$53) -> 0
B28: Project 3 | C28: Total | D28: =D8 -> 46568 | E28: =EOMONTH(D28,1) -> 46599 | F28: =EOMONTH(E28,1) -> 46630 | G28: =EOMONTH(F28,1) -> 46660 | H28: =EOMONTH(G28,1) -> 46691 | I28: =EOMONTH(H28,1) -> 46721 | J28: =EOMONTH(I28,1) -> 46752 | K28: =EOMONTH(J28,1) -> 46783 | L28: =EOMONTH(K28,1) -> 46812 | ... DT28: =EOMONTH(DS28,1) -> 50221
B29: Cash Flow | C29: =SUM(D29:DT29) -> 3393552 | D29: =IF($E$8="Yes",'Rolled Up Cash Flows'!E$31,'Rolled Up Cash Flows'!E$53) -> 46666.667 | E29: =IF($E$8="Yes",'Rolled Up Cash Flows'!F$31,'Rolled Up Cash Flows'!F$53) -> -3333.3333 | F29: =IF($E$8="Yes",'Rolled Up Cash Flows'!G$31,'Rolled Up Cash Flows'!G$53) -> -3333.3333 | G29: =IF($E$8="Yes",'Rolled Up Cash Flows'!H$31,'Rolled Up Cash Flows'!H$53) -> -3333.3333 | H29: =IF($E$8="Yes",'Rolled Up Cash Flows'!I$31,'Rolled Up Cash Flows'!I$53) -> -3333.3333 | I29: =IF($E$8="Yes",'Rolled Up Cash Flows'!J$31,'Rolled Up Cash Flows'!J$53) -> -3333.3333 | J29: =IF($E$8="Yes",'Rolled Up Cash Flows'!K$31,'Rolled Up Cash Flows'!K$53) -> 6250 | K29: =IF($E$8="Yes",'Rolled Up Cash Flows'!L$31,'Rolled Up Cash Flows'!L$53) -> 6250 | ... DT29: =IF($E$8="Yes",'Rolled Up Cash Flows'!DU$31,'Rolled Up Cash Flows'!DU$53) -> 0
B31: Project 4 | C31: Total | D31: =D9 -> 46660 | E31: =EOMONTH(D31,1) -> 46691 | F31: =EOMONTH(E31,1) -> 46721 | G31: =EOMONTH(F31,1) -> 46752 | H31: =EOMONTH(G31,1) -> 46783 | I31: =EOMONTH(H31,1) -> 46812 | J31: =EOMONTH(I31,1) -> 46843 | K31: =EOMONTH(J31,1) -> 46873 | L31: =EOMONTH(K31,1) -> 46904 | ... DT31: =EOMONTH(DS31,1) -> 50313
B32: Cash Flow | C32: =SUM(D32:DT32) -> 105000 | D32: =IF($E$9="Yes",'Rolled Up Cash Flows'!E$31,'Rolled Up Cash Flows'!E$53) -> 46666.667 | E32: =IF($E$9="Yes",'Rolled Up Cash Flows'!F$31,'Rolled Up Cash Flows'!F$53) -> -3333.3333 | F32: =IF($E$9="Yes",'Rolled Up Cash Flows'!G$31,'Rolled Up Cash Flows'!G$53) -> -3333.3333 | G32: =IF($E$9="Yes",'Rolled Up Cash Flows'!H$31,'Rolled Up Cash Flows'!H$53) -> -3333.3333 | H32: =IF($E$9="Yes",'Rolled Up Cash Flows'!I$31,'Rolled Up Cash Flows'!I$53) -> -3333.3333 | I32: =IF($E$9="Yes",'Rolled Up Cash Flows'!J$31,'Rolled Up Cash Flows'!J$53) -> -3333.3333 | J32: =IF($E$9="Yes",'Rolled Up Cash Flows'!K$31,'Rolled Up Cash Flows'!K$53) -> 6250 | K32: =IF($E$9="Yes",'Rolled Up Cash Flows'!L$31,'Rolled Up Cash Flows'!L$53) -> 6250 | ... DT32: =IF($E$9="Yes",'Rolled Up Cash Flows'!DU$31,'Rolled Up Cash Flows'!DU$53) -> 0
B34: Project 5 | C34: Total | D34: =D10 -> 46752 | E34: =EOMONTH(D34,1) -> 46783 | F34: =EOMONTH(E34,1) -> 46812 | G34: =EOMONTH(F34,1) -> 46843 | H34: =EOMONTH(G34,1) -> 46873 | I34: =EOMONTH(H34,1) -> 46904 | J34: =EOMONTH(I34,1) -> 46934 | K34: =EOMONTH(J34,1) -> 46965 | L34: =EOMONTH(K34,1) -> 46996 | ... DT34: =EOMONTH(DS34,1) -> 50405
B35: Cash Flow | C35: =SUM(D35:DT35) -> 3393552 | D35: =IF($E$10="Yes",'Rolled Up Cash Flows'!E$31,'Rolled Up Cash Flows'!E$53) -> 46666.667 | E35: =IF($E$10="Yes",'Rolled Up Cash Flows'!F$31,'Rolled Up Cash Flows'!F$53) -> -3333.3333 | F35: =IF($E$10="Yes",'Rolled Up Cash Flows'!G$31,'Rolled Up Cash Flows'!G$53) -> -3333.3333 | G35: =IF($E$10="Yes",'Rolled Up Cash Flows'!H$31,'Rolled Up Cash Flows'!H$53) -> -3333.3333 | H35: =IF($E$10="Yes",'Rolled Up Cash Flows'!I$31,'Rolled Up Cash Flows'!I$53) -> -3333.3333 | I35: =IF($E$10="Yes",'Rolled Up Cash Flows'!J$31,'Rolled Up Cash Flows'!J$53) -> -3333.3333 | J35: =IF($E$10="Yes",'Rolled Up Cash Flows'!K$31,'Rolled Up Cash Flows'!K$53) -> 6250 | K35: =IF($E$10="Yes",'Rolled Up Cash Flows'!L$31,'Rolled Up Cash Flows'!L$53) -> 6250 | ... DT35: =IF($E$10="Yes",'Rolled Up Cash Flows'!DU$31,'Rolled Up Cash Flows'!DU$53) -> 0
B37: Project 6 | C37: Total | D37: =D11 -> 46843 | E37: =EOMONTH(D37,1) -> 46873 | F37: =EOMONTH(E37,1) -> 46904 | G37: =EOMONTH(F37,1) -> 46934 | H37: =EOMONTH(G37,1) -> 46965 | I37: =EOMONTH(H37,1) -> 46996 | J37: =EOMONTH(I37,1) -> 47026 | K37: =EOMONTH(J37,1) -> 47057 | L37: =EOMONTH(K37,1) -> 47087 | ... DT37: =EOMONTH(DS37,1) -> 50495
B38: Cash Flow | C38: =SUM(D38:DT38) -> 105000 | D38: =IF($E$11="Yes",'Rolled Up Cash Flows'!E$31,'Rolled Up Cash Flows'!E$53) -> 46666.667 | E38: =IF($E$11="Yes",'Rolled Up Cash Flows'!F$31,'Rolled Up Cash Flows'!F$53) -> -3333.3333 | F38: =IF($E$11="Yes",'Rolled Up Cash Flows'!G$31,'Rolled Up Cash Flows'!G$53) -> -3333.3333 | G38: =IF($E$11="Yes",'Rolled Up Cash Flows'!H$31,'Rolled Up Cash Flows'!H$53) -> -3333.3333 | H38: =IF($E$11="Yes",'Rolled Up Cash Flows'!I$31,'Rolled Up Cash Flows'!I$53) -> -3333.3333 | I38: =IF($E$11="Yes",'Rolled Up Cash Flows'!J$31,'Rolled Up Cash Flows'!J$53) -> -3333.3333 | J38: =IF($E$11="Yes",'Rolled Up Cash Flows'!K$31,'Rolled Up Cash Flows'!K$53) -> 6250 | K38: =IF($E$11="Yes",'Rolled Up Cash Flows'!L$31,'Rolled Up Cash Flows'!L$53) -> 6250 | ... DT38: =IF($E$11="Yes",'Rolled Up Cash Flows'!DU$31,'Rolled Up Cash Flows'!DU$53) -> 0
B40: Project 7 | C40: Total | D40: =D12 -> 46934 | E40: =EOMONTH(D40,1) -> 46965 | F40: =EOMONTH(E40,1) -> 46996 | G40: =EOMONTH(F40,1) -> 47026 | H40: =EOMONTH(G40,1) -> 47057 | I40: =EOMONTH(H40,1) -> 47087 | J40: =EOMONTH(I40,1) -> 47118 | K40: =EOMONTH(J40,1) -> 47149 | L40: =EOMONTH(K40,1) -> 47177 | ... DT40: =EOMONTH(DS40,1) -> 50586
B41: Cash Flow | C41: =SUM(D41:DT41) -> 3393552 | D41: =IF($E$12="Yes",'Rolled Up Cash Flows'!E$31,'Rolled Up Cash Flows'!E$53) -> 46666.667 | E41: =IF($E$12="Yes",'Rolled Up Cash Flows'!F$31,'Rolled Up Cash Flows'!F$53) -> -3333.3333 | F41: =IF($E$12="Yes",'Rolled Up Cash Flows'!G$31,'Rolled Up Cash Flows'!G$53) -> -3333.3333 | G41: =IF($E$12="Yes",'Rolled Up Cash Flows'!H$31,'Rolled Up Cash Flows'!H$53) -> -3333.3333 | H41: =IF($E$12="Yes",'Rolled Up Cash Flows'!I$31,'Rolled Up Cash Flows'!I$53) -> -3333.3333 | I41: =IF($E$12="Yes",'Rolled Up Cash Flows'!J$31,'Rolled Up Cash Flows'!J$53) -> -3333.3333 | J41: =IF($E$12="Yes",'Rolled Up Cash Flows'!K$31,'Rolled Up Cash Flows'!K$53) -> 6250 | K41: =IF($E$12="Yes",'Rolled Up Cash Flows'!L$31,'Rolled Up Cash Flows'!L$53) -> 6250 | ... DT41: =IF($E$12="Yes",'Rolled Up Cash Flows'!DU$31,'Rolled Up Cash Flows'!DU$53) -> 0
B43: Project 8 | C43: Total | D43: =D13 -> 47026 | E43: =EOMONTH(D43,1) -> 47057 | F43: =EOMONTH(E43,1) -> 47087 | G43: =EOMONTH(F43,1) -> 47118 | H43: =EOMONTH(G43,1) -> 47149 | I43: =EOMONTH(H43,1) -> 47177 | J43: =EOMONTH(I43,1) -> 47208 | K43: =EOMONTH(J43,1) -> 47238 | L43: =EOMONTH(K43,1) -> 47269 | ... DT43: =EOMONTH(DS43,1) -> 50678
B44: Cash Flow | C44: =SUM(D44:DT44) -> 105000 | D44: =IF($E$13="Yes",'Rolled Up Cash Flows'!E$31,'Rolled Up Cash Flows'!E$53) -> 46666.667 | E44: =IF($E$13="Yes",'Rolled Up Cash Flows'!F$31,'Rolled Up Cash Flows'!F$53) -> -3333.3333 | F44: =IF($E$13="Yes",'Rolled Up Cash Flows'!G$31,'Rolled Up Cash Flows'!G$53) -> -3333.3333 | G44: =IF($E$13="Yes",'Rolled Up Cash Flows'!H$31,'Rolled Up Cash Flows'!H$53) -> -3333.3333 | H44: =IF($E$13="Yes",'Rolled Up Cash Flows'!I$31,'Rolled Up Cash Flows'!I$53) -> -3333.3333 | I44: =IF($E$13="Yes",'Rolled Up Cash Flows'!J$31,'Rolled Up Cash Flows'!J$53) -> -3333.3333 | J44: =IF($E$13="Yes",'Rolled Up Cash Flows'!K$31,'Rolled Up Cash Flows'!K$53) -> 6250 | K44: =IF($E$13="Yes",'Rolled Up Cash Flows'!L$31,'Rolled Up Cash Flows'!L$53) -> 6250 | ... DT44: =IF($E$13="Yes",'Rolled Up Cash Flows'!DU$31,'Rolled Up Cash Flows'!DU$53) -> 0
B46: Project 9 | C46: Total | D46: =D14 -> 47118 | E46: =EOMONTH(D46,1) -> 47149 | F46: =EOMONTH(E46,1) -> 47177 | G46: =EOMONTH(F46,1) -> 47208 | H46: =EOMONTH(G46,1) -> 47238 | I46: =EOMONTH(H46,1) -> 47269 | J46: =EOMONTH(I46,1) -> 47299 | K46: =EOMONTH(J46,1) -> 47330 | L46: =EOMONTH(K46,1) -> 47361 | ... DT46: =EOMONTH(DS46,1) -> 50770
B47: Cash Flow | C47: =SUM(D47:DT47) -> 3393552 | D47: =IF($E$14="Yes",'Rolled Up Cash Flows'!E$31,'Rolled Up Cash Flows'!E$53) -> 46666.667 | E47: =IF($E$14="Yes",'Rolled Up Cash Flows'!F$31,'Rolled Up Cash Flows'!F$53) -> -3333.3333 | F47: =IF($E$14="Yes",'Rolled Up Cash Flows'!G$31,'Rolled Up Cash Flows'!G$53) -> -3333.3333 | G47: =IF($E$14="Yes",'Rolled Up Cash Flows'!H$31,'Rolled Up Cash Flows'!H$53) -> -3333.3333 | H47: =IF($E$14="Yes",'Rolled Up Cash Flows'!I$31,'Rolled Up Cash Flows'!I$53) -> -3333.3333 | I47: =IF($E$14="Yes",'Rolled Up Cash Flows'!J$31,'Rolled Up Cash Flows'!J$53) -> -3333.3333 | J47: =IF($E$14="Yes",'Rolled Up Cash Flows'!K$31,'Rolled Up Cash Flows'!K$53) -> 6250 | K47: =IF($E$14="Yes",'Rolled Up Cash Flows'!L$31,'Rolled Up Cash Flows'!L$53) -> 6250 | ... DT47: =IF($E$14="Yes",'Rolled Up Cash Flows'!DU$31,'Rolled Up Cash Flows'!DU$53) -> 0
B49: Project 10 | C49: Total | D49: =D15 -> 47208 | E49: =EOMONTH(D49,1) -> 47238 | F49: =EOMONTH(E49,1) -> 47269 | G49: =EOMONTH(F49,1) -> 47299 | H49: =EOMONTH(G49,1) -> 47330 | I49: =EOMONTH(H49,1) -> 47361 | J49: =EOMONTH(I49,1) -> 47391 | K49: =EOMONTH(J49,1) -> 47422 | L49: =EOMONTH(K49,1) -> 47452 | ... DT49: =EOMONTH(DS49,1) -> 50860
B50: Cash Flow | C50: =SUM(D50:DT50) -> 105000 | D50: =IF($E$15="Yes",'Rolled Up Cash Flows'!E$31,'Rolled Up Cash Flows'!E$53) -> 46666.667 | E50: =IF($E$15="Yes",'Rolled Up Cash Flows'!F$31,'Rolled Up Cash Flows'!F$53) -> -3333.3333 | F50: =IF($E$15="Yes",'Rolled Up Cash Flows'!G$31,'Rolled Up Cash Flows'!G$53) -> -3333.3333 | G50: =IF($E$15="Yes",'Rolled Up Cash Flows'!H$31,'Rolled Up Cash Flows'!H$53) -> -3333.3333 | H50: =IF($E$15="Yes",'Rolled Up Cash Flows'!I$31,'Rolled Up Cash Flows'!I$53) -> -3333.3333 | I50: =IF($E$15="Yes",'Rolled Up Cash Flows'!J$31,'Rolled Up Cash Flows'!J$53) -> -3333.3333 | J50: =IF($E$15="Yes",'Rolled Up Cash Flows'!K$31,'Rolled Up Cash Flows'!K$53) -> 6250 | K50: =IF($E$15="Yes",'Rolled Up Cash Flows'!L$31,'Rolled Up Cash Flows'!L$53) -> 6250 | ... DT50: =IF($E$15="Yes",'Rolled Up Cash Flows'!DU$31,'Rolled Up Cash Flows'!DU$53) -> 0
A72: Yes
A73: No

Sheet The Commons Platform CF
D3: Year | E3: =YEAR(E4) -> 2026 | F3: =YEAR(F4) -> 2027 | G3: =YEAR(G4) -> 2027 | H3: =YEAR(H4) -> 2027 | I3: =YEAR(I4) -> 2027 | J3: =YEAR(J4) -> 2027 | K3: =YEAR(K4) -> 2027 | L3: =YEAR(L4) -> 2027 | ... DU3: =YEAR(DU4) -> 2036
C4: The Commons Platform Cash Flow | D4: Total | E4: ='Single Project Assumptions'!D11 -> 46387 | F4: =EOMONTH(E4,1) -> 46418 | G4: =EOMONTH(F4,1) -> 46446 | H4: =EOMONTH(G4,1) -> 46477 | I4: =EOMONTH(H4,1) -> 46507 | J4: =EOMONTH(I4,1) -> 46538 | K4: =EOMONTH(J4,1) -> 46568 | L4: =EOMONTH(K4,1) -> 46599 | M4: =EOMONTH(L4,1) -> 46630 | ... DU4: =EOMONTH(DT4,1) -> 50040
C6: Project Level Cash Flows
C7: 1 | D7: =SUM(E7:DU7) -> 3393552 | E7: =IF(E$4<'Platform Assumptions'!$D$22,0,HLOOKUP(E$4,'Platform Assumptions'!$D22:$DT23,2,FALSE)) -> 46666.667 | F7: =IF(F$4<'Platform Assumptions'!$D$22,0,HLOOKUP(F$4,'Platform Assumptions'!$D22:$DT23,2,FALSE)) -> -3333.3333 | G7: =IF(G$4<'Platform Assumptions'!$D$22,0,HLOOKUP(G$4,'Platform Assumptions'!$D22:$DT23,2,FALSE)) -> -3333.3333 | H7: =IF(H$4<'Platform Assumptions'!$D$22,0,HLOOKUP(H$4,'Platform Assumptions'!$D22:$DT23,2,FALSE)) -> -3333.3333 | I7: =IF(I$4<'Platform Assumptions'!$D$22,0,HLOOKUP(I$4,'Platform Assumptions'!$D22:$DT23,2,FALSE)) -> -3333.3333 | J7: =IF(J$4<'Platform Assumptions'!$D$22,0,HLOOKUP(J$4,'Platform Assumptions'!$D22:$DT23,2,FALSE)) -> -3333.3333 | K7: =IF(K$4<'Platform Assumptions'!$D$22,0,HLOOKUP(K$4,'Platform Assumptions'!$D22:$DT23,2,FALSE)) -> 6250 | L7: =IF(L$4<'Platform Assumptions'!$D$22,0,HLOOKUP(L$4,'Platform Assumptions'!$D22:$DT23,2,FALSE)) -> 6250 | ... DU7: =IF(DU$4<'Platform Assumptions'!$D$22,0,HLOOKUP(DU$4,'Platform Assumptions'!$D22:$DT23,2,FALSE)) -> 0
C8: =C7+1 -> 2 | D8: =SUM(E8:DU8) -> 105000 | E8: =IF(E$4<'Platform Assumptions'!$D$25,0,HLOOKUP(E$4,'Platform Assumptions'!$D25:$DT26,2,FALSE)) -> 0 | F8: =IF(F$4<'Platform Assumptions'!$D$25,0,HLOOKUP(F$4,'Platform Assumptions'!$D25:$DT26,2,FALSE)) -> 0 | G8: =IF(G$4<'Platform Assumptions'!$D$25,0,HLOOKUP(G$4,'Platform Assumptions'!$D25:$DT26,2,FALSE)) -> 0 | H8: =IF(H$4<'Platform Assumptions'!$D$25,0,HLOOKUP(H$4,'Platform Assumptions'!$D25:$DT26,2,FALSE)) -> 46666.667 | I8: =IF(I$4<'Platform Assumptions'!$D$25,0,HLOOKUP(I$4,'Platform Assumptions'!$D25:$DT26,2,FALSE)) -> -3333.3333 | J8: =IF(J$4<'Platform Assumptions'!$D$25,0,HLOOKUP(J$4,'Platform Assumptions'!$D25:$DT26,2,FALSE)) -> -3333.3333 | K8: =IF(K$4<'Platform Assumptions'!$D$25,0,HLOOKUP(K$4,'Platform Assumptions'!$D25:$DT26,2,FALSE)) -> -3333.3333 | L8: =IF(L$4<'Platform Assumptions'!$D$25,0,HLOOKUP(L$4,'Platform Assumptions'!$D25:$DT26,2,FALSE)) -> -3333.3333 | ... DU8: =IF(DU$4<'Platform Assumptions'!$D$25,0,HLOOKUP(DU$4,'Platform Assumptions'!$D25:$DT26,2,FALSE)) -> 0
C9: =C8+1 -> 3 | D9: =SUM(E9:DU9) -> 3393552 | E9: =IF(E$4<'Platform Assumptions'!$D$28,0,HLOOKUP(E$4,'Platform Assumptions'!$D28:$DT29,2,FALSE)) -> 0 | F9: =IF(F$4<'Platform Assumptions'!$D$28,0,HLOOKUP(F$4,'Platform Assumptions'!$D28:$DT29,2,FALSE)) -> 0 | G9: =IF(G$4<'Platform Assumptions'!$D$28,0,HLOOKUP(G$4,'Platform Assumptions'!$D28:$DT29,2,FALSE)) -> 0 | H9: =IF(H$4<'Platform Assumptions'!$D$28,0,HLOOKUP(H$4,'Platform Assumptions'!$D28:$DT29,2,FALSE)) -> 0 | I9: =IF(I$4<'Platform Assumptions'!$D$28,0,HLOOKUP(I$4,'Platform Assumptions'!$D28:$DT29,2,FALSE)) -> 0 | J9: =IF(J$4<'Platform Assumptions'!$D$28,0,HLOOKUP(J$4,'Platform Assumptions'!$D28:$DT29,2,FALSE)) -> 0 | K9: =IF(K$4<'Platform Assumptions'!$D$28,0,HLOOKUP(K$4,'Platform Assumptions'!$D28:$DT29,2,FALSE)) -> 46666.667 | L9: =IF(L$4<'Platform Assumptions'!$D$28,0,HLOOKUP(L$4,'Platform Assumptions'!$D28:$DT29,2,FALSE)) -> -3333.3333 | ... DU9: =IF(DU$4<'Platform Assumptions'!$D$28,0,HLOOKUP(DU$4,'Platform Assumptions'!$D28:$DT29,2,FALSE)) -> 0
C10: =C9+1 -> 4 | D10: =SUM(E10:DU10) -> 105000 | E10: =IF(E$4<'Platform Assumptions'!$D$31,0,HLOOKUP(E$4,'Platform Assumptions'!$D31:$DT32,2,FALSE)) -> 0 | F10: =IF(F$4<'Platform Assumptions'!$D$31,0,HLOOKUP(F$4,'Platform Assumptions'!$D31:$DT32,2,FALSE)) -> 0 | G10: =IF(G$4<'Platform Assumptions'!$D$31,0,HLOOKUP(G$4,'Platform Assumptions'!$D31:$DT32,2,FALSE)) -> 0 | H10: =IF(H$4<'Platform Assumptions'!$D$31,0,HLOOKUP(H$4,'Platform Assumptions'!$D31:$DT32,2,FALSE)) -> 0 | I10: =IF(I$4<'Platform Assumptions'!$D$31,0,HLOOKUP(I$4,'Platform Assumptions'!$D31:$DT32,2,FALSE)) -> 0 | J10: =IF(J$4<'Platform Assumptions'!$D$31,0,HLOOKUP(J$4,'Platform Assumptions'!$D31:$DT32,2,FALSE)) -> 0 | K10: =IF(K$4<'Platform Assumptions'!$D$31,0,HLOOKUP(K$4,'Platform Assumptions'!$D31:$DT32,2,FALSE)) -> 0 | L10: =IF(L$4<'Platform Assumptions'!$D$31,0,HLOOKUP(L$4,'Platform Assumptions'!$D31:$DT32,2,FALSE)) -> 0 | ... DU10: =IF(DU$4<'Platform Assumptions'!$D$31,0,HLOOKUP(DU$4,'Platform Assumptions'!$D31:$DT32,2,FALSE)) -> 0
C11: =C10+1 -> 5 | D11: =SUM(E11:DU11) -> 3380052 | E11: =IF(E$4<'Platform Assumptions'!$D$34,0,HLOOKUP(E$4,'Platform Assumptions'!$D34:$DT35,2,FALSE)) -> 0 | F11: =IF(F$4<'Platform Assumptions'!$D$34,0,HLOOKUP(F$4,'Platform Assumptions'!$D34:$DT35,2,FALSE)) -> 0 | G11: =IF(G$4<'Platform Assumptions'!$D$34,0,HLOOKUP(G$4,'Platform Assumptions'!$D34:$DT35,2,FALSE)) -> 0 | H11: =IF(H$4<'Platform Assumptions'!$D$34,0,HLOOKUP(H$4,'Platform Assumptions'!$D34:$DT35,2,FALSE)) -> 0 | I11: =IF(I$4<'Platform Assumptions'!$D$34,0,HLOOKUP(I$4,'Platform Assumptions'!$D34:$DT35,2,FALSE)) -> 0 | J11: =IF(J$4<'Platform Assumptions'!$D$34,0,HLOOKUP(J$4,'Platform Assumptions'!$D34:$DT35,2,FALSE)) -> 0 | K11: =IF(K$4<'Platform Assumptions'!$D$34,0,HLOOKUP(K$4,'Platform Assumptions'!$D34:$DT35,2,FALSE)) -> 0 | L11: =IF(L$4<'Platform Assumptions'!$D$34,0,HLOOKUP(L$4,'Platform Assumptions'!$D34:$DT35,2,FALSE)) -> 0 | ... DU11: =IF(DU$4<'Platform Assumptions'!$D$34,0,HLOOKUP(DU$4,'Platform Assumptions'!$D34:$DT35,2,FALSE)) -> 6750
C12: =C11+1 -> 6 | D12: =SUM(E12:DU12) -> 105000 | E12: =IF(E$4<'Platform Assumptions'!$D$37,0,HLOOKUP(E$4,'Platform Assumptions'!$D37:$DT38,2,FALSE)) -> 0 | F12: =IF(F$4<'Platform Assumptions'!$D$37,0,HLOOKUP(F$4,'Platform Assumptions'!$D37:$DT38,2,FALSE)) -> 0 | G12: =IF(G$4<'Platform Assumptions'!$D$37,0,HLOOKUP(G$4,'Platform Assumptions'!$D37:$DT38,2,FALSE)) -> 0 | H12: =IF(H$4<'Platform Assumptions'!$D$37,0,HLOOKUP(H$4,'Platform Assumptions'!$D37:$DT38,2,FALSE)) -> 0 | I12: =IF(I$4<'Platform Assumptions'!$D$37,0,HLOOKUP(I$4,'Platform Assumptions'!$D37:$DT38,2,FALSE)) -> 0 | J12: =IF(J$4<'Platform Assumptions'!$D$37,0,HLOOKUP(J$4,'Platform Assumptions'!$D37:$DT38,2,FALSE)) -> 0 | K12: =IF(K$4<'Platform Assumptions'!$D$37,0,HLOOKUP(K$4,'Platform Assumptions'!$D37:$DT38,2,FALSE)) -> 0 | L12: =IF(L$4<'Platform Assumptions'!$D$37,0,HLOOKUP(L$4,'Platform Assumptions'!$D37:$DT38,2,FALSE)) -> 0 | ... DU12: =IF(DU$4<'Platform Assumptions'!$D$37,0,HLOOKUP(DU$4,'Platform Assumptions'!$D37:$DT38,2,FALSE)) -> 0
C13: =C12+1 -> 7 | D13: =SUM(E13:DU13) -> 3339552 | E13: =IF(E$4<'Platform Assumptions'!$D$40,0,HLOOKUP(E$4,'Platform Assumptions'!$D40:$DT41,2,FALSE)) -> 0 | F13: =IF(F$4<'Platform Assumptions'!$D$40,0,HLOOKUP(F$4,'Platform Assumptions'!$D40:$DT41,2,FALSE)) -> 0 | G13: =IF(G$4<'Platform Assumptions'!$D$40,0,HLOOKUP(G$4,'Platform Assumptions'!$D40:$DT41,2,FALSE)) -> 0 | H13: =IF(H$4<'Platform Assumptions'!$D$40,0,HLOOKUP(H$4,'Platform Assumptions'!$D40:$DT41,2,FALSE)) -> 0 | I13: =IF(I$4<'Platform Assumptions'!$D$40,0,HLOOKUP(I$4,'Platform Assumptions'!$D40:$DT41,2,FALSE)) -> 0 | J13: =IF(J$4<'Platform Assumptions'!$D$40,0,HLOOKUP(J$4,'Platform Assumptions'!$D40:$DT41,2,FALSE)) -> 0 | K13: =IF(K$4<'Platform Assumptions'!$D$40,0,HLOOKUP(K$4,'Platform Assumptions'!$D40:$DT41,2,FALSE)) -> 0 | L13: =IF(L$4<'Platform Assumptions'!$D$40,0,HLOOKUP(L$4,'Platform Assumptions'!$D40:$DT41,2,FALSE)) -> 0 | ... DU13: =IF(DU$4<'Platform Assumptions'!$D$40,0,HLOOKUP(DU$4,'Platform Assumptions'!$D40:$DT41,2,FALSE)) -> 6750
C14: =C13+1 -> 8 | D14: =SUM(E14:DU14) -> 105000 | E14: =IF(E$4<'Platform Assumptions'!$D$43,0,HLOOKUP(E$4,'Platform Assumptions'!$D43:$DT44,2,FALSE)) -> 0 | F14: =IF(F$4<'Platform Assumptions'!$D$43,0,HLOOKUP(F$4,'Platform Assumptions'!$D43:$DT44,2,FALSE)) -> 0 | G14: =IF(G$4<'Platform Assumptions'!$D$43,0,HLOOKUP(G$4,'Platform Assumptions'!$D43:$DT44,2,FALSE)) -> 0 | H14: =IF(H$4<'Platform Assumptions'!$D$43,0,HLOOKUP(H$4,'Platform Assumptions'!$D43:$DT44,2,FALSE)) -> 0 | I14: =IF(I$4<'Platform Assumptions'!$D$43,0,HLOOKUP(I$4,'Platform Assumptions'!$D43:$DT44,2,FALSE)) -> 0 | J14: =IF(J$4<'Platform Assumptions'!$D$43,0,HLOOKUP(J$4,'Platform Assumptions'!$D43:$DT44,2,FALSE)) -> 0 | K14: =IF(K$4<'Platform Assumptions'!$D$43,0,HLOOKUP(K$4,'Platform Assumptions'!$D43:$DT44,2,FALSE)) -> 0 | L14: =IF(L$4<'Platform Assumptions'!$D$43,0,HLOOKUP(L$4,'Platform Assumptions'!$D43:$DT44,2,FALSE)) -> 0 | ... DU14: =IF(DU$4<'Platform Assumptions'!$D$43,0,HLOOKUP(DU$4,'Platform Assumptions'!$D43:$DT44,2,FALSE)) -> 0
C15: =C14+1 -> 9 | D15: =SUM(E15:DU15) -> 3299052 | E15: =IF(E$4<'Platform Assumptions'!$D$46,0,HLOOKUP(E$4,'Platform Assumptions'!$D46:$DT47,2,FALSE)) -> 0 | F15: =IF(F$4<'Platform Assumptions'!$D$46,0,HLOOKUP(F$4,'Platform Assumptions'!$D46:$DT47,2,FALSE)) -> 0 | G15: =IF(G$4<'Platform Assumptions'!$D$46,0,HLOOKUP(G$4,'Platform Assumptions'!$D46:$DT47,2,FALSE)) -> 0 | H15: =IF(H$4<'Platform Assumptions'!$D$46,0,HLOOKUP(H$4,'Platform Assumptions'!$D46:$DT47,2,FALSE)) -> 0 | I15: =IF(I$4<'Platform Assumptions'!$D$46,0,HLOOKUP(I$4,'Platform Assumptions'!$D46:$DT47,2,FALSE)) -> 0 | J15: =IF(J$4<'Platform Assumptions'!$D$46,0,HLOOKUP(J$4,'Platform Assumptions'!$D46:$DT47,2,FALSE)) -> 0 | K15: =IF(K$4<'Platform Assumptions'!$D$46,0,HLOOKUP(K$4,'Platform Assumptions'!$D46:$DT47,2,FALSE)) -> 0 | L15: =IF(L$4<'Platform Assumptions'!$D$46,0,HLOOKUP(L$4,'Platform Assumptions'!$D46:$DT47,2,FALSE)) -> 0 | ... DU15: =IF(DU$4<'Platform Assumptions'!$D$46,0,HLOOKUP(DU$4,'Platform Assumptions'!$D46:$DT47,2,FALSE)) -> 6750
C16: =C15+1 -> 10 | D16: =SUM(E16:DU16) -> 105000 | E16: =IF(E$4<'Platform Assumptions'!$D$49,0,HLOOKUP(E$4,'Platform Assumptions'!$D49:$DT50,2,FALSE)) -> 0 | F16: =IF(F$4<'Platform Assumptions'!$D$49,0,HLOOKUP(F$4,'Platform Assumptions'!$D49:$DT50,2,FALSE)) -> 0 | G16: =IF(G$4<'Platform Assumptions'!$D$49,0,HLOOKUP(G$4,'Platform Assumptions'!$D49:$DT50,2,FALSE)) -> 0 | H16: =IF(H$4<'Platform Assumptions'!$D$49,0,HLOOKUP(H$4,'Platform Assumptions'!$D49:$DT50,2,FALSE)) -> 0 | I16: =IF(I$4<'Platform Assumptions'!$D$49,0,HLOOKUP(I$4,'Platform Assumptions'!$D49:$DT50,2,FALSE)) -> 0 | J16: =IF(J$4<'Platform Assumptions'!$D$49,0,HLOOKUP(J$4,'Platform Assumptions'!$D49:$DT50,2,FALSE)) -> 0 | K16: =IF(K$4<'Platform Assumptions'!$D$49,0,HLOOKUP(K$4,'Platform Assumptions'!$D49:$DT50,2,FALSE)) -> 0 | L16: =IF(L$4<'Platform Assumptions'!$D$49,0,HLOOKUP(L$4,'Platform Assumptions'!$D49:$DT50,2,FALSE)) -> 0 | ... DU16: =IF(DU$4<'Platform Assumptions'!$D$49,0,HLOOKUP(DU$4,'Platform Assumptions'!$D49:$DT50,2,FALSE)) -> 0
C17: Total Project Level Cash Flows | D17: =SUM(E17:DU17) -> 17330760 | E17: =SUM(E7:E16) -> 46666.667 | F17: =SUM(F7:F16) -> -3333.3333 | G17: =SUM(G7:G16) -> -3333.3333 | H17: =SUM(H7:H16) -> 43333.333 | I17: =SUM(I7:I16) -> -6666.6667 | J17: =SUM(J7:J16) -> -6666.6667 | K17: =SUM(K7:K16) -> 49583.333 | L17: =SUM(L7:L16) -> -416.66667 | ... DU17: =SUM(DU7:DU16) -> 20250
C19: Central Overhead Costs | D19: =SUM(E19:DU19) -> -5041666.7 | E19: =-'Platform Assumptions'!$I$7 -> -41666.667 | F19: =-'Platform Assumptions'!$I$7 -> -41666.667 | G19: =-'Platform Assumptions'!$I$7 -> -41666.667 | H19: =-'Platform Assumptions'!$I$7 -> -41666.667 | I19: =-'Platform Assumptions'!$I$7 -> -41666.667 | J19: =-'Platform Assumptions'!$I$7 -> -41666.667 | K19: =-'Platform Assumptions'!$I$7 -> -41666.667 | L19: =-'Platform Assumptions'!$I$7 -> -41666.667 | ... DU19: =-'Platform Assumptions'!$I$7 -> -41666.667
C21: Net Cash Flows | D21: =SUM(E21:DU21) -> 12289093 | E21: =E17+E19 -> 5000 | F21: =F17+F19 -> -45000 | G21: =G17+G19 -> -45000 | H21: =H17+H19 -> 1666.6667 | I21: =I17+I19 -> -48333.333 | J21: =J17+J19 -> -48333.333 | K21: =K17+K19 -> 7916.6667 | L21: =L17+L19 -> -42083.333 | ... DU21: =DU17+DU19 -> -21416.667
E23: =+E21 -> 5000 | F23: =+F21+E23 -> -40000 | G23: =+G21+F23 -> -85000 | H23: =+H21+G23 -> -83333.333 | I23: =+I21+H23 -> -131666.67 | J23: =+J21+I23 -> -180000 | K23: =+K21+J23 -> -172083.33 | L23: =+L21+K23 -> -214166.67 | M23: =+M21+L23 -> -256250 | ... DU23: =+DU21+DT23 -> 12289093

Sheet Single Project Cash Flows--->
M4: Description
M5: This model sets out the economics for a single “Commons” project and illustrates how a multi-stakeholder development can be structured without The Commons owning land or funding construction. The project follows a four-stage process designed to align landowners, entitlement capital, developers and future residents.
M9: 1 - Option Phase: The Commons enters into an option agreement with a farmer, allowing the land to remain in agricultural use while the project is explored. The farmer continues to earn farming income during this period. The Commons’ role is to articulate the vision, align incentives, and secure an Entitlement Investor to take the project forward.
M13: 2 - Entitlement Phase: The Entitlement Investor funds and manages the planning and entitlement process. Importantly, they do not acquire the land upfront and do not pay a traditional option fee. Instead, their economic upside is back-ended and capped, realised through the uplift in land value once entitlements are secured. This limits capital at risk while preserving strong returns if successful.
M17: 3 - Development Phase: Following successful entitlement, a developer steps in and pays out the Entitlement Investor. The residual uplift in land value (net of this payment) is contributed as equity by the landowner and The Commons. The developer funds construction, sells the homes, and earns a development return. The Commons and the landowner receive capital formation and delivery fees to ensure alignment and oversight during build-out.
M21: 4 - Operations Phase: Once occupied, residents pay three transparent, ongoing charges: (i) a stewardship fee to The Commons, (ii) service charges covering shared operating costs, and (iii) a land payment to the landowner. These payments support long-term community management and provide the landowner with a stable, inflation-linked income that materially exceeds traditional agricultural yields.

Sheet Single Project Assumptions
B3: TIMING ASSUMPTIONS
B5: Model Timing | F5: Key
B6: Model Start Date | D6: 46387 | F6: INPUTS
B7: Exit Date | D7: =T13 -> 49765 | F7: OUTPUTS
B8: Hold Period (years) | D8: =YEARFRAC(D6,D7) -> 9.25
B10: Land Option | F10: Entitlement Phase | J10: Development Phase | N10: Residential Sales | R10: Operational Phase
B11: Option Date | D11: =D6 -> 46387 | F11: Entitement Investor Step In Date | H11: =D15 -> 46568 | J11: Developer Step In Date | L11: =H15 -> 47118 | N11: Months to Sales Start (from const. start) | P11: 18 | R11: Operational Start Date | T11: =L15 -> 47938
B12: Option Duration (months) | D12: 18 | F12: Entltlement Period | H12: 12 | J12: Months to Development Start | L12: 3 | N12: Sales Start Date | P12: =EOMONTH(L13,P11) -> 47756 | R12: Hold Period | T12: 60
B13: Option Expiration Date | D13: =EOMONTH(D11,D12) -> 46934 | F13: Entitlements Obtained | H13: =EOMONTH(H11,H12) -> 46934 | J13: Development Start Date | L13: =EOMONTH(L11,L12) -> 47208 | N13: Sell Out Months | P13: 18 | R13: Exit Date | T13: =EOMONTH(T11,T12) -> 49765
B14: Months to Engage Entitlement Investor | D14: 6 | F14: Months to Engage Developer | H14: 6 | J14: Development Period | L14: 24 | N14: Sales End Date | P14: =EOMONTH(P12,P13) -> 48304
B15: Entitlement Investor Step In Date | D15: =EOMONTH(D11,D14) -> 46568 | F15: Developer Step In / Entitlement Exit | H15: =EOMONTH(H13,H14) -> 47118 | J15: Development Completion Date | L15: =EOMONTH(L13,L14) -> 47938 | N15: Sales Velocity (units / month) | P15: =D21/P13 -> 8.3333333
B17: PROJECT AND COST ASSUMPTIONS
B19: Residential Units and Areas | F19: Entitlement Costs | J19: Developer Costs | N19: Ownership Split at Development
B20: Land Area (acres) | D20: 50 | F20: Entitlment Costs / Unit | H20: 25000 | J20: Land Entry Value | L20: =H39-H41 -> 1875000 | N20: Land (Farmer) | P20: =((L20+L22)/L31)*Q20 -> 0.0059649741 | Q20: 0.5
B21: Number of Units | D21: 150 | F21: Total Entitlement Costs | H21: =H20*D21 -> 3750000 | J21: Acquisition Costs % | L21: 0.015 | N21: Land (The Commons) | P21: =P20/Q20*Q21 -> 0.0059649741 | Q21: =1-Q20 -> 0.5
B22: Average Unit Size sq ft | D22: 2500 | J22: Acquisition Costs | L22: =L20*L21 -> 28125 | N22: Construction (Developer) | P22: =1-P20-P21 -> 0.98807005
B23: Total Residential Area sq ft | D23: =D21*D22 -> 375000 | J23: Infrastructure / Unit | L23: 100000 | N23: Total Ownership | P23: =SUM(P20:P22) -> 1
J24: Hard Costs / Unit | L24: 750000
B25: Amenities | J25: Soft Costs % | L25: 0.15
B26: Amenity Area sq ft | D26: 50000 | J26: Soft Costs | L26: =L25*SUM(L23:L24) -> 127500 | N26: Sales Costs
J27: Contingency % | L27: 0.075 | N27: Marketing % of GDV | P27: 0.01
B28: The Commons Controlled / Management | J28: Contingency | L28: =L27*(SUM(L26,L24,L23)) -> 73312.5 | N28: Marketing Costs | P28: =P27*L38 -> 2250000
B29: Total Area sq ft | D29: 10000 | J29: Total Costs Per Unit | L29: =SUM(L23,L24,L26,L28) -> 1050812.5 | N29: Agents Fees % of GDV | P29: 0.04
J30: Total Development Costs | L30: =L29*D21 -> 157621875 | N30: Agents Fees | P30: =P29*L38 -> 9000000
J31: All-In Cost Basis | L31: =L20+L22+L30 -> 159525000
J32: All-In Costs Basis / Unit | L32: =L31/D21 -> 1063500
B34: PRIICNG AND OPERATING ASSUMPTIONS
B36: Day 1 Land Value | F36: Entitled Land Value | J36: Residential Sales Prices
B37: Land Area (acres) | D37: =D20 -> 50 | F37: Land Area (acres) | H37: =D37 -> 50 | J37: Average Sale Price / Unit | L37: 1500000
B38: Day 1 Value / Acre | D38: 20000 | F38: Entitled Land Value / Acre | H38: 150000 | J38: Total Reidential Sales | L38: =L37*D21 -> 225000000
B39: Day 1 Land Value | D39: =D37*D38 -> 1000000 | F39: Entitled Land Value | H39: =H37*H38 -> 7500000 | J39: Sale Price / sq ft | L39: =L38/D23 -> 600
F40: Entitlement Investor Equity Multiple | H40: 1.5 | J40: Sales Velocity (units / month) | L40: =P15 -> 8.3333333
F41: Entitlement Investor Implied Exit Value | H41: =H40*H21 -> 5625000 | J41: Deposit % | L41: 0.15
F42: Sales Costs | H42: 0.01 | J42: Deposit / Unit | L42: =L41*L37 -> 225000
B45: FEE ASSUMPTIONS AND ECONOMICS
B47: Farmer Economics | F47: The Commons Fees - Options and Entitlement | J47: The Commons Fees - Development | N47: The Commons Fees - Operational | R47: Service Charges
B48: Day 1 Land Value | D48: =D39 -> 1000000 | F48: Option Stage Fees | J48: Development Stage Fees | N48: Operational Stage Fees | R48: Operational Stage Service Charges
B49: Crop Yield | D49: 0.02 | F49: Land Access / Structuring Fee | H49: 50000 | J49: Capital Formation (% GDV) | L49: 0.01 | N49: Operating Fee (per unit per month) | P49: 150 | R49: Service Charges (per unit per month) | T49: 200
B50: Crop Yield Income | D50: =D48*D49 -> 20000 | F50: Date Paid | H50: =D11 -> 46387 | J50: Capital Formation Fee | L50: =L49*L38 -> 2250000 | N50: Operating Fee (per unit per year) | P50: =P49*12 -> 1800 | R50: Service Charges (per unit per year) | T50: =T49*12 -> 2400
B51: Target Yield At Stabilizaton | D51: 0.15 | F51: Costs to Secure Entitlement Investor | H51: 20000 | J51: Date Paid | L51: =L11 -> 47118 | N51: Operating Fee per month | P51: =P49*D21 -> 22500 | R51: Service Charges per month | T51: =T49*D21 -> 30000
B52: Target income At Stabilization | D52: =D51*D39 -> 150000 | F52: Cost Start Date | H52: =D11 -> 46387 | J52: The Commons Share | L52: 0.6 | N52: Operating Fee per year | P52: =P51*12 -> 270000 | R52: Service Charges Per year | T52: =T51*12 -> 360000
B53: Per Unit / Year | D53: =D52/D21 -> 1000 | F53: Cost End Date | H53: =D15 -> 46568 | J53: Landowner Share | L53: =1-L52 -> 0.4 | N53: Fee Pay Start | P53: =T11 -> 47938 | R53: Fee Pay Start | T53: =T11 -> 47938
B54: Per Unit / Month | D54: =D53/12 -> 83.333333 | F54: Months | H54: =D14 -> 6 | N54: Fee Pay End | P54: =T13 -> 49765 | R54: Fee Pay End | T54: =T13 -> 49765
B55: vs Crop Yield | D55: =(D52-D50)/D50 -> 6.5 | J55: Delivery Fee (% of dev costs) | L55: 0.0025
B56: Fee Pay Start | D56: =T11 -> 47938 | F56: Entitlement Stage Fees | J56: Delivery Fee | L56: =L55*L30 -> 394054.69 | N56: EBITDA Margin Assumed | P56: 0.3 | R56: EBITDA Margin Assumed | T56: 0
B57: Fee Pay End | D57: =T13 -> 49765 | F57: Entitlement Fee (% of entitled land value) | H57: 0.01 | J57: Fee Pay Start | L57: =L13 -> 47208 | N57: EBITDA | P57: =P52*P56 -> 81000 | R57: EBITDA | T57: =T52*T56 -> 0
F58: Entitlement Fee Total | H58: =H57*H39 -> 75000 | J58: Fee Pay End | L58: =L15 -> 47938 | N58: Implied Operating Costs | P58: =P52-P57 -> 189000 | R58: Implied Operating Costs | T58: =T52-T57 -> 360000
F59: Fee Pay Start | H59: =H11 -> 46568 | J59: The Commons Share | L59: 0.6 | N59: Fee Pay Start | P59: =P53 -> 47938 | R59: Fee Pay Start | T59: =T53 -> 47938
F60: Fee Pay End | H60: =H13 -> 46934 | J60: Landowner Share | L60: =1-L59 -> 0.4 | N60: Fee Pay End | P60: =P54 -> 49765 | R60: Fee Pay End | T60: =T54 -> 49765
F61: Success Fee (% of entitled land value) | H61: 0.005
F62: Success Fee Total | H62: =H61*H39 -> 37500
F63: Date Paid | H63: =H13 -> 46934

Sheet Rolled Up Cash Flows
D3: Year | E3: =YEAR(E4) -> 2026 | F3: =YEAR(F4) -> 2027 | G3: =YEAR(G4) -> 2027 | H3: =YEAR(H4) -> 2027 | I3: =YEAR(I4) -> 2027 | J3: =YEAR(J4) -> 2027 | K3: =YEAR(K4) -> 2027 | L3: =YEAR(L4) -> 2027 | ... DU3: =YEAR(DU4) -> 2036
C4: Rolled Up Cash Flows Per Stakeholder | D4: Total | E4: ='Single Project Assumptions'!D11 -> 46387 | F4: =EOMONTH(E4,1) -> 46418 | G4: =EOMONTH(F4,1) -> 46446 | H4: =EOMONTH(G4,1) -> 46477 | I4: =EOMONTH(H4,1) -> 46507 | J4: =EOMONTH(I4,1) -> 46538 | K4: =EOMONTH(J4,1) -> 46568 | L4: =EOMONTH(K4,1) -> 46599 | M4: =EOMONTH(L4,1) -> 46630 | ... DU4: =EOMONTH(DT4,1) -> 50040
C6: Landowner Cash Flows
C7: Day 1 Land Value | D7: =SUM(E7:DU7) -> -1000000 | E7: =IF(E$4='Single Project Assumptions'!$D$11,-'Single Project Assumptions'!$D$48,0) -> -1000000 | F7: =IF(F$4='Single Project Assumptions'!$D$11,-'Single Project Assumptions'!$D$48,0) -> 0 | G7: =IF(G$4='Single Project Assumptions'!$D$11,-'Single Project Assumptions'!$D$48,0) -> 0 | H7: =IF(H$4='Single Project Assumptions'!$D$11,-'Single Project Assumptions'!$D$48,0) -> 0 | I7: =IF(I$4='Single Project Assumptions'!$D$11,-'Single Project Assumptions'!$D$48,0) -> 0 | J7: =IF(J$4='Single Project Assumptions'!$D$11,-'Single Project Assumptions'!$D$48,0) -> 0 | K7: =IF(K$4='Single Project Assumptions'!$D$11,-'Single Project Assumptions'!$D$48,0) -> 0 | L7: =IF(L$4='Single Project Assumptions'!$D$11,-'Single Project Assumptions'!$D$48,0) -> 0 | ... DU7: =IF(DU$4='Single Project Assumptions'!$D$11,-'Single Project Assumptions'!$D$48,0) -> 0
C8: Option Phase - Farming Yield | D8: =SUM(E8:DU8) -> 10000 | E8: ='Option Phase'!E7 -> 1666.6667 | F8: ='Option Phase'!F7 -> 1666.6667 | G8: ='Option Phase'!G7 -> 1666.6667 | H8: ='Option Phase'!H7 -> 1666.6667 | I8: ='Option Phase'!I7 -> 1666.6667 | J8: ='Option Phase'!J7 -> 1666.6667 | K8: ='Option Phase'!K7 -> 0 | L8: ='Option Phase'!L7 -> 0 | ... DU8: ='Option Phase'!DU7 -> 0
C9: Option Phase - Option Payment | D9: =SUM(E9:DU9) -> -50000 | E9: ='Option Phase'!E8 -> -50000 | F9: ='Option Phase'!F8 -> 0 | G9: ='Option Phase'!G8 -> 0 | H9: ='Option Phase'!H8 -> 0 | I9: ='Option Phase'!I8 -> 0 | J9: ='Option Phase'!J8 -> 0 | K9: ='Option Phase'!K8 -> 0 | L9: ='Option Phase'!L8 -> 0 | ... DU9: ='Option Phase'!DU8 -> 0
C10: Entitlement Phase - Farming Yield | D10: =SUM(E10:DU10) -> 20000 | E10: ='Entitlement Phase'!E18 -> 0 | F10: ='Entitlement Phase'!F18 -> 0 | G10: ='Entitlement Phase'!G18 -> 0 | H10: ='Entitlement Phase'!H18 -> 0 | I10: ='Entitlement Phase'!I18 -> 0 | J10: ='Entitlement Phase'!J18 -> 0 | K10: ='Entitlement Phase'!K18 -> 1666.6667 | L10: ='Entitlement Phase'!L18 -> 1666.6667 | ... DU10: ='Entitlement Phase'!DU18 -> 0
C11: Development Phase - Capital Formation Fees | D11: =SUM(E11:DU11) -> 900000 | E11: ='Development Phase'!E37 -> 0 | F11: ='Development Phase'!F37 -> 0 | G11: ='Development Phase'!G37 -> 0 | H11: ='Development Phase'!H37 -> 0 | I11: ='Development Phase'!I37 -> 0 | J11: ='Development Phase'!J37 -> 0 | K11: ='Development Phase'!K37 -> 0 | L11: ='Development Phase'!L37 -> 0 | ... DU11: ='Development Phase'!DU37 -> 0
C12: Development Phase - Delivery Fees | D12: =SUM(E12:DU12) -> 157621.88 | E12: ='Development Phase'!E41 -> 0 | F12: ='Development Phase'!F41 -> 0 | G12: ='Development Phase'!G41 -> 0 | H12: ='Development Phase'!H41 -> 0 | I12: ='Development Phase'!I41 -> 0 | J12: ='Development Phase'!J41 -> 0 | K12: ='Development Phase'!K41 -> 0 | L12: ='Development Phase'!L41 -> 0 | ... DU12: ='Development Phase'!DU41 -> 0
C13: Development Phase - Equity Participation | D13: =SUM(E13:DU13) -> 1342119.2 | E13: ='Development Phase'!E33 -> 0 | F13: ='Development Phase'!F33 -> 0 | G13: ='Development Phase'!G33 -> 0 | H13: ='Development Phase'!H33 -> 0 | I13: ='Development Phase'!I33 -> 0 | J13: ='Development Phase'!J33 -> 0 | K13: ='Development Phase'!K33 -> 0 | L13: ='Development Phase'!L33 -> 0 | ... DU13: ='Development Phase'!DU33 -> 0
C14: Operational Phase - Stewardship Fees | D14: =SUM(E14:DU14) -> 704166.67 | E14: ='Operational Phase'!E27 -> 0 | F14: ='Operational Phase'!F27 -> 0 | G14: ='Operational Phase'!G27 -> 0 | H14: ='Operational Phase'!H27 -> 0 | I14: ='Operational Phase'!I27 -> 0 | J14: ='Operational Phase'!J27 -> 0 | K14: ='Operational Phase'!K27 -> 0 | L14: ='Operational Phase'!L27 -> 0 | ... DU14: ='Operational Phase'!DU27 -> 0
C15: Total Landowner Cash Flows | D15: =SUM(E15:DU15) -> 2083907.7 | E15: =SUM(E7:E14) -> -1048333.3 | F15: =SUM(F7:F14) -> 1666.6667 | G15: =SUM(G7:G14) -> 1666.6667 | H15: =SUM(H7:H14) -> 1666.6667 | I15: =SUM(I7:I14) -> 1666.6667 | J15: =SUM(J7:J14) -> 1666.6667 | K15: =SUM(K7:K14) -> 1666.6667 | L15: =SUM(L7:L14) -> 1666.6667 | ... DU15: =SUM(DU7:DU14) -> 0
C16: Annualized Yield on Day 1 Land Value | D16: =AVERAGE(E16:DU16) -> 0.072809917 | E16: =F16 -> 0.02 | F16: =(SUM(F8,F10,F14)*12)/-$D$7 -> 0.02 | G16: =(SUM(G8,G10,G14)*12)/-$D$7 -> 0.02 | H16: =(SUM(H8,H10,H14)*12)/-$D$7 -> 0.02 | I16: =(SUM(I8,I10,I14)*12)/-$D$7 -> 0.02 | J16: =(SUM(J8,J10,J14)*12)/-$D$7 -> 0.02 | K16: =(SUM(K8,K10,K14)*12)/-$D$7 -> 0.02 | L16: =(SUM(L8,L10,L14)*12)/-$D$7 -> 0.02 | M16: =(SUM(M8,M10,M14)*12)/-$D$7 -> 0.02 | ... DU16: =(SUM(DU8,DU10,DU14)*12)/-$D$7 -> 0
C17: Peak Equity | D17: =-MIN(E17:DU17) -> 1048333.3 | E17: =E15 -> -1048333.3 | F17: =F15+E17 -> -1046666.7 | G17: =G15+F17 -> -1045000 | H17: =H15+G17 -> -1043333.3 | I17: =I15+H17 -> -1041666.7 | J17: =J15+I17 -> -1040000 | K17: =K15+J17 -> -1038333.3 | L17: =L15+K17 -> -1036666.7 | M17: =M15+L17 -> -1035000 | ... DU17: =DU15+DT17 -> 2083907.7
C18: IRR | D18: =XIRR(E15:DU15,E4:DU4,0.1) -> 0.33907558
C19: Equity Multiple | D19: =D15/D17+1 -> 2.9878293
C21: The Commons Cash Flows
C22: Option Phase - Option Payment | D22: =SUM(E22:DU22) -> 50000 | E22: ='Option Phase'!E12 -> 50000 | F22: ='Option Phase'!F12 -> 0 | G22: ='Option Phase'!G12 -> 0 | H22: ='Option Phase'!H12 -> 0 | I22: ='Option Phase'!I12 -> 0 | J22: ='Option Phase'!J12 -> 0 | K22: ='Option Phase'!K12 -> 0 | L22: ='Option Phase'!L12 -> 0 | ... DU22: ='Option Phase'!DU12 -> 0
C23: Option Phase - Costs to Secure Entitlement Investor | D23: =SUM(E23:DU23) -> -20000 | E23: ='Option Phase'!E13 -> -3333.3333 | F23: ='Option Phase'!F13 -> -3333.3333 | G23: ='Option Phase'!G13 -> -3333.3333 | H23: ='Option Phase'!H13 -> -3333.3333 | I23: ='Option Phase'!I13 -> -3333.3333 | J23: ='Option Phase'!J13 -> -3333.3333 | K23: ='Option Phase'!K13 -> 0 | L23: ='Option Phase'!L13 -> 0 | ... DU23: ='Option Phase'!DU13 -> 0
C24: Entitlement Phase - Entitlement Fee | D24: =SUM(E24:DU24) -> 75000 | E24: =-'Entitlement Phase'!E7 -> 0 | F24: =-'Entitlement Phase'!F7 -> 0 | G24: =-'Entitlement Phase'!G7 -> 0 | H24: =-'Entitlement Phase'!H7 -> 0 | I24: =-'Entitlement Phase'!I7 -> 0 | J24: =-'Entitlement Phase'!J7 -> 0 | K24: =-'Entitlement Phase'!K7 -> 6250 | L24: =-'Entitlement Phase'!L7 -> 6250 | ... DU24: =-'Entitlement Phase'!DU7 -> 0
C25: Entitlement Phase - Entitlement Success Fee | D25: =SUM(E25:DU25) -> 37500 | E25: =-'Entitlement Phase'!E8 -> 0 | F25: =-'Entitlement Phase'!F8 -> 0 | G25: =-'Entitlement Phase'!G8 -> 0 | H25: =-'Entitlement Phase'!H8 -> 0 | I25: =-'Entitlement Phase'!I8 -> 0 | J25: =-'Entitlement Phase'!J8 -> 0 | K25: =-'Entitlement Phase'!K8 -> 0 | L25: =-'Entitlement Phase'!L8 -> 0 | ... DU25: =-'Entitlement Phase'!DU8 -> 0
C26: Development Phase - Capital Formation Fee | D26: =SUM(E26:DU26) -> 1350000 | E26: ='Development Phase'!E38 -> 0 | F26: ='Development Phase'!F38 -> 0 | G26: ='Development Phase'!G38 -> 0 | H26: ='Development Phase'!H38 -> 0 | I26: ='Development Phase'!I38 -> 0 | J26: ='Development Phase'!J38 -> 0 | K26: ='Development Phase'!K38 -> 0 | L26: ='Development Phase'!L38 -> 0 | ... DU26: ='Development Phase'!DU38 -> 0
C27: Development Phase - Delivery Fee | D27: =SUM(E27:DU27) -> 236432.81 | E27: ='Development Phase'!E42 -> 0 | F27: ='Development Phase'!F42 -> 0 | G27: ='Development Phase'!G42 -> 0 | H27: ='Development Phase'!H42 -> 0 | I27: ='Development Phase'!I42 -> 0 | J27: ='Development Phase'!J42 -> 0 | K27: ='Development Phase'!K42 -> 0 | L27: ='Development Phase'!L42 -> 0 | ... DU27: ='Development Phase'!DU42 -> 0
C28: Development Phase - Equity Participation | D28: =SUM(E28:DU28) -> 1342119.2 | E28: ='Development Phase'!E34 -> 0 | F28: ='Development Phase'!F34 -> 0 | G28: ='Development Phase'!G34 -> 0 | H28: ='Development Phase'!H34 -> 0 | I28: ='Development Phase'!I34 -> 0 | J28: ='Development Phase'!J34 -> 0 | K28: ='Development Phase'!K34 -> 0 | L28: ='Development Phase'!L34 -> 0 | ... DU28: ='Development Phase'!DU34 -> 0
C29: Operational Phase - Operations Fees | D29: =SUM(E29:DU29) -> 1267500 | E29: ='Operational Phase'!E15 -> 0 | F29: ='Operational Phase'!F15 -> 0 | G29: ='Operational Phase'!G15 -> 0 | H29: ='Operational Phase'!H15 -> 0 | I29: ='Operational Phase'!I15 -> 0 | J29: ='Operational Phase'!J15 -> 0 | K29: ='Operational Phase'!K15 -> 0 | L29: ='Operational Phase'!L15 -> 0 | ... DU29: ='Operational Phase'!DU15 -> 0
C30: Operational Phase - Operations Costs | D30: =SUM(E30:DU30) -> -945000 | E30: ='Operational Phase'!E16 -> 0 | F30: ='Operational Phase'!F16 -> 0 | G30: ='Operational Phase'!G16 -> 0 | H30: ='Operational Phase'!H16 -> 0 | I30: ='Operational Phase'!I16 -> 0 | J30: ='Operational Phase'!J16 -> 0 | K30: ='Operational Phase'!K16 -> 0 | L30: ='Operational Phase'!L16 -> 0 | ... DU30: ='Operational Phase'!DU16 -> 0
B31: c | C31: The Commons Cash Flows | D31: =SUM(E31:DU31) -> 3393552 | E31: =SUM(E22:E30) -> 46666.667 | F31: =SUM(F22:F30) -> -3333.3333 | G31: =SUM(G22:G30) -> -3333.3333 | H31: =SUM(H22:H30) -> -3333.3333 | I31: =SUM(I22:I30) -> -3333.3333 | J31: =SUM(J22:J30) -> -3333.3333 | K31: =SUM(K22:K30) -> 6250 | L31: =SUM(L22:L30) -> 6250 | ... DU31: =SUM(DU22:DU30) -> 0
C32: Peak Equity | D32: =-MIN(E32:DU32) -> -30000 | E32: =E31 -> 46666.667 | F32: =F31+E32 -> 43333.333 | G32: =G31+F32 -> 40000 | H32: =H31+G32 -> 36666.667 | I32: =I31+H32 -> 33333.333 | J32: =J31+I32 -> 30000 | K32: =K31+J32 -> 36250 | L32: =L31+K32 -> 42500 | M32: =M31+L32 -> 48750 | ... DU32: =DU31+DT32 -> 3393552
C33: IRR | D33: na
C34: Equity Multiple | D34: na
C36: Entitlement Investor Cash Flow
C37: Entitlement Investor Net Cash Flow | D37: =SUM(E37:DU37) -> 1706250 | E37: ='Entitlement Phase'!E11 -> 0 | F37: ='Entitlement Phase'!F11 -> 0 | G37: ='Entitlement Phase'!G11 -> 0 | H37: ='Entitlement Phase'!H11 -> 0 | I37: ='Entitlement Phase'!I11 -> 0 | J37: ='Entitlement Phase'!J11 -> 0 | K37: ='Entitlement Phase'!K11 -> -318750 | L37: ='Entitlement Phase'!L11 -> -318750 | ... DU37: ='Entitlement Phase'!DU11 -> 0
C38: Peak Equity | D38: =-MIN(E38:DU38) -> 3862500 | E38: =E37 -> 0 | F38: =F37+E38 -> 0 | G38: =G37+F38 -> 0 | H38: =H37+G38 -> 0 | I38: =I37+H38 -> 0 | J38: =J37+I38 -> 0 | K38: =K37+J38 -> -318750 | L38: =L37+K38 -> -637500 | M38: =M37+L38 -> -956250 | ... DU38: =DU37+DT38 -> 1706250
C39: IRR | D39: ='Entitlement Phase'!D13 -> 0.41443852
C40: Equity Multiple | D40: ='Entitlement Phase'!D14 -> 1.4417476
C42: Development Investor Cash Flow
C43: Developer Net Cash Flow | D43: =SUM(E43:DU43) -> 56340457 | E43: ='Development Phase'!E27 -> 0 | F43: ='Development Phase'!F27 -> 0 | G43: ='Development Phase'!G27 -> 0 | H43: ='Development Phase'!H27 -> 0 | I43: ='Development Phase'!I27 -> 0 | J43: ='Development Phase'!J27 -> 0 | K43: ='Development Phase'!K27 -> 0 | L43: ='Development Phase'!L27 -> 0 | ... DU43: ='Development Phase'!DU27 -> 0
C44: Peak Equity | D44: =-MIN(E44:DU44) -> 1.5485952e+08 | E44: =E43 -> 0 | F44: =F43+E44 -> 0 | G44: =G43+F44 -> 0 | H44: =H43+G44 -> 0 | I44: =I43+H44 -> 0 | J44: =J43+I44 -> 0 | K44: =K43+J44 -> 0 | L44: =L43+K44 -> 0 | M44: =M43+L44 -> 0 | ... DU44: =DU43+DT44 -> 56340457
C45: IRR | D45: ='Development Phase'!D29 -> 0.22888162
C46: Equity Multiple | D46: ='Development Phase'!D30 -> 1.3638166
C49: The Commons - Abortive Project Cash Flow
C50: Option Phase - Option Payment | D50: =SUM(E50:DU50) -> 50000 | E50: =E22 -> 50000 | F50: =F22 -> 0 | G50: =G22 -> 0 | H50: =H22 -> 0 | I50: =I22 -> 0 | J50: =J22 -> 0 | K50: =K22 -> 0 | L50: =L22 -> 0 | ... DU50: =DU22 -> 0
C51: Option Phase - Costs to Secure Entitlement Investor | D51: =SUM(E51:DU51) -> -20000 | E51: =E23 -> -3333.3333 | F51: =F23 -> -3333.3333 | G51: =G23 -> -3333.3333 | H51: =H23 -> -3333.3333 | I51: =I23 -> -3333.3333 | J51: =J23 -> -3333.3333 | K51: =K23 -> 0 | L51: =L23 -> 0 | ... DU51: =DU23 -> 0
C52: Entitlement Phase - Entitlement Fee | D52: =SUM(E52:DU52) -> 75000 | E52: =E24 -> 0 | F52: =F24 -> 0 | G52: =G24 -> 0 | H52: =H24 -> 0 | I52: =I24 -> 0 | J52: =J24 -> 0 | K52: =K24 -> 6250 | L52: =L24 -> 6250 | ... DU52: =DU24 -> 0
C53: The Commons Cash Flows | D53: =SUM(E53:DU53) -> 105000 | E53: =SUM(E50:E52) -> 46666.667 | F53: =SUM(F50:F52) -> -3333.3333 | G53: =SUM(G50:G52) -> -3333.3333 | H53: =SUM(H50:H52) -> -3333.3333 | I53: =SUM(I50:I52) -> -3333.3333 | J53: =SUM(J50:J52) -> -3333.3333 | K53: =SUM(K50:K52) -> 6250 | L53: =SUM(L50:L52) -> 6250 | ... DU53: =SUM(DU50:DU52) -> 0

Sheet Option Phase
D3: Year | E3: =YEAR(E4) -> 2026 | F3: =YEAR(F4) -> 2027 | G3: =YEAR(G4) -> 2027 | H3: =YEAR(H4) -> 2027 | I3: =YEAR(I4) -> 2027 | J3: =YEAR(J4) -> 2027 | K3: =YEAR(K4) -> 2027 | L3: =YEAR(L4) -> 2027 | ... DU3: =YEAR(DU4) -> 2036
C4: Option Phase Cash Flow | D4: Total | E4: ='Single Project Assumptions'!D11 -> 46387 | F4: =EOMONTH(E4,1) -> 46418 | G4: =EOMONTH(F4,1) -> 46446 | H4: =EOMONTH(G4,1) -> 46477 | I4: =EOMONTH(H4,1) -> 46507 | J4: =EOMONTH(I4,1) -> 46538 | K4: =EOMONTH(J4,1) -> 46568 | L4: =EOMONTH(K4,1) -> 46599 | M4: =EOMONTH(L4,1) -> 46630 | ... DU4: =EOMONTH(DT4,1) -> 50040
C6: Landonwer
C7: Landower (Farming Land) | D7: =SUM(E7:DU7) -> 10000 | E7: =IF(AND(E$4>='Single Project Assumptions'!$D$11,'Option Phase'!E$4<'Single Project Assumptions'!$D$15),'Single Project Assumptions'!$D$50/12,0) -> 1666.6667 | F7: =IF(AND(F$4>='Single Project Assumptions'!$D$11,'Option Phase'!F$4<'Single Project Assumptions'!$D$15),'Single Project Assumptions'!$D$50/12,0) -> 1666.6667 | G7: =IF(AND(G$4>='Single Project Assumptions'!$D$11,'Option Phase'!G$4<'Single Project Assumptions'!$D$15),'Single Project Assumptions'!$D$50/12,0) -> 1666.6667 | H7: =IF(AND(H$4>='Single Project Assumptions'!$D$11,'Option Phase'!H$4<'Single Project Assumptions'!$D$15),'Single Project Assumptions'!$D$50/12,0) -> 1666.6667 | I7: =IF(AND(I$4>='Single Project Assumptions'!$D$11,'Option Phase'!I$4<'Single Project Assumptions'!$D$15),'Single Project Assumptions'!$D$50/12,0) -> 1666.6667 | J7: =IF(AND(J$4>='Single Project Assumptions'!$D$11,'Option Phase'!J$4<'Single Project Assumptions'!$D$15),'Single Project Assumptions'!$D$50/12,0) -> 1666.6667 | K7: =IF(AND(K$4>='Single Project Assumptions'!$D$11,'Option Phase'!K$4<'Single Project Assumptions'!$D$15),'Single Project Assumptions'!$D$50/12,0) -> 0 | L7: =IF(AND(L$4>='Single Project Assumptions'!$D$11,'Option Phase'!L$4<'Single Project Assumptions'!$D$15),'Single Project Assumptions'!$D$50/12,0) -> 0 | ... DU7: =IF(AND(DU$4>='Single Project Assumptions'!$D$11,'Option Phase'!DU$4<'Single Project Assumptions'!$D$15),'Single Project Assumptions'!$D$50/12,0) -> 0
C8: Option Payment (The Commons) | D8: =SUM(E8:DU8) -> -50000 | E8: =IF(E$4='Single Project Assumptions'!$H$50,-'Single Project Assumptions'!$H$49,0) -> -50000 | F8: =IF(F$4='Single Project Assumptions'!$H$50,-'Single Project Assumptions'!$H$49,0) -> 0 | G8: =IF(G$4='Single Project Assumptions'!$H$50,-'Single Project Assumptions'!$H$49,0) -> 0 | H8: =IF(H$4='Single Project Assumptions'!$H$50,-'Single Project Assumptions'!$H$49,0) -> 0 | I8: =IF(I$4='Single Project Assumptions'!$H$50,-'Single Project Assumptions'!$H$49,0) -> 0 | J8: =IF(J$4='Single Project Assumptions'!$H$50,-'Single Project Assumptions'!$H$49,0) -> 0 | K8: =IF(K$4='Single Project Assumptions'!$H$50,-'Single Project Assumptions'!$H$49,0) -> 0 | L8: =IF(L$4='Single Project Assumptions'!$H$50,-'Single Project Assumptions'!$H$49,0) -> 0 | ... DU8: =IF(DU$4='Single Project Assumptions'!$H$50,-'Single Project Assumptions'!$H$49,0) -> 0
C9: Landowner Net Cash Flow | D9: =SUM(E9:DU9) -> -40000 | E9: =SUM(E7:E8) -> -48333.333 | F9: =SUM(F7:F8) -> 1666.6667 | G9: =SUM(G7:G8) -> 1666.6667 | H9: =SUM(H7:H8) -> 1666.6667 | I9: =SUM(I7:I8) -> 1666.6667 | J9: =SUM(J7:J8) -> 1666.6667 | K9: =SUM(K7:K8) -> 0 | L9: =SUM(L7:L8) -> 0 | ... DU9: =SUM(DU7:DU8) -> 0
C11: The Commons
C12: Option Payment (The Commons) | D12: =SUM(E12:DU12) -> 50000 | E12: =-E8 -> 50000 | F12: =-F8 -> 0 | G12: =-G8 -> 0 | H12: =-H8 -> 0 | I12: =-I8 -> 0 | J12: =-J8 -> 0 | K12: =-K8 -> 0 | L12: =-L8 -> 0 | ... DU12: =-DU8 -> 0
C13: Costs to Secure Entitlement Investor | D13: =SUM(E13:DU13) -> -20000 | E13: =IF(AND(E$4>='Single Project Assumptions'!$H$52,'Option Phase'!E$4<'Single Project Assumptions'!$H$53),-'Single Project Assumptions'!$H$51/'Single Project Assumptions'!$H$54,0) -> -3333.3333 | F13: =IF(AND(F$4>='Single Project Assumptions'!$H$52,'Option Phase'!F$4<'Single Project Assumptions'!$H$53),-'Single Project Assumptions'!$H$51/'Single Project Assumptions'!$H$54,0) -> -3333.3333 | G13: =IF(AND(G$4>='Single Project Assumptions'!$H$52,'Option Phase'!G$4<'Single Project Assumptions'!$H$53),-'Single Project Assumptions'!$H$51/'Single Project Assumptions'!$H$54,0) -> -3333.3333 | H13: =IF(AND(H$4>='Single Project Assumptions'!$H$52,'Option Phase'!H$4<'Single Project Assumptions'!$H$53),-'Single Project Assumptions'!$H$51/'Single Project Assumptions'!$H$54,0) -> -3333.3333 | I13: =IF(AND(I$4>='Single Project Assumptions'!$H$52,'Option Phase'!I$4<'Single Project Assumptions'!$H$53),-'Single Project Assumptions'!$H$51/'Single Project Assumptions'!$H$54,0) -> -3333.3333 | J13: =IF(AND(J$4>='Single Project Assumptions'!$H$52,'Option Phase'!J$4<'Single Project Assumptions'!$H$53),-'Single Project Assumptions'!$H$51/'Single Project Assumptions'!$H$54,0) -> -3333.3333 | K13: =IF(AND(K$4>='Single Project Assumptions'!$H$52,'Option Phase'!K$4<'Single Project Assumptions'!$H$53),-'Single Project Assumptions'!$H$51/'Single Project Assumptions'!$H$54,0) -> 0 | L13: =IF(AND(L$4>='Single Project Assumptions'!$H$52,'Option Phase'!L$4<'Single Project Assumptions'!$H$53),-'Single Project Assumptions'!$H$51/'Single Project Assumptions'!$H$54,0) -> 0 | ... DU13: =IF(AND(DU$4>='Single Project Assumptions'!$H$52,'Option Phase'!DU$4<'Single Project Assumptions'!$H$53),-'Single Project Assumptions'!$H$51/'Single Project Assumptions'!$H$54,0) -> 0
C14: The Commons Net Cash Flow | D14: =SUM(E14:DU14) -> 30000 | E14: =SUM(E12:E13) -> 46666.667 | F14: =SUM(F12:F13) -> -3333.3333 | G14: =SUM(G12:G13) -> -3333.3333 | H14: =SUM(H12:H13) -> -3333.3333 | I14: =SUM(I12:I13) -> -3333.3333 | J14: =SUM(J12:J13) -> -3333.3333 | K14: =SUM(K12:K13) -> 0 | L14: =SUM(L12:L13) -> 0 | ... DU14: =SUM(DU12:DU13) -> 0

Sheet Entitlement Phase
D2: Flag | E2: =IF(E4='Single Project Assumptions'!$H$11,1,0) -> 0 | F2: =IF(F4='Single Project Assumptions'!$H$11,1,0) -> 0 | G2: =IF(G4='Single Project Assumptions'!$H$11,1,0) -> 0 | H2: =IF(H4='Single Project Assumptions'!$H$11,1,0) -> 0 | I2: =IF(I4='Single Project Assumptions'!$H$11,1,0) -> 0 | J2: =IF(J4='Single Project Assumptions'!$H$11,1,0) -> 0 | K2: =IF(K4='Single Project Assumptions'!$H$11,1,0) -> 1 | L2: =IF(L4='Single Project Assumptions'!$H$11,1,0) -> 0 | ... DU2: =IF(DU4='Single Project Assumptions'!$H$11,1,0) -> 0
D3: Year | E3: =YEAR(E4) -> 2026 | F3: =YEAR(F4) -> 2027 | G3: =YEAR(G4) -> 2027 | H3: =YEAR(H4) -> 2027 | I3: =YEAR(I4) -> 2027 | J3: =YEAR(J4) -> 2027 | K3: =YEAR(K4) -> 2027 | L3: =YEAR(L4) -> 2027 | ... DU3: =YEAR(DU4) -> 2036
C4: Entitlement Phase Cash Flow | D4: Total | E4: ='Single Project Assumptions'!D6 -> 46387 | F4: =EOMONTH(E4,1) -> 46418 | G4: =EOMONTH(F4,1) -> 46446 | H4: =EOMONTH(G4,1) -> 46477 | I4: =EOMONTH(H4,1) -> 46507 | J4: =EOMONTH(I4,1) -> 46538 | K4: =EOMONTH(J4,1) -> 46568 | L4: =EOMONTH(K4,1) -> 46599 | M4: =EOMONTH(L4,1) -> 46630 | ... DU4: =EOMONTH(DT4,1) -> 50040
C6: Entitlement Costs | D6: =SUM(E6:DU6) -> -3750000 | E6: =-IF(AND(E$4>='Single Project Assumptions'!$H$11,'Entitlement Phase'!E$4<'Single Project Assumptions'!$H$13),('Single Project Assumptions'!$H$21/'Single Project Assumptions'!$H$12),0) -> 0 | F6: =-IF(AND(F$4>='Single Project Assumptions'!$H$11,'Entitlement Phase'!F$4<'Single Project Assumptions'!$H$13),('Single Project Assumptions'!$H$21/'Single Project Assumptions'!$H$12),0) -> 0 | G6: =-IF(AND(G$4>='Single Project Assumptions'!$H$11,'Entitlement Phase'!G$4<'Single Project Assumptions'!$H$13),('Single Project Assumptions'!$H$21/'Single Project Assumptions'!$H$12),0) -> 0 | H6: =-IF(AND(H$4>='Single Project Assumptions'!$H$11,'Entitlement Phase'!H$4<'Single Project Assumptions'!$H$13),('Single Project Assumptions'!$H$21/'Single Project Assumptions'!$H$12),0) -> 0 | I6: =-IF(AND(I$4>='Single Project Assumptions'!$H$11,'Entitlement Phase'!I$4<'Single Project Assumptions'!$H$13),('Single Project Assumptions'!$H$21/'Single Project Assumptions'!$H$12),0) -> 0 | J6: =-IF(AND(J$4>='Single Project Assumptions'!$H$11,'Entitlement Phase'!J$4<'Single Project Assumptions'!$H$13),('Single Project Assumptions'!$H$21/'Single Project Assumptions'!$H$12),0) -> 0 | K6: =-IF(AND(K$4>='Single Project Assumptions'!$H$11,'Entitlement Phase'!K$4<'Single Project Assumptions'!$H$13),('Single Project Assumptions'!$H$21/'Single Project Assumptions'!$H$12),0) -> -312500 | L6: =-IF(AND(L$4>='Single Project Assumptions'!$H$11,'Entitlement Phase'!L$4<'Single Project Assumptions'!$H$13),('Single Project Assumptions'!$H$21/'Single Project Assumptions'!$H$12),0) -> -312500 | ... DU6: =-IF(AND(DU$4>='Single Project Assumptions'!$H$11,'Entitlement Phase'!DU$4<'Single Project Assumptions'!$H$13),('Single Project Assumptions'!$H$21/'Single Project Assumptions'!$H$12),0) -> 0
C7: Entitlement Fees (The Commons) | D7: =SUM(E7:DU7) -> -75000 | E7: =IF(AND(E$4>='Single Project Assumptions'!$H$59,'Entitlement Phase'!E$4<'Single Project Assumptions'!$H$60),(-'Single Project Assumptions'!$H$58)/'Single Project Assumptions'!$H$12,0) -> 0 | F7: =IF(AND(F$4>='Single Project Assumptions'!$H$59,'Entitlement Phase'!F$4<'Single Project Assumptions'!$H$60),(-'Single Project Assumptions'!$H$58)/'Single Project Assumptions'!$H$12,0) -> 0 | G7: =IF(AND(G$4>='Single Project Assumptions'!$H$59,'Entitlement Phase'!G$4<'Single Project Assumptions'!$H$60),(-'Single Project Assumptions'!$H$58)/'Single Project Assumptions'!$H$12,0) -> 0 | H7: =IF(AND(H$4>='Single Project Assumptions'!$H$59,'Entitlement Phase'!H$4<'Single Project Assumptions'!$H$60),(-'Single Project Assumptions'!$H$58)/'Single Project Assumptions'!$H$12,0) -> 0 | I7: =IF(AND(I$4>='Single Project Assumptions'!$H$59,'Entitlement Phase'!I$4<'Single Project Assumptions'!$H$60),(-'Single Project Assumptions'!$H$58)/'Single Project Assumptions'!$H$12,0) -> 0 | J7: =IF(AND(J$4>='Single Project Assumptions'!$H$59,'Entitlement Phase'!J$4<'Single Project Assumptions'!$H$60),(-'Single Project Assumptions'!$H$58)/'Single Project Assumptions'!$H$12,0) -> 0 | K7: =IF(AND(K$4>='Single Project Assumptions'!$H$59,'Entitlement Phase'!K$4<'Single Project Assumptions'!$H$60),(-'Single Project Assumptions'!$H$58)/'Single Project Assumptions'!$H$12,0) -> -6250 | L7: =IF(AND(L$4>='Single Project Assumptions'!$H$59,'Entitlement Phase'!L$4<'Single Project Assumptions'!$H$60),(-'Single Project Assumptions'!$H$58)/'Single Project Assumptions'!$H$12,0) -> -6250 | ... DU7: =IF(AND(DU$4>='Single Project Assumptions'!$H$59,'Entitlement Phase'!DU$4<'Single Project Assumptions'!$H$60),(-'Single Project Assumptions'!$H$58)/'Single Project Assumptions'!$H$12,0) -> 0
C8: Entitlement Success Fee (The Commons) | D8: =SUM(E8:DU8) -> -37500 | E8: =IF(E$4='Single Project Assumptions'!$H$63,-'Single Project Assumptions'!$H$62,0) -> 0 | F8: =IF(F$4='Single Project Assumptions'!$H$63,-'Single Project Assumptions'!$H$62,0) -> 0 | G8: =IF(G$4='Single Project Assumptions'!$H$63,-'Single Project Assumptions'!$H$62,0) -> 0 | H8: =IF(H$4='Single Project Assumptions'!$H$63,-'Single Project Assumptions'!$H$62,0) -> 0 | I8: =IF(I$4='Single Project Assumptions'!$H$63,-'Single Project Assumptions'!$H$62,0) -> 0 | J8: =IF(J$4='Single Project Assumptions'!$H$63,-'Single Project Assumptions'!$H$62,0) -> 0 | K8: =IF(K$4='Single Project Assumptions'!$H$63,-'Single Project Assumptions'!$H$62,0) -> 0 | L8: =IF(L$4='Single Project Assumptions'!$H$63,-'Single Project Assumptions'!$H$62,0) -> 0 | ... DU8: =IF(DU$4='Single Project Assumptions'!$H$63,-'Single Project Assumptions'!$H$62,0) -> 0
C9: Sale Value | D9: =SUM(E9:DU9) -> 5625000 | E9: =IF(E$4='Single Project Assumptions'!$H$15,'Single Project Assumptions'!$H$41,0) -> 0 | F9: =IF(F$4='Single Project Assumptions'!$H$15,'Single Project Assumptions'!$H$41,0) -> 0 | G9: =IF(G$4='Single Project Assumptions'!$H$15,'Single Project Assumptions'!$H$41,0) -> 0 | H9: =IF(H$4='Single Project Assumptions'!$H$15,'Single Project Assumptions'!$H$41,0) -> 0 | I9: =IF(I$4='Single Project Assumptions'!$H$15,'Single Project Assumptions'!$H$41,0) -> 0 | J9: =IF(J$4='Single Project Assumptions'!$H$15,'Single Project Assumptions'!$H$41,0) -> 0 | K9: =IF(K$4='Single Project Assumptions'!$H$15,'Single Project Assumptions'!$H$41,0) -> 0 | L9: =IF(L$4='Single Project Assumptions'!$H$15,'Single Project Assumptions'!$H$41,0) -> 0 | ... DU9: =IF(DU$4='Single Project Assumptions'!$H$15,'Single Project Assumptions'!$H$41,0) -> 0
C10: Sale Costs | D10: =SUM(E10:DU10) -> -56250 | E10: =-E9*'Single Project Assumptions'!$H$42 -> 0 | F10: =-F9*'Single Project Assumptions'!$H$42 -> 0 | G10: =-G9*'Single Project Assumptions'!$H$42 -> 0 | H10: =-H9*'Single Project Assumptions'!$H$42 -> 0 | I10: =-I9*'Single Project Assumptions'!$H$42 -> 0 | J10: =-J9*'Single Project Assumptions'!$H$42 -> 0 | K10: =-K9*'Single Project Assumptions'!$H$42 -> 0 | L10: =-L9*'Single Project Assumptions'!$H$42 -> 0 | ... DU10: =-DU9*'Single Project Assumptions'!$H$42 -> 0
C11: Entitlement Investor Cash Flow | D11: =SUM(E11:DU11) -> 1706250 | E11: =SUM(E6:E10) -> 0 | F11: =SUM(F6:F10) -> 0 | G11: =SUM(G6:G10) -> 0 | H11: =SUM(H6:H10) -> 0 | I11: =SUM(I6:I10) -> 0 | J11: =SUM(J6:J10) -> 0 | K11: =SUM(K6:K10) -> -318750 | L11: =SUM(L6:L10) -> -318750 | ... DU11: =SUM(DU6:DU10) -> 0
C12: Peak Equity | D12: =-MIN(E12:DU12) -> 3862500 | E12: =E11 -> 0 | F12: =E12+F11 -> 0 | G12: =F12+G11 -> 0 | H12: =G12+H11 -> 0 | I12: =H12+I11 -> 0 | J12: =I12+J11 -> 0 | K12: =J12+K11 -> -318750 | L12: =K12+L11 -> -637500 | M12: =L12+M11 -> -956250 | ... DU12: =DT12+DU11 -> 1706250
C13: IRR | D13: =HLOOKUP(1,$E$2:$DU$13,12,FALSE) -> 0.41443852 | E13: =XIRR(E11:$DU$11,E4:$DU$4,0.1) -> 2.9802322e-09 | F13: =XIRR(F11:$DU$11,F4:$DU$4,0.1) -> 2.9802322e-09 | G13: =XIRR(G11:$DU$11,G4:$DU$4,0.1) -> 2.9802322e-09 | H13: =XIRR(H11:$DU$11,H4:$DU$4,0.1) -> 2.9802322e-09 | I13: =XIRR(I11:$DU$11,I4:$DU$4,0.1) -> 2.9802322e-09 | J13: =XIRR(J11:$DU$11,J4:$DU$4,0.1) -> 2.9802322e-09 | K13: =XIRR(K11:$DU$11,K4:$DU$4,0.1) -> 0.41443852 | L13: =XIRR(L11:$DU$11,L4:$DU$4,0.1) -> 0.56141154 | ... DU13: =XIRR(DU11:$DU$11,DU4:$DU$4,0.1) -> #N/A
C14: Equity Multiple | D14: =D11/D12+1 -> 1.4417476
C16: The Commons Fees Total | D16: =SUM(E16:DU16) -> 112500 | E16: =-E7-E8 -> 0 | F16: =-F7-F8 -> 0 | G16: =-G7-G8 -> 0 | H16: =-H7-H8 -> 0 | I16: =-I7-I8 -> 0 | J16: =-J7-J8 -> 0 | K16: =-K7-K8 -> 6250 | L16: =-L7-L8 -> 6250 | ... DU16: =-DU7-DU8 -> 0
C18: Landowner (Farming Land) | D18: =SUM(E18:DU18) -> 20000 | E18: =IF(AND(E$4>='Single Project Assumptions'!$H$11,'Entitlement Phase'!E$4<'Single Project Assumptions'!$H$13),'Single Project Assumptions'!$D$50/12,0) -> 0 | F18: =IF(AND(F$4>='Single Project Assumptions'!$H$11,'Entitlement Phase'!F$4<'Single Project Assumptions'!$H$13),'Single Project Assumptions'!$D$50/12,0) -> 0 | G18: =IF(AND(G$4>='Single Project Assumptions'!$H$11,'Entitlement Phase'!G$4<'Single Project Assumptions'!$H$13),'Single Project Assumptions'!$D$50/12,0) -> 0 | H18: =IF(AND(H$4>='Single Project Assumptions'!$H$11,'Entitlement Phase'!H$4<'Single Project Assumptions'!$H$13),'Single Project Assumptions'!$D$50/12,0) -> 0 | I18: =IF(AND(I$4>='Single Project Assumptions'!$H$11,'Entitlement Phase'!I$4<'Single Project Assumptions'!$H$13),'Single Project Assumptions'!$D$50/12,0) -> 0 | J18: =IF(AND(J$4>='Single Project Assumptions'!$H$11,'Entitlement Phase'!J$4<'Single Project Assumptions'!$H$13),'Single Project Assumptions'!$D$50/12,0) -> 0 | K18: =IF(AND(K$4>='Single Project Assumptions'!$H$11,'Entitlement Phase'!K$4<'Single Project Assumptions'!$H$13),'Single Project Assumptions'!$D$50/12,0) -> 1666.6667 | L18: =IF(AND(L$4>='Single Project Assumptions'!$H$11,'Entitlement Phase'!L$4<'Single Project Assumptions'!$H$13),'Single Project Assumptions'!$D$50/12,0) -> 1666.6667 | ... DU18: =IF(AND(DU$4>='Single Project Assumptions'!$H$11,'Entitlement Phase'!DU$4<'Single Project Assumptions'!$H$13),'Single Project Assumptions'!$D$50/12,0) -> 0
C19: Yield on Original Land Value (annualized) | D19: =MAX(E19:DU19) -> 0.02 | E19: =(E18*12)/'Single Project Assumptions'!$D$39 -> 0 | F19: =(F18*12)/'Single Project Assumptions'!$D$39 -> 0 | G19: =(G18*12)/'Single Project Assumptions'!$D$39 -> 0 | H19: =(H18*12)/'Single Project Assumptions'!$D$39 -> 0 | I19: =(I18*12)/'Single Project Assumptions'!$D$39 -> 0 | J19: =(J18*12)/'Single Project Assumptions'!$D$39 -> 0 | K19: =(K18*12)/'Single Project Assumptions'!$D$39 -> 0.02 | L19: =(L18*12)/'Single Project Assumptions'!$D$39 -> 0.02 | ... DU19: =(DU18*12)/'Single Project Assumptions'!$D$39 -> 0

Sheet Development Phase
D2: Flag | E2: =IF(E4='Single Project Assumptions'!$L$11,1,0) -> 0 | F2: =IF(F4='Single Project Assumptions'!$L$11,1,0) -> 0 | G2: =IF(G4='Single Project Assumptions'!$L$11,1,0) -> 0 | H2: =IF(H4='Single Project Assumptions'!$L$11,1,0) -> 0 | I2: =IF(I4='Single Project Assumptions'!$L$11,1,0) -> 0 | J2: =IF(J4='Single Project Assumptions'!$L$11,1,0) -> 0 | K2: =IF(K4='Single Project Assumptions'!$L$11,1,0) -> 0 | L2: =IF(L4='Single Project Assumptions'!$L$11,1,0) -> 0 | ... DU2: =IF(DU4='Single Project Assumptions'!$L$11,1,0) -> 0
D3: Year | E3: =YEAR(E4) -> 2026 | F3: =YEAR(F4) -> 2027 | G3: =YEAR(G4) -> 2027 | H3: =YEAR(H4) -> 2027 | I3: =YEAR(I4) -> 2027 | J3: =YEAR(J4) -> 2027 | K3: =YEAR(K4) -> 2027 | L3: =YEAR(L4) -> 2027 | ... DU3: =YEAR(DU4) -> 2036
C4: Development Phase Cash Flow | D4: Total | E4: ='Single Project Assumptions'!D6 -> 46387 | F4: =EOMONTH(E4,1) -> 46418 | G4: =EOMONTH(F4,1) -> 46446 | H4: =EOMONTH(G4,1) -> 46477 | I4: =EOMONTH(H4,1) -> 46507 | J4: =EOMONTH(I4,1) -> 46538 | K4: =EOMONTH(J4,1) -> 46568 | L4: =EOMONTH(K4,1) -> 46599 | M4: =EOMONTH(L4,1) -> 46630 | ... DU4: =EOMONTH(DT4,1) -> 50040
C6: Units Sold Opening Balance | E6: 0 | F6: =E9 -> 0 | G6: =F9 -> 0 | H6: =G9 -> 0 | I6: =H9 -> 0 | J6: =I9 -> 0 | K6: =J9 -> 0 | L6: =K9 -> 0 | M6: =L9 -> 0 | ... DU6: =DT9 -> 0
C7: Unit Sales | D7: =SUM(E7:DU7) -> 150 | E7: =IF(AND(E$4>='Single Project Assumptions'!$P$12,'Development Phase'!E$4<'Single Project Assumptions'!$P$14),'Single Project Assumptions'!$P$15,0) -> 0 | F7: =IF(AND(F$4>='Single Project Assumptions'!$P$12,'Development Phase'!F$4<'Single Project Assumptions'!$P$14),'Single Project Assumptions'!$P$15,0) -> 0 | G7: =IF(AND(G$4>='Single Project Assumptions'!$P$12,'Development Phase'!G$4<'Single Project Assumptions'!$P$14),'Single Project Assumptions'!$P$15,0) -> 0 | H7: =IF(AND(H$4>='Single Project Assumptions'!$P$12,'Development Phase'!H$4<'Single Project Assumptions'!$P$14),'Single Project Assumptions'!$P$15,0) -> 0 | I7: =IF(AND(I$4>='Single Project Assumptions'!$P$12,'Development Phase'!I$4<'Single Project Assumptions'!$P$14),'Single Project Assumptions'!$P$15,0) -> 0 | J7: =IF(AND(J$4>='Single Project Assumptions'!$P$12,'Development Phase'!J$4<'Single Project Assumptions'!$P$14),'Single Project Assumptions'!$P$15,0) -> 0 | K7: =IF(AND(K$4>='Single Project Assumptions'!$P$12,'Development Phase'!K$4<'Single Project Assumptions'!$P$14),'Single Project Assumptions'!$P$15,0) -> 0 | L7: =IF(AND(L$4>='Single Project Assumptions'!$P$12,'Development Phase'!L$4<'Single Project Assumptions'!$P$14),'Single Project Assumptions'!$P$15,0) -> 0 | ... DU7: =IF(AND(DU$4>='Single Project Assumptions'!$P$12,'Development Phase'!DU$4<'Single Project Assumptions'!$P$14),'Single Project Assumptions'!$P$15,0) -> 0
C8: Unit Closings | D8: =SUM(E8:DU8) -> -150 | E8: =IF(E$4<'Single Project Assumptions'!$L$15,0,-SUM('Development Phase'!E6:E7)) -> 0 | F8: =IF(F$4<'Single Project Assumptions'!$L$15,0,-SUM('Development Phase'!F6:F7)) -> 0 | G8: =IF(G$4<'Single Project Assumptions'!$L$15,0,-SUM('Development Phase'!G6:G7)) -> 0 | H8: =IF(H$4<'Single Project Assumptions'!$L$15,0,-SUM('Development Phase'!H6:H7)) -> 0 | I8: =IF(I$4<'Single Project Assumptions'!$L$15,0,-SUM('Development Phase'!I6:I7)) -> 0 | J8: =IF(J$4<'Single Project Assumptions'!$L$15,0,-SUM('Development Phase'!J6:J7)) -> 0 | K8: =IF(K$4<'Single Project Assumptions'!$L$15,0,-SUM('Development Phase'!K6:K7)) -> 0 | L8: =IF(L$4<'Single Project Assumptions'!$L$15,0,-SUM('Development Phase'!L6:L7)) -> 0 | ... DU8: =IF(DU$4<'Single Project Assumptions'!$L$15,0,-SUM('Development Phase'!DU6:DU7)) -> 0
C9: Units Sold Closing Balance | E9: =SUM(E6:E8) -> 0 | F9: =SUM(F6:F8) -> 0 | G9: =SUM(G6:G8) -> 0 | H9: =SUM(H6:H8) -> 0 | I9: =SUM(I6:I8) -> 0 | J9: =SUM(J6:J8) -> 0 | K9: =SUM(K6:K8) -> 0 | L9: =SUM(L6:L8) -> 0 | ... DU9: =SUM(DU6:DU8) -> 0
C11: Residential Sales - Deposit Payments | D11: =SUM(E11:DU11) -> 33750000 | E11: =E7*'Single Project Assumptions'!$L$42 -> 0 | F11: =F7*'Single Project Assumptions'!$L$42 -> 0 | G11: =G7*'Single Project Assumptions'!$L$42 -> 0 | H11: =H7*'Single Project Assumptions'!$L$42 -> 0 | I11: =I7*'Single Project Assumptions'!$L$42 -> 0 | J11: =J7*'Single Project Assumptions'!$L$42 -> 0 | K11: =K7*'Single Project Assumptions'!$L$42 -> 0 | L11: =L7*'Single Project Assumptions'!$L$42 -> 0 | ... DU11: =DU7*'Single Project Assumptions'!$L$42 -> 0
C12: Residential Sales - Closing Payments | D12: =SUM(E12:DU12) -> 191250000 | E12: =-E8*('Single Project Assumptions'!$L$37-'Single Project Assumptions'!$L$42) -> 0 | F12: =-F8*('Single Project Assumptions'!$L$37-'Single Project Assumptions'!$L$42) -> 0 | G12: =-G8*('Single Project Assumptions'!$L$37-'Single Project Assumptions'!$L$42) -> 0 | H12: =-H8*('Single Project Assumptions'!$L$37-'Single Project Assumptions'!$L$42) -> 0 | I12: =-I8*('Single Project Assumptions'!$L$37-'Single Project Assumptions'!$L$42) -> 0 | J12: =-J8*('Single Project Assumptions'!$L$37-'Single Project Assumptions'!$L$42) -> 0 | K12: =-K8*('Single Project Assumptions'!$L$37-'Single Project Assumptions'!$L$42) -> 0 | L12: =-L8*('Single Project Assumptions'!$L$37-'Single Project Assumptions'!$L$42) -> 0 | ... DU12: =-DU8*('Single Project Assumptions'!$L$37-'Single Project Assumptions'!$L$42) -> 0
C13: Residential Sales - Total | D13: =SUM(E13:DU13) -> 225000000 | E13: =SUM(E11:E12) -> 0 | F13: =SUM(F11:F12) -> 0 | G13: =SUM(G11:G12) -> 0 | H13: =SUM(H11:H12) -> 0 | I13: =SUM(I11:I12) -> 0 | J13: =SUM(J11:J12) -> 0 | K13: =SUM(K11:K12) -> 0 | L13: =SUM(L11:L12) -> 0 | ... DU13: =SUM(DU11:DU12) -> 0
C15: Land Acquisiton | D15: =SUM(E15:DU15) -> -5625000 | E15: =-IF(E$4='Single Project Assumptions'!$L$11,'Single Project Assumptions'!$H$41,0) -> 0 | F15: =-IF(F$4='Single Project Assumptions'!$L$11,'Single Project Assumptions'!$H$41,0) -> 0 | G15: =-IF(G$4='Single Project Assumptions'!$L$11,'Single Project Assumptions'!$H$41,0) -> 0 | H15: =-IF(H$4='Single Project Assumptions'!$L$11,'Single Project Assumptions'!$H$41,0) -> 0 | I15: =-IF(I$4='Single Project Assumptions'!$L$11,'Single Project Assumptions'!$H$41,0) -> 0 | J15: =-IF(J$4='Single Project Assumptions'!$L$11,'Single Project Assumptions'!$H$41,0) -> 0 | K15: =-IF(K$4='Single Project Assumptions'!$L$11,'Single Project Assumptions'!$H$41,0) -> 0 | L15: =-IF(L$4='Single Project Assumptions'!$L$11,'Single Project Assumptions'!$H$41,0) -> 0 | ... DU15: =-IF(DU$4='Single Project Assumptions'!$L$11,'Single Project Assumptions'!$H$41,0) -> 0
C16: Acquisition Costs | D16: =SUM(E16:DU16) -> -84375 | E16: =E15*'Single Project Assumptions'!$L$21 -> 0 | F16: =F15*'Single Project Assumptions'!$L$21 -> 0 | G16: =G15*'Single Project Assumptions'!$L$21 -> 0 | H16: =H15*'Single Project Assumptions'!$L$21 -> 0 | I16: =I15*'Single Project Assumptions'!$L$21 -> 0 | J16: =J15*'Single Project Assumptions'!$L$21 -> 0 | K16: =K15*'Single Project Assumptions'!$L$21 -> 0 | L16: =L15*'Single Project Assumptions'!$L$21 -> 0 | ... DU16: =DU15*'Single Project Assumptions'!$L$21 -> 0
C17: Development Costs | D17: =SUM(E17:DU17) -> -157621875 | E17: =IF(AND(E$4>='Single Project Assumptions'!$L$13,'Development Phase'!E$4<'Single Project Assumptions'!$L$15),-'Single Project Assumptions'!$L$30/'Single Project Assumptions'!$L$14,0) -> 0 | F17: =IF(AND(F$4>='Single Project Assumptions'!$L$13,'Development Phase'!F$4<'Single Project Assumptions'!$L$15),-'Single Project Assumptions'!$L$30/'Single Project Assumptions'!$L$14,0) -> 0 | G17: =IF(AND(G$4>='Single Project Assumptions'!$L$13,'Development Phase'!G$4<'Single Project Assumptions'!$L$15),-'Single Project Assumptions'!$L$30/'Single Project Assumptions'!$L$14,0) -> 0 | H17: =IF(AND(H$4>='Single Project Assumptions'!$L$13,'Development Phase'!H$4<'Single Project Assumptions'!$L$15),-'Single Project Assumptions'!$L$30/'Single Project Assumptions'!$L$14,0) -> 0 | I17: =IF(AND(I$4>='Single Project Assumptions'!$L$13,'Development Phase'!I$4<'Single Project Assumptions'!$L$15),-'Single Project Assumptions'!$L$30/'Single Project Assumptions'!$L$14,0) -> 0 | J17: =IF(AND(J$4>='Single Project Assumptions'!$L$13,'Development Phase'!J$4<'Single Project Assumptions'!$L$15),-'Single Project Assumptions'!$L$30/'Single Project Assumptions'!$L$14,0) -> 0 | K17: =IF(AND(K$4>='Single Project Assumptions'!$L$13,'Development Phase'!K$4<'Single Project Assumptions'!$L$15),-'Single Project Assumptions'!$L$30/'Single Project Assumptions'!$L$14,0) -> 0 | L17: =IF(AND(L$4>='Single Project Assumptions'!$L$13,'Development Phase'!L$4<'Single Project Assumptions'!$L$15),-'Single Project Assumptions'!$L$30/'Single Project Assumptions'!$L$14,0) -> 0 | ... DU17: =IF(AND(DU$4>='Single Project Assumptions'!$L$13,'Development Phase'!DU$4<'Single Project Assumptions'!$L$15),-'Single Project Assumptions'!$L$30/'Single Project Assumptions'!$L$14,0) -> 0
C18: Capital Formation (The Commons) | D18: =SUM(E18:DU18) -> -2250000 | E18: =IF(E$4='Single Project Assumptions'!$L$51,-'Single Project Assumptions'!$L$50,0) -> 0 | F18: =IF(F$4='Single Project Assumptions'!$L$51,-'Single Project Assumptions'!$L$50,0) -> 0 | G18: =IF(G$4='Single Project Assumptions'!$L$51,-'Single Project Assumptions'!$L$50,0) -> 0 | H18: =IF(H$4='Single Project Assumptions'!$L$51,-'Single Project Assumptions'!$L$50,0) -> 0 | I18: =IF(I$4='Single Project Assumptions'!$L$51,-'Single Project Assumptions'!$L$50,0) -> 0 | J18: =IF(J$4='Single Project Assumptions'!$L$51,-'Single Project Assumptions'!$L$50,0) -> 0 | K18: =IF(K$4='Single Project Assumptions'!$L$51,-'Single Project Assumptions'!$L$50,0) -> 0 | L18: =IF(L$4='Single Project Assumptions'!$L$51,-'Single Project Assumptions'!$L$50,0) -> 0 | ... DU18: =IF(DU$4='Single Project Assumptions'!$L$51,-'Single Project Assumptions'!$L$50,0) -> 0
C19: Delivery Fee (The Commons) | D19: =SUM(E19:DU19) -> -394054.69 | E19: =IF(AND(E$4>='Single Project Assumptions'!$L$57,'Development Phase'!E$4<'Single Project Assumptions'!$L$58),(-'Single Project Assumptions'!$L$56/'Single Project Assumptions'!$L$14),0) -> 0 | F19: =IF(AND(F$4>='Single Project Assumptions'!$L$57,'Development Phase'!F$4<'Single Project Assumptions'!$L$58),(-'Single Project Assumptions'!$L$56/'Single Project Assumptions'!$L$14),0) -> 0 | G19: =IF(AND(G$4>='Single Project Assumptions'!$L$57,'Development Phase'!G$4<'Single Project Assumptions'!$L$58),(-'Single Project Assumptions'!$L$56/'Single Project Assumptions'!$L$14),0) -> 0 | H19: =IF(AND(H$4>='Single Project Assumptions'!$L$57,'Development Phase'!H$4<'Single Project Assumptions'!$L$58),(-'Single Project Assumptions'!$L$56/'Single Project Assumptions'!$L$14),0) -> 0 | I19: =IF(AND(I$4>='Single Project Assumptions'!$L$57,'Development Phase'!I$4<'Single Project Assumptions'!$L$58),(-'Single Project Assumptions'!$L$56/'Single Project Assumptions'!$L$14),0) -> 0 | J19: =IF(AND(J$4>='Single Project Assumptions'!$L$57,'Development Phase'!J$4<'Single Project Assumptions'!$L$58),(-'Single Project Assumptions'!$L$56/'Single Project Assumptions'!$L$14),0) -> 0 | K19: =IF(AND(K$4>='Single Project Assumptions'!$L$57,'Development Phase'!K$4<'Single Project Assumptions'!$L$58),(-'Single Project Assumptions'!$L$56/'Single Project Assumptions'!$L$14),0) -> 0 | L19: =IF(AND(L$4>='Single Project Assumptions'!$L$57,'Development Phase'!L$4<'Single Project Assumptions'!$L$58),(-'Single Project Assumptions'!$L$56/'Single Project Assumptions'!$L$14),0) -> 0 | ... DU19: =IF(AND(DU$4>='Single Project Assumptions'!$L$57,'Development Phase'!DU$4<'Single Project Assumptions'!$L$58),(-'Single Project Assumptions'!$L$56/'Single Project Assumptions'!$L$14),0) -> 0
C20: Total Development Costs | D20: =SUM(E20:DU20) -> -1.659753e+08 | E20: =SUM(E15:E19) -> 0 | F20: =SUM(F15:F19) -> 0 | G20: =SUM(G15:G19) -> 0 | H20: =SUM(H15:H19) -> 0 | I20: =SUM(I15:I19) -> 0 | J20: =SUM(J15:J19) -> 0 | K20: =SUM(K15:K19) -> 0 | L20: =SUM(L15:L19) -> 0 | ... DU20: =SUM(DU15:DU19) -> 0
C22: Project Unlevered Cash Flow | D22: =SUM(E22:DU22) -> 59024695 | E22: =E13+E20 -> 0 | F22: =F13+F20 -> 0 | G22: =G13+G20 -> 0 | H22: =H13+H20 -> 0 | I22: =I13+I20 -> 0 | J22: =J13+J20 -> 0 | K22: =K13+K20 -> 0 | L22: =L13+L20 -> 0 | ... DU22: =DU13+DU20 -> 0
C23: Peak Equity | D23: =-MIN(E23:DU23) -> 1.547253e+08 | E23: =E22 -> 0 | F23: =F22+E23 -> 0 | G23: =G22+F23 -> 0 | H23: =H22+G23 -> 0 | I23: =I22+H23 -> 0 | J23: =J22+I23 -> 0 | K23: =K22+J23 -> 0 | L23: =L22+K23 -> 0 | M23: =M22+L23 -> 0 | ... DU23: =DU22+DT23 -> 59024695
C24: IRR | D24: =HLOOKUP(1,E2:DU24,23,FALSE) -> 0.23911703 | E24: =XIRR(E$22:$DU22,E$4:$DU4,0.1) -> 2.9802322e-09 | F24: =XIRR(F$22:$DU22,F$4:$DU4,0.1) -> 2.9802322e-09 | G24: =XIRR(G$22:$DU22,G$4:$DU4,0.1) -> 2.9802322e-09 | H24: =XIRR(H$22:$DU22,H$4:$DU4,0.1) -> 2.9802322e-09 | I24: =XIRR(I$22:$DU22,I$4:$DU4,0.1) -> 2.9802322e-09 | J24: =XIRR(J$22:$DU22,J$4:$DU4,0.1) -> 2.9802322e-09 | K24: =XIRR(K$22:$DU22,K$4:$DU4,0.1) -> 2.9802322e-09 | L24: =XIRR(L$22:$DU22,L$4:$DU4,0.1) -> 2.9802322e-09 | ... DU24: =XIRR(DU$22:$DU22,DU$4:$DU4,0.1) -> #N/A
C25: Equity Multiple | D25: =D22/D23+1 -> 1.3814806
C27: Developer Cash Flow | D27: =SUM(E27:DU27) -> 56340457 | E27: =E20+(E13*'Single Project Assumptions'!$P$22) -> 0 | F27: =F20+(F13*'Single Project Assumptions'!$P$22) -> 0 | G27: =G20+(G13*'Single Project Assumptions'!$P$22) -> 0 | H27: =H20+(H13*'Single Project Assumptions'!$P$22) -> 0 | I27: =I20+(I13*'Single Project Assumptions'!$P$22) -> 0 | J27: =J20+(J13*'Single Project Assumptions'!$P$22) -> 0 | K27: =K20+(K13*'Single Project Assumptions'!$P$22) -> 0 | L27: =L20+(L13*'Single Project Assumptions'!$P$22) -> 0 | ... DU27: =DU20+(DU13*'Single Project Assumptions'!$P$22) -> 0
C28: Peak Equity | D28: =-MIN(E28:DU28) -> 1.5485952e+08 | E28: =E27 -> 0 | F28: =F27+E28 -> 0 | G28: =G27+F28 -> 0 | H28: =H27+G28 -> 0 | I28: =I27+H28 -> 0 | J28: =J27+I28 -> 0 | K28: =K27+J28 -> 0 | L28: =L27+K28 -> 0 | M28: =M27+L28 -> 0 | ... DU28: =DU27+DT28 -> 56340457
C29: IRR | D29: =HLOOKUP(1,E2:DU29,28,FALSE) -> 0.22888162 | E29: =XIRR(E$27:$DU27,E$4:$DU4,0.1) -> 2.9802322e-09 | F29: =XIRR(F$27:$DU27,F$4:$DU4,0.1) -> 2.9802322e-09 | G29: =XIRR(G$27:$DU27,G$4:$DU4,0.1) -> 2.9802322e-09 | H29: =XIRR(H$27:$DU27,H$4:$DU4,0.1) -> 2.9802322e-09 | I29: =XIRR(I$27:$DU27,I$4:$DU4,0.1) -> 2.9802322e-09 | J29: =XIRR(J$27:$DU27,J$4:$DU4,0.1) -> 2.9802322e-09 | K29: =XIRR(K$27:$DU27,K$4:$DU4,0.1) -> 2.9802322e-09 | L29: =XIRR(L$27:$DU27,L$4:$DU4,0.1) -> 2.9802322e-09 | ... DU29: =XIRR(DU$27:$DU27,DU$4:$DU4,0.1) -> #N/A
C30: Equity Multiple | D30: =D27/D28+1 -> 1.3638166
C32: Equity Participation
C33: Landowner Share | D33: =SUM(E33:DU33) -> 1342119.2 | E33: =(E13*'Single Project Assumptions'!$P$20) -> 0 | F33: =(F13*'Single Project Assumptions'!$P$20) -> 0 | G33: =(G13*'Single Project Assumptions'!$P$20) -> 0 | H33: =(H13*'Single Project Assumptions'!$P$20) -> 0 | I33: =(I13*'Single Project Assumptions'!$P$20) -> 0 | J33: =(J13*'Single Project Assumptions'!$P$20) -> 0 | K33: =(K13*'Single Project Assumptions'!$P$20) -> 0 | L33: =(L13*'Single Project Assumptions'!$P$20) -> 0 | ... DU33: =(DU13*'Single Project Assumptions'!$P$20) -> 0
C34: The Commons Share | D34: =SUM(E34:DU34) -> 1342119.2 | E34: =E13*('Single Project Assumptions'!$P$21) -> 0 | F34: =F13*('Single Project Assumptions'!$P$21) -> 0 | G34: =G13*('Single Project Assumptions'!$P$21) -> 0 | H34: =H13*('Single Project Assumptions'!$P$21) -> 0 | I34: =I13*('Single Project Assumptions'!$P$21) -> 0 | J34: =J13*('Single Project Assumptions'!$P$21) -> 0 | K34: =K13*('Single Project Assumptions'!$P$21) -> 0 | L34: =L13*('Single Project Assumptions'!$P$21) -> 0 | ... DU34: =DU13*('Single Project Assumptions'!$P$21) -> 0
C36: Capital Formation Fees
C37: Landowner Share | D37: =SUM(E37:DU37) -> 900000 | E37: =-E$18*'Single Project Assumptions'!$L$53 -> 0 | F37: =-F$18*'Single Project Assumptions'!$L$53 -> 0 | G37: =-G$18*'Single Project Assumptions'!$L$53 -> 0 | H37: =-H$18*'Single Project Assumptions'!$L$53 -> 0 | I37: =-I$18*'Single Project Assumptions'!$L$53 -> 0 | J37: =-J$18*'Single Project Assumptions'!$L$53 -> 0 | K37: =-K$18*'Single Project Assumptions'!$L$53 -> 0 | L37: =-L$18*'Single Project Assumptions'!$L$53 -> 0 | ... DU37: =-DU$18*'Single Project Assumptions'!$L$53 -> 0
C38: The Commons Share | D38: =SUM(E38:DU38) -> 1350000 | E38: =-E$18*'Single Project Assumptions'!$L$52 -> 0 | F38: =-F$18*'Single Project Assumptions'!$L$52 -> 0 | G38: =-G$18*'Single Project Assumptions'!$L$52 -> 0 | H38: =-H$18*'Single Project Assumptions'!$L$52 -> 0 | I38: =-I$18*'Single Project Assumptions'!$L$52 -> 0 | J38: =-J$18*'Single Project Assumptions'!$L$52 -> 0 | K38: =-K$18*'Single Project Assumptions'!$L$52 -> 0 | L38: =-L$18*'Single Project Assumptions'!$L$52 -> 0 | ... DU38: =-DU$18*'Single Project Assumptions'!$L$52 -> 0
C40: Delivery Fees
C41: Landowner Share | D41: =SUM(E41:DU41) -> 157621.88 | E41: =-E$19*'Single Project Assumptions'!$L$60 -> 0 | F41: =-F$19*'Single Project Assumptions'!$L$60 -> 0 | G41: =-G$19*'Single Project Assumptions'!$L$60 -> 0 | H41: =-H$19*'Single Project Assumptions'!$L$60 -> 0 | I41: =-I$19*'Single Project Assumptions'!$L$60 -> 0 | J41: =-J$19*'Single Project Assumptions'!$L$60 -> 0 | K41: =-K$19*'Single Project Assumptions'!$L$60 -> 0 | L41: =-L$19*'Single Project Assumptions'!$L$60 -> 0 | ... DU41: =-DU$19*'Single Project Assumptions'!$L$60 -> 0
C42: The Commons Share | D42: =SUM(E42:DU42) -> 236432.81 | E42: =-E$19*'Single Project Assumptions'!$L$59 -> 0 | F42: =-F$19*'Single Project Assumptions'!$L$59 -> 0 | G42: =-G$19*'Single Project Assumptions'!$L$59 -> 0 | H42: =-H$19*'Single Project Assumptions'!$L$59 -> 0 | I42: =-I$19*'Single Project Assumptions'!$L$59 -> 0 | J42: =-J$19*'Single Project Assumptions'!$L$59 -> 0 | K42: =-K$19*'Single Project Assumptions'!$L$59 -> 0 | L42: =-L$19*'Single Project Assumptions'!$L$59 -> 0 | ... DU42: =-DU$19*'Single Project Assumptions'!$L$59 -> 0
C44: Total Fees and Equity
C45: Landowner Share | D45: =SUM(E45:DU45) -> 2399741.1 | E45: =SUM(E33,E37,E41) -> 0 | F45: =SUM(F33,F37,F41) -> 0 | G45: =SUM(G33,G37,G41) -> 0 | H45: =SUM(H33,H37,H41) -> 0 | I45: =SUM(I33,I37,I41) -> 0 | J45: =SUM(J33,J37,J41) -> 0 | K45: =SUM(K33,K37,K41) -> 0 | L45: =SUM(L33,L37,L41) -> 0 | ... DU45: =SUM(DU33,DU37,DU41) -> 0
C46: The Commons Share | D46: =SUM(E46:DU46) -> 2928552 | E46: =SUM(E34,E38,E42) -> 0 | F46: =SUM(F34,F38,F42) -> 0 | G46: =SUM(G34,G38,G42) -> 0 | H46: =SUM(H34,H38,H42) -> 0 | I46: =SUM(I34,I38,I42) -> 0 | J46: =SUM(J34,J38,J42) -> 0 | K46: =SUM(K34,K38,K42) -> 0 | L46: =SUM(L34,L38,L42) -> 0 | ... DU46: =SUM(DU34,DU38,DU42) -> 0

Sheet Operational Phase
D3: Year | E3: =YEAR(E4) -> 2026 | F3: =YEAR(F4) -> 2027 | G3: =YEAR(G4) -> 2027 | H3: =YEAR(H4) -> 2027 | I3: =YEAR(I4) -> 2027 | J3: =YEAR(J4) -> 2027 | K3: =YEAR(K4) -> 2027 | L3: =YEAR(L4) -> 2027 | ... DU3: =YEAR(DU4) -> 2036
C4: Operational Phase CF | D4: Total | E4: ='Single Project Assumptions'!D6 -> 46387 | F4: =EOMONTH(E4,1) -> 46418 | G4: =EOMONTH(F4,1) -> 46446 | H4: =EOMONTH(G4,1) -> 46477 | I4: =EOMONTH(H4,1) -> 46507 | J4: =EOMONTH(I4,1) -> 46538 | K4: =EOMONTH(J4,1) -> 46568 | L4: =EOMONTH(K4,1) -> 46599 | M4: =EOMONTH(L4,1) -> 46630 | ... DU4: =EOMONTH(DT4,1) -> 50040
C6: Cumulative Operating Units | E6: =-SUMIF('Development Phase'!$E$4:$DU$4,"<="&'Operational Phase'!E$4,'Development Phase'!$E$8:$DU$8) -> 0 | F6: =-SUMIF('Development Phase'!$E$4:$DU$4,"<="&'Operational Phase'!F$4,'Development Phase'!$E$8:$DU$8) -> 0 | G6: =-SUMIF('Development Phase'!$E$4:$DU$4,"<="&'Operational Phase'!G$4,'Development Phase'!$E$8:$DU$8) -> 0 | H6: =-SUMIF('Development Phase'!$E$4:$DU$4,"<="&'Operational Phase'!H$4,'Development Phase'!$E$8:$DU$8) -> 0 | I6: =-SUMIF('Development Phase'!$E$4:$DU$4,"<="&'Operational Phase'!I$4,'Development Phase'!$E$8:$DU$8) -> 0 | J6: =-SUMIF('Development Phase'!$E$4:$DU$4,"<="&'Operational Phase'!J$4,'Development Phase'!$E$8:$DU$8) -> 0 | K6: =-SUMIF('Development Phase'!$E$4:$DU$4,"<="&'Operational Phase'!K$4,'Development Phase'!$E$8:$DU$8) -> 0 | L6: =-SUMIF('Development Phase'!$E$4:$DU$4,"<="&'Operational Phase'!L$4,'Development Phase'!$E$8:$DU$8) -> 0 | ... DU6: =-SUMIF('Development Phase'!$E$4:$DU$4,"<="&'Operational Phase'!DU$4,'Development Phase'!$E$8:$DU$8) -> 150
C8: Operating Fees (The Commons) | D8: =SUM(E8:DU8) -> 1267500 | E8: =IF(AND(E$4>='Single Project Assumptions'!$P$53,'Operational Phase'!E$4<'Single Project Assumptions'!$P$54),'Single Project Assumptions'!$P$49*'Operational Phase'!E$6,0) -> 0 | F8: =IF(AND(F$4>='Single Project Assumptions'!$P$53,'Operational Phase'!F$4<'Single Project Assumptions'!$P$54),'Single Project Assumptions'!$P$49*'Operational Phase'!F$6,0) -> 0 | G8: =IF(AND(G$4>='Single Project Assumptions'!$P$53,'Operational Phase'!G$4<'Single Project Assumptions'!$P$54),'Single Project Assumptions'!$P$49*'Operational Phase'!G$6,0) -> 0 | H8: =IF(AND(H$4>='Single Project Assumptions'!$P$53,'Operational Phase'!H$4<'Single Project Assumptions'!$P$54),'Single Project Assumptions'!$P$49*'Operational Phase'!H$6,0) -> 0 | I8: =IF(AND(I$4>='Single Project Assumptions'!$P$53,'Operational Phase'!I$4<'Single Project Assumptions'!$P$54),'Single Project Assumptions'!$P$49*'Operational Phase'!I$6,0) -> 0 | J8: =IF(AND(J$4>='Single Project Assumptions'!$P$53,'Operational Phase'!J$4<'Single Project Assumptions'!$P$54),'Single Project Assumptions'!$P$49*'Operational Phase'!J$6,0) -> 0 | K8: =IF(AND(K$4>='Single Project Assumptions'!$P$53,'Operational Phase'!K$4<'Single Project Assumptions'!$P$54),'Single Project Assumptions'!$P$49*'Operational Phase'!K$6,0) -> 0 | L8: =IF(AND(L$4>='Single Project Assumptions'!$P$53,'Operational Phase'!L$4<'Single Project Assumptions'!$P$54),'Single Project Assumptions'!$P$49*'Operational Phase'!L$6,0) -> 0 | ... DU8: =IF(AND(DU$4>='Single Project Assumptions'!$P$53,'Operational Phase'!DU$4<'Single Project Assumptions'!$P$54),'Single Project Assumptions'!$P$49*'Operational Phase'!DU$6,0) -> 0
C9: Landowner Payments (Landowner) | D9: =SUM(E9:DU9) -> 704166.67 | E9: =IF(AND(E$4>='Single Project Assumptions'!$D$56,'Operational Phase'!E$4<'Single Project Assumptions'!$D$57),'Single Project Assumptions'!$D$54*E$6,0) -> 0 | F9: =IF(AND(F$4>='Single Project Assumptions'!$D$56,'Operational Phase'!F$4<'Single Project Assumptions'!$D$57),'Single Project Assumptions'!$D$54*F$6,0) -> 0 | G9: =IF(AND(G$4>='Single Project Assumptions'!$D$56,'Operational Phase'!G$4<'Single Project Assumptions'!$D$57),'Single Project Assumptions'!$D$54*G$6,0) -> 0 | H9: =IF(AND(H$4>='Single Project Assumptions'!$D$56,'Operational Phase'!H$4<'Single Project Assumptions'!$D$57),'Single Project Assumptions'!$D$54*H$6,0) -> 0 | I9: =IF(AND(I$4>='Single Project Assumptions'!$D$56,'Operational Phase'!I$4<'Single Project Assumptions'!$D$57),'Single Project Assumptions'!$D$54*I$6,0) -> 0 | J9: =IF(AND(J$4>='Single Project Assumptions'!$D$56,'Operational Phase'!J$4<'Single Project Assumptions'!$D$57),'Single Project Assumptions'!$D$54*J$6,0) -> 0 | K9: =IF(AND(K$4>='Single Project Assumptions'!$D$56,'Operational Phase'!K$4<'Single Project Assumptions'!$D$57),'Single Project Assumptions'!$D$54*K$6,0) -> 0 | L9: =IF(AND(L$4>='Single Project Assumptions'!$D$56,'Operational Phase'!L$4<'Single Project Assumptions'!$D$57),'Single Project Assumptions'!$D$54*L$6,0) -> 0 | ... DU9: =IF(AND(DU$4>='Single Project Assumptions'!$D$56,'Operational Phase'!DU$4<'Single Project Assumptions'!$D$57),'Single Project Assumptions'!$D$54*DU$6,0) -> 0
C10: Service Charge Income | D10: =SUM(E10:DU10) -> 1690000 | E10: =IF(AND(E$4>='Single Project Assumptions'!$T$53,'Operational Phase'!E$4<'Single Project Assumptions'!$T$54),'Single Project Assumptions'!$T$49*'Operational Phase'!E$6,0) -> 0 | F10: =IF(AND(F$4>='Single Project Assumptions'!$T$53,'Operational Phase'!F$4<'Single Project Assumptions'!$T$54),'Single Project Assumptions'!$T$49*'Operational Phase'!F$6,0) -> 0 | G10: =IF(AND(G$4>='Single Project Assumptions'!$T$53,'Operational Phase'!G$4<'Single Project Assumptions'!$T$54),'Single Project Assumptions'!$T$49*'Operational Phase'!G$6,0) -> 0 | H10: =IF(AND(H$4>='Single Project Assumptions'!$T$53,'Operational Phase'!H$4<'Single Project Assumptions'!$T$54),'Single Project Assumptions'!$T$49*'Operational Phase'!H$6,0) -> 0 | I10: =IF(AND(I$4>='Single Project Assumptions'!$T$53,'Operational Phase'!I$4<'Single Project Assumptions'!$T$54),'Single Project Assumptions'!$T$49*'Operational Phase'!I$6,0) -> 0 | J10: =IF(AND(J$4>='Single Project Assumptions'!$T$53,'Operational Phase'!J$4<'Single Project Assumptions'!$T$54),'Single Project Assumptions'!$T$49*'Operational Phase'!J$6,0) -> 0 | K10: =IF(AND(K$4>='Single Project Assumptions'!$T$53,'Operational Phase'!K$4<'Single Project Assumptions'!$T$54),'Single Project Assumptions'!$T$49*'Operational Phase'!K$6,0) -> 0 | L10: =IF(AND(L$4>='Single Project Assumptions'!$T$53,'Operational Phase'!L$4<'Single Project Assumptions'!$T$54),'Single Project Assumptions'!$T$49*'Operational Phase'!L$6,0) -> 0 | ... DU10: =IF(AND(DU$4>='Single Project Assumptions'!$T$53,'Operational Phase'!DU$4<'Single Project Assumptions'!$T$54),'Single Project Assumptions'!$T$49*'Operational Phase'!DU$6,0) -> 0
C11: Total Fees Paid By Residents | D11: =SUM(E11:DU11) -> 3661666.7 | E11: =SUM(E8:E10) -> 0 | F11: =SUM(F8:F10) -> 0 | G11: =SUM(G8:G10) -> 0 | H11: =SUM(H8:H10) -> 0 | I11: =SUM(I8:I10) -> 0 | J11: =SUM(J8:J10) -> 0 | K11: =SUM(K8:K10) -> 0 | L11: =SUM(L8:L10) -> 0 | ... DU11: =SUM(DU8:DU10) -> 0
C12: Per Operating Unit | E12: =IF(ISERROR(E11/E6),0,(E11/E6)) -> 0 | F12: =IF(ISERROR(F11/F6),0,(F11/F6)) -> 0 | G12: =IF(ISERROR(G11/G6),0,(G11/G6)) -> 0 | H12: =IF(ISERROR(H11/H6),0,(H11/H6)) -> 0 | I12: =IF(ISERROR(I11/I6),0,(I11/I6)) -> 0 | J12: =IF(ISERROR(J11/J6),0,(J11/J6)) -> 0 | K12: =IF(ISERROR(K11/K6),0,(K11/K6)) -> 0 | L12: =IF(ISERROR(L11/L6),0,(L11/L6)) -> 0 | ... DU12: =IF(ISERROR(DU11/DU6),0,(DU11/DU6)) -> 0
C14: The Commons
C15: Operating Fees (The Commons) | D15: =SUM(E15:DU15) -> 1267500 | E15: =E8 -> 0 | F15: =F8 -> 0 | G15: =G8 -> 0 | H15: =H8 -> 0 | I15: =I8 -> 0 | J15: =J8 -> 0 | K15: =K8 -> 0 | L15: =L8 -> 0 | ... DU15: =DU8 -> 0
C16: Operating Costs | D16: =SUM(E16:DU16) -> -945000 | E16: =IF(AND(E$4>='Single Project Assumptions'!$P$59,'Operational Phase'!E$4<'Single Project Assumptions'!$P$60),-'Single Project Assumptions'!$P$58/12,0) -> 0 | F16: =IF(AND(F$4>='Single Project Assumptions'!$P$59,'Operational Phase'!F$4<'Single Project Assumptions'!$P$60),-'Single Project Assumptions'!$P$58/12,0) -> 0 | G16: =IF(AND(G$4>='Single Project Assumptions'!$P$59,'Operational Phase'!G$4<'Single Project Assumptions'!$P$60),-'Single Project Assumptions'!$P$58/12,0) -> 0 | H16: =IF(AND(H$4>='Single Project Assumptions'!$P$59,'Operational Phase'!H$4<'Single Project Assumptions'!$P$60),-'Single Project Assumptions'!$P$58/12,0) -> 0 | I16: =IF(AND(I$4>='Single Project Assumptions'!$P$59,'Operational Phase'!I$4<'Single Project Assumptions'!$P$60),-'Single Project Assumptions'!$P$58/12,0) -> 0 | J16: =IF(AND(J$4>='Single Project Assumptions'!$P$59,'Operational Phase'!J$4<'Single Project Assumptions'!$P$60),-'Single Project Assumptions'!$P$58/12,0) -> 0 | K16: =IF(AND(K$4>='Single Project Assumptions'!$P$59,'Operational Phase'!K$4<'Single Project Assumptions'!$P$60),-'Single Project Assumptions'!$P$58/12,0) -> 0 | L16: =IF(AND(L$4>='Single Project Assumptions'!$P$59,'Operational Phase'!L$4<'Single Project Assumptions'!$P$60),-'Single Project Assumptions'!$P$58/12,0) -> 0 | ... DU16: =IF(AND(DU$4>='Single Project Assumptions'!$P$59,'Operational Phase'!DU$4<'Single Project Assumptions'!$P$60),-'Single Project Assumptions'!$P$58/12,0) -> 0
C17: The Commons EBITDA | D17: =SUM(E17:DU17) -> 322500 | E17: =SUM(E15:E16) -> 0 | F17: =SUM(F15:F16) -> 0 | G17: =SUM(G15:G16) -> 0 | H17: =SUM(H15:H16) -> 0 | I17: =SUM(I15:I16) -> 0 | J17: =SUM(J15:J16) -> 0 | K17: =SUM(K15:K16) -> 0 | L17: =SUM(L15:L16) -> 0 | ... DU17: =SUM(DU15:DU16) -> 0
C18: Margin | D18: =MAX(E18:DU18) -> 0.3 | E18: =IF(ISERROR(E17/E15),0,(E17/E15)) -> 0 | F18: =IF(ISERROR(F17/F15),0,(F17/F15)) -> 0 | G18: =IF(ISERROR(G17/G15),0,(G17/G15)) -> 0 | H18: =IF(ISERROR(H17/H15),0,(H17/H15)) -> 0 | I18: =IF(ISERROR(I17/I15),0,(I17/I15)) -> 0 | J18: =IF(ISERROR(J17/J15),0,(J17/J15)) -> 0 | K18: =IF(ISERROR(K17/K15),0,(K17/K15)) -> 0 | L18: =IF(ISERROR(L17/L15),0,(L17/L15)) -> 0 | ... DU18: =IF(ISERROR(DU17/DU15),0,(DU17/DU15)) -> 0
C20: Community
C21: Service Charge Income | D21: =D10 -> 1690000 | E21: =E10 -> 0 | F21: =F10 -> 0 | G21: =G10 -> 0 | H21: =H10 -> 0 | I21: =I10 -> 0 | J21: =J10 -> 0 | K21: =K10 -> 0 | ... DU21: =DU10 -> 0
C22: Service Charge Costs | D22: =SUM(E22:DU22) -> -1800000 | E22: =IF(AND(E$4>='Single Project Assumptions'!$T$53,'Operational Phase'!E$4<'Single Project Assumptions'!$T$54),-'Single Project Assumptions'!$T$58/12,0) -> 0 | F22: =IF(AND(F$4>='Single Project Assumptions'!$T$53,'Operational Phase'!F$4<'Single Project Assumptions'!$T$54),-'Single Project Assumptions'!$T$58/12,0) -> 0 | G22: =IF(AND(G$4>='Single Project Assumptions'!$T$53,'Operational Phase'!G$4<'Single Project Assumptions'!$T$54),-'Single Project Assumptions'!$T$58/12,0) -> 0 | H22: =IF(AND(H$4>='Single Project Assumptions'!$T$53,'Operational Phase'!H$4<'Single Project Assumptions'!$T$54),-'Single Project Assumptions'!$T$58/12,0) -> 0 | I22: =IF(AND(I$4>='Single Project Assumptions'!$T$53,'Operational Phase'!I$4<'Single Project Assumptions'!$T$54),-'Single Project Assumptions'!$T$58/12,0) -> 0 | J22: =IF(AND(J$4>='Single Project Assumptions'!$T$53,'Operational Phase'!J$4<'Single Project Assumptions'!$T$54),-'Single Project Assumptions'!$T$58/12,0) -> 0 | K22: =IF(AND(K$4>='Single Project Assumptions'!$T$53,'Operational Phase'!K$4<'Single Project Assumptions'!$T$54),-'Single Project Assumptions'!$T$58/12,0) -> 0 | L22: =IF(AND(L$4>='Single Project Assumptions'!$T$53,'Operational Phase'!L$4<'Single Project Assumptions'!$T$54),-'Single Project Assumptions'!$T$58/12,0) -> 0 | ... DU22: =IF(AND(DU$4>='Single Project Assumptions'!$T$53,'Operational Phase'!DU$4<'Single Project Assumptions'!$T$54),-'Single Project Assumptions'!$T$58/12,0) -> 0
C23: The Commons EBITDA | D23: =SUM(E23:DU23) -> -110000 | E23: =SUM(E21:E22) -> 0 | F23: =SUM(F21:F22) -> 0 | G23: =SUM(G21:G22) -> 0 | H23: =SUM(H21:H22) -> 0 | I23: =SUM(I21:I22) -> 0 | J23: =SUM(J21:J22) -> 0 | K23: =SUM(K21:K22) -> 0 | L23: =SUM(L21:L22) -> 0 | ... DU23: =SUM(DU21:DU22) -> 0
C24: Margin | D24: =MAX(E24:DU24) -> 0 | E24: =IF(ISERROR(E23/E21),0,(E23/E21)) -> 0 | F24: =IF(ISERROR(F23/F21),0,(F23/F21)) -> 0 | G24: =IF(ISERROR(G23/G21),0,(G23/G21)) -> 0 | H24: =IF(ISERROR(H23/H21),0,(H23/H21)) -> 0 | I24: =IF(ISERROR(I23/I21),0,(I23/I21)) -> 0 | J24: =IF(ISERROR(J23/J21),0,(J23/J21)) -> 0 | K24: =IF(ISERROR(K23/K21),0,(K23/K21)) -> 0 | L24: =IF(ISERROR(L23/L21),0,(L23/L21)) -> 0 | ... DU24: =IF(ISERROR(DU23/DU21),0,(DU23/DU21)) -> 0
C26: Landowner Stewardship Payment
C27: Landowner Stewardship Payment | D27: =D15 -> 1267500 | E27: =E9 -> 0 | F27: =F9 -> 0 | G27: =G9 -> 0 | H27: =H9 -> 0 | I27: =I9 -> 0 | J27: =J9 -> 0 | K27: =K9 -> 0 | L27: =L9 -> 0 | ... DU27: =DU9 -> 0
C28: Yield on Original Land Value (annualized) | D28: =MAX(E28:DU28) -> 0.15 | E28: =(E27*12)/'Single Project Assumptions'!$D$39 -> 0 | F28: =(F27*12)/'Single Project Assumptions'!$D$39 -> 0 | G28: =(G27*12)/'Single Project Assumptions'!$D$39 -> 0 | H28: =(H27*12)/'Single Project Assumptions'!$D$39 -> 0 | I28: =(I27*12)/'Single Project Assumptions'!$D$39 -> 0 | J28: =(J27*12)/'Single Project Assumptions'!$D$39 -> 0 | K28: =(K27*12)/'Single Project Assumptions'!$D$39 -> 0 | L28: =(L27*12)/'Single Project Assumptions'!$D$39 -> 0 | ... DU28: =(DU27*12)/'Single Project Assumptions'!$D$39 -> 0

Sheet Calc_Helper
A1: Calc helper (hidden) — do not edit
A3: Global dates (first 120 months) | B3: (links to Development Phase timeline) | C3: ='Development Phase'!E4 -> 46387 | D3: ='Development Phase'!F4 -> 46418 | E3: ='Development Phase'!G4 -> 46446 | F3: ='Development Phase'!H4 -> 46477 | G3: ='Development Phase'!I4 -> 46507 | H3: ='Development Phase'!J4 -> 46538 | I3: ='Development Phase'!K4 -> 46568 | J3: ='Development Phase'!L4 -> 46599 | ... DR3: ='Development Phase'!DT4 -> 50009
A4: Month # | C4: 1 | D4: 2 | E4: 3 | F4: 4 | G4: 5 | H4: 6 | I4: 7 | J4: 8 | K4: 9 | L4: 10 | M4: 11 | N4: 12 | O4: 13 | P4: 14 | Q4: 15 | R4: 16 | S4: 17 | T4: 18 | U4: 19 | V4: 20 | W4: 21 | X4: 22 | Y4: 23 | Z4: 24 | AA4: 25 | AB4: 26 | AC4: 27 | AD4: 28 | AE4: 29 | AF4: 30 | AG4: 31 | AH4: 32 | AI4: 33 | AJ4: 34 | AK4: 35 | AL4: 36 | AM4: 37 | AN4: 38 | AO4: 39 | AP4: 40 | AQ4: 41 | AR4: 42 | AS4: 43 | AT4: 44 | AU4: 45 | AV4: 46 | AW4: 47 | AX4: 48 | AY4: 49 | AZ4: 50 | BA4: 51 | BB4: 52 | BC4: 53 | BD4: 54 | BE4: 55 | BF4: 56 | BG4: 57 | BH4: 58 | BI4: 59 | BJ4: 60 | BK4: 61 | BL4: 62 | BM4: 63 | BN4: 64 | BO4: 65 | BP4: 66 | BQ4: 67 | BR4: 68 | BS4: 69 | BT4: 70 | BU4: 71 | BV4: 72 | BW4: 73 | BX4: 74 | BY4: 75 | BZ4: 76 | CA4: 77 | CB4: 78 | CC4: 79 | CD4: 80 | CE4: 81 | CF4: 82 | CG4: 83 | CH4: 84 | CI4: 85 | CJ4: 86 | CK4: 87 | CL4: 88 | CM4: 89 | CN4: 90 | CO4: 91 | CP4: 92 | CQ4: 93 | CR4: 94 | CS4: 95 | CT4: 96 | CU4: 97 | CV4: 98 | CW4: 99 | CX4: 100 | CY4: 101 | CZ4: 102 | DA4: 103 | DB4: 104 | DC4: 105 | DD4: 106 | DE4: 107 | DF4: 108 | DG4: 109 | DH4: 110 | DI4: 111 | DJ4: 112 | DK4: 113 | DL4: 114 | DM4: 115 | DN4: 116 | DO4: 117 | DP4: 118 | DQ4: 119 | DR4: 120
A5: Base Developer CF (single project) | C5: ='Development Phase'!E27 -> 0 | D5: ='Development Phase'!F27 -> 0 | E5: ='Development Phase'!G27 -> 0 | F5: ='Development Phase'!H27 -> 0 | G5: ='Development Phase'!I27 -> 0 | H5: ='Development Phase'!J27 -> 0 | I5: ='Development Phase'!K27 -> 0 | J5: ='Development Phase'!L27 -> 0 | ... DR5: ='Development Phase'!DT27 -> 0
A6: Base Sales Revenue (gross) | C6: ='Development Phase'!E13 -> 0 | D6: ='Development Phase'!F13 -> 0 | E6: ='Development Phase'!G13 -> 0 | F6: ='Development Phase'!H13 -> 0 | G6: ='Development Phase'!I13 -> 0 | H6: ='Development Phase'!J13 -> 0 | I6: ='Development Phase'!K13 -> 0 | J6: ='Development Phase'!L13 -> 0 | ... DR6: ='Development Phase'!DT13 -> 0
A7: Base Closing Payments (cash at close) | C7: ='Development Phase'!E12 -> 0 | D7: ='Development Phase'!F12 -> 0 | E7: ='Development Phase'!G12 -> 0 | F7: ='Development Phase'!H12 -> 0 | G7: ='Development Phase'!I12 -> 0 | H7: ='Development Phase'!J12 -> 0 | I7: ='Development Phase'!K12 -> 0 | J7: ='Development Phase'!L12 -> 0 | ... DR7: ='Development Phase'!DT12 -> 0
A9: Project | B9: Start Date | C9: Entitlement? | D9: (from Platform Assumptions)
A10: 1 | B10: ='Platform Assumptions'!D6 -> 46387 | C10: ='Platform Assumptions'!E6 -> Yes
A11: 2 | B11: ='Platform Assumptions'!D7 -> 46477 | C11: ='Platform Assumptions'!E7 -> No
A12: 3 | B12: ='Platform Assumptions'!D8 -> 46568 | C12: ='Platform Assumptions'!E8 -> Yes
A13: 4 | B13: ='Platform Assumptions'!D9 -> 46660 | C13: ='Platform Assumptions'!E9 -> No
A14: 5 | B14: ='Platform Assumptions'!D10 -> 46752 | C14: ='Platform Assumptions'!E10 -> Yes
A15: 6 | B15: ='Platform Assumptions'!D11 -> 46843 | C15: ='Platform Assumptions'!E11 -> No
A16: 7 | B16: ='Platform Assumptions'!D12 -> 46934 | C16: ='Platform Assumptions'!E12 -> Yes
A17: 8 | B17: ='Platform Assumptions'!D13 -> 47026 | C17: ='Platform Assumptions'!E13 -> No
A18: 9 | B18: ='Platform Assumptions'!D14 -> 47118 | C18: ='Platform Assumptions'!E14 -> Yes
A19: 10 | B19: ='Platform Assumptions'!D15 -> 47208 | C19: ='Platform Assumptions'!E15 -> No
A25: P1 DevCF | C25: =IF($C10<>"Yes",0,IF(AND(C$3>=$B10,C$3<=EOMONTH($B10,119)),INDEX($C$5:$DR$5,1,12*(YEAR(C$3)-YEAR($B10))+MONTH(C$3)-MONTH($B10)+1),0)) -> 0 | D25: =IF($C10<>"Yes",0,IF(AND(D$3>=$B10,D$3<=EOMONTH($B10,119)),INDEX($C$5:$DR$5,1,12*(YEAR(D$3)-YEAR($B10))+MONTH(D$3)-MONTH($B10)+1),0)) -> 0 | E25: =IF($C10<>"Yes",0,IF(AND(E$3>=$B10,E$3<=EOMONTH($B10,119)),INDEX($C$5:$DR$5,1,12*(YEAR(E$3)-YEAR($B10))+MONTH(E$3)-MONTH($B10)+1),0)) -> 0 | F25: =IF($C10<>"Yes",0,IF(AND(F$3>=$B10,F$3<=EOMONTH($B10,119)),INDEX($C$5:$DR$5,1,12*(YEAR(F$3)-YEAR($B10))+MONTH(F$3)-MONTH($B10)+1),0)) -> 0 | G25: =IF($C10<>"Yes",0,IF(AND(G$3>=$B10,G$3<=EOMONTH($B10,119)),INDEX($C$5:$DR$5,1,12*(YEAR(G$3)-YEAR($B10))+MONTH(G$3)-MONTH($B10)+1),0)) -> 0 | H25: =IF($C10<>"Yes",0,IF(AND(H$3>=$B10,H$3<=EOMONTH($B10,119)),INDEX($C$5:$DR$5,1,12*(YEAR(H$3)-YEAR($B10))+MONTH(H$3)-MONTH($B10)+1),0)) -> 0 | I25: =IF($C10<>"Yes",0,IF(AND(I$3>=$B10,I$3<=EOMONTH($B10,119)),INDEX($C$5:$DR$5,1,12*(YEAR(I$3)-YEAR($B10))+MONTH(I$3)-MONTH($B10)+1),0)) -> 0 | J25: =IF($C10<>"Yes",0,IF(AND(J$3>=$B10,J$3<=EOMONTH($B10,119)),INDEX($C$5:$DR$5,1,12*(YEAR(J$3)-YEAR($B10))+MONTH(J$3)-MONTH($B10)+1),0)) -> 0 | ... DR25: =IF($C10<>"Yes",0,IF(AND(DR$3>=$B10,DR$3<=EOMONTH($B10,119)),INDEX($C$5:$DR$5,1,12*(YEAR(DR$3)-YEAR($B10))+MONTH(DR$3)-MONTH($B10)+1),0)) -> 0
A26: P1 Sales | C26: =IF($C10<>"Yes",0,IF(AND(C$3>=$B10,C$3<=EOMONTH($B10,119)),INDEX($C$6:$DR$6,1,12*(YEAR(C$3)-YEAR($B10))+MONTH(C$3)-MONTH($B10)+1),0)) -> 0 | D26: =IF($C10<>"Yes",0,IF(AND(D$3>=$B10,D$3<=EOMONTH($B10,119)),INDEX($C$6:$DR$6,1,12*(YEAR(D$3)-YEAR($B10))+MONTH(D$3)-MONTH($B10)+1),0)) -> 0 | E26: =IF($C10<>"Yes",0,IF(AND(E$3>=$B10,E$3<=EOMONTH($B10,119)),INDEX($C$6:$DR$6,1,12*(YEAR(E$3)-YEAR($B10))+MONTH(E$3)-MONTH($B10)+1),0)) -> 0 | F26: =IF($C10<>"Yes",0,IF(AND(F$3>=$B10,F$3<=EOMONTH($B10,119)),INDEX($C$6:$DR$6,1,12*(YEAR(F$3)-YEAR($B10))+MONTH(F$3)-MONTH($B10)+1),0)) -> 0 | G26: =IF($C10<>"Yes",0,IF(AND(G$3>=$B10,G$3<=EOMONTH($B10,119)),INDEX($C$6:$DR$6,1,12*(YEAR(G$3)-YEAR($B10))+MONTH(G$3)-MONTH($B10)+1),0)) -> 0 | H26: =IF($C10<>"Yes",0,IF(AND(H$3>=$B10,H$3<=EOMONTH($B10,119)),INDEX($C$6:$DR$6,1,12*(YEAR(H$3)-YEAR($B10))+MONTH(H$3)-MONTH($B10)+1),0)) -> 0 | I26: =IF($C10<>"Yes",0,IF(AND(I$3>=$B10,I$3<=EOMONTH($B10,119)),INDEX($C$6:$DR$6,1,12*(YEAR(I$3)-YEAR($B10))+MONTH(I$3)-MONTH($B10)+1),0)) -> 0 | J26: =IF($C10<>"Yes",0,IF(AND(J$3>=$B10,J$3<=EOMONTH($B10,119)),INDEX($C$6:$DR$6,1,12*(YEAR(J$3)-YEAR($B10))+MONTH(J$3)-MONTH($B10)+1),0)) -> 0 | ... DR26: =IF($C10<>"Yes",0,IF(AND(DR$3>=$B10,DR$3<=EOMONTH($B10,119)),INDEX($C$6:$DR$6,1,12*(YEAR(DR$3)-YEAR($B10))+MONTH(DR$3)-MONTH($B10)+1),0)) -> 0
A27: P1 ClosingPay | C27: =IF($C10<>"Yes",0,IF(AND(C$3>=$B10,C$3<=EOMONTH($B10,119)),INDEX($C$7:$DR$7,1,12*(YEAR(C$3)-YEAR($B10))+MONTH(C$3)-MONTH($B10)+1),0)) -> 0 | D27: =IF($C10<>"Yes",0,IF(AND(D$3>=$B10,D$3<=EOMONTH($B10,119)),INDEX($C$7:$DR$7,1,12*(YEAR(D$3)-YEAR($B10))+MONTH(D$3)-MONTH($B10)+1),0)) -> 0 | E27: =IF($C10<>"Yes",0,IF(AND(E$3>=$B10,E$3<=EOMONTH($B10,119)),INDEX($C$7:$DR$7,1,12*(YEAR(E$3)-YEAR($B10))+MONTH(E$3)-MONTH($B10)+1),0)) -> 0 | F27: =IF($C10<>"Yes",0,IF(AND(F$3>=$B10,F$3<=EOMONTH($B10,119)),INDEX($C$7:$DR$7,1,12*(YEAR(F$3)-YEAR($B10))+MONTH(F$3)-MONTH($B10)+1),0)) -> 0 | G27: =IF($C10<>"Yes",0,IF(AND(G$3>=$B10,G$3<=EOMONTH($B10,119)),INDEX($C$7:$DR$7,1,12*(YEAR(G$3)-YEAR($B10))+MONTH(G$3)-MONTH($B10)+1),0)) -> 0 | H27: =IF($C10<>"Yes",0,IF(AND(H$3>=$B10,H$3<=EOMONTH($B10,119)),INDEX($C$7:$DR$7,1,12*(YEAR(H$3)-YEAR($B10))+MONTH(H$3)-MONTH($B10)+1),0)) -> 0 | I27: =IF($C10<>"Yes",0,IF(AND(I$3>=$B10,I$3<=EOMONTH($B10,119)),INDEX($C$7:$DR$7,1,12*(YEAR(I$3)-YEAR($B10))+MONTH(I$3)-MONTH($B10)+1),0)) -> 0 | J27: =IF($C10<>"Yes",0,IF(AND(J$3>=$B10,J$3<=EOMONTH($B10,119)),INDEX($C$7:$DR$7,1,12*(YEAR(J$3)-YEAR($B10))+MONTH(J$3)-MONTH($B10)+1),0)) -> 0 | ... DR27: =IF($C10<>"Yes",0,IF(AND(DR$3>=$B10,DR$3<=EOMONTH($B10,119)),INDEX($C$7:$DR$7,1,12*(YEAR(DR$3)-YEAR($B10))+MONTH(DR$3)-MONTH($B10)+1),0)) -> 0
A28: P2 DevCF | C28: =IF($C11<>"Yes",0,IF(AND(C$3>=$B11,C$3<=EOMONTH($B11,119)),INDEX($C$5:$DR$5,1,12*(YEAR(C$3)-YEAR($B11))+MONTH(C$3)-MONTH($B11)+1),0)) -> 0 | D28: =IF($C11<>"Yes",0,IF(AND(D$3>=$B11,D$3<=EOMONTH($B11,119)),INDEX($C$5:$DR$5,1,12*(YEAR(D$3)-YEAR($B11))+MONTH(D$3)-MONTH($B11)+1),0)) -> 0 | E28: =IF($C11<>"Yes",0,IF(AND(E$3>=$B11,E$3<=EOMONTH($B11,119)),INDEX($C$5:$DR$5,1,12*(YEAR(E$3)-YEAR($B11))+MONTH(E$3)-MONTH($B11)+1),0)) -> 0 | F28: =IF($C11<>"Yes",0,IF(AND(F$3>=$B11,F$3<=EOMONTH($B11,119)),INDEX($C$5:$DR$5,1,12*(YEAR(F$3)-YEAR($B11))+MONTH(F$3)-MONTH($B11)+1),0)) -> 0 | G28: =IF($C11<>"Yes",0,IF(AND(G$3>=$B11,G$3<=EOMONTH($B11,119)),INDEX($C$5:$DR$5,1,12*(YEAR(G$3)-YEAR($B11))+MONTH(G$3)-MONTH($B11)+1),0)) -> 0 | H28: =IF($C11<>"Yes",0,IF(AND(H$3>=$B11,H$3<=EOMONTH($B11,119)),INDEX($C$5:$DR$5,1,12*(YEAR(H$3)-YEAR($B11))+MONTH(H$3)-MONTH($B11)+1),0)) -> 0 | I28: =IF($C11<>"Yes",0,IF(AND(I$3>=$B11,I$3<=EOMONTH($B11,119)),INDEX($C$5:$DR$5,1,12*(YEAR(I$3)-YEAR($B11))+MONTH(I$3)-MONTH($B11)+1),0)) -> 0 | J28: =IF($C11<>"Yes",0,IF(AND(J$3>=$B11,J$3<=EOMONTH($B11,119)),INDEX($C$5:$DR$5,1,12*(YEAR(J$3)-YEAR($B11))+MONTH(J$3)-MONTH($B11)+1),0)) -> 0 | ... DR28: =IF($C11<>"Yes",0,IF(AND(DR$3>=$B11,DR$3<=EOMONTH($B11,119)),INDEX($C$5:$DR$5,1,12*(YEAR(DR$3)-YEAR($B11))+MONTH(DR$3)-MONTH($B11)+1),0)) -> 0
A29: P2 Sales | C29: =IF($C11<>"Yes",0,IF(AND(C$3>=$B11,C$3<=EOMONTH($B11,119)),INDEX($C$6:$DR$6,1,12*(YEAR(C$3)-YEAR($B11))+MONTH(C$3)-MONTH($B11)+1),0)) -> 0 | D29: =IF($C11<>"Yes",0,IF(AND(D$3>=$B11,D$3<=EOMONTH($B11,119)),INDEX($C$6:$DR$6,1,12*(YEAR(D$3)-YEAR($B11))+MONTH(D$3)-MONTH($B11)+1),0)) -> 0 | E29: =IF($C11<>"Yes",0,IF(AND(E$3>=$B11,E$3<=EOMONTH($B11,119)),INDEX($C$6:$DR$6,1,12*(YEAR(E$3)-YEAR($B11))+MONTH(E$3)-MONTH($B11)+1),0)) -> 0 | F29: =IF($C11<>"Yes",0,IF(AND(F$3>=$B11,F$3<=EOMONTH($B11,119)),INDEX($C$6:$DR$6,1,12*(YEAR(F$3)-YEAR($B11))+MONTH(F$3)-MONTH($B11)+1),0)) -> 0 | G29: =IF($C11<>"Yes",0,IF(AND(G$3>=$B11,G$3<=EOMONTH($B11,119)),INDEX($C$6:$DR$6,1,12*(YEAR(G$3)-YEAR($B11))+MONTH(G$3)-MONTH($B11)+1),0)) -> 0 | H29: =IF($C11<>"Yes",0,IF(AND(H$3>=$B11,H$3<=EOMONTH($B11,119)),INDEX($C$6:$DR$6,1,12*(YEAR(H$3)-YEAR($B11))+MONTH(H$3)-MONTH($B11)+1),0)) -> 0 | I29: =IF($C11<>"Yes",0,IF(AND(I$3>=$B11,I$3<=EOMONTH($B11,119)),INDEX($C$6:$DR$6,1,12*(YEAR(I$3)-YEAR($B11))+MONTH(I$3)-MONTH($B11)+1),0)) -> 0 | J29: =IF($C11<>"Yes",0,IF(AND(J$3>=$B11,J$3<=EOMONTH($B11,119)),INDEX($C$6:$DR$6,1,12*(YEAR(J$3)-YEAR($B11))+MONTH(J$3)-MONTH($B11)+1),0)) -> 0 | ... DR29: =IF($C11<>"Yes",0,IF(AND(DR$3>=$B11,DR$3<=EOMONTH($B11,119)),INDEX($C$6:$DR$6,1,12*(YEAR(DR$3)-YEAR($B11))+MONTH(DR$3)-MONTH($B11)+1),0)) -> 0
A30: P2 ClosingPay | C30: =IF($C11<>"Yes",0,IF(AND(C$3>=$B11,C$3<=EOMONTH($B11,119)),INDEX($C$7:$DR$7,1,12*(YEAR(C$3)-YEAR($B11))+MONTH(C$3)-MONTH($B11)+1),0)) -> 0 | D30: =IF($C11<>"Yes",0,IF(AND(D$3>=$B11,D$3<=EOMONTH($B11,119)),INDEX($C$7:$DR$7,1,12*(YEAR(D$3)-YEAR($B11))+MONTH(D$3)-MONTH($B11)+1),0)) -> 0 | E30: =IF($C11<>"Yes",0,IF(AND(E$3>=$B11,E$3<=EOMONTH($B11,119)),INDEX($C$7:$DR$7,1,12*(YEAR(E$3)-YEAR($B11))+MONTH(E$3)-MONTH($B11)+1),0)) -> 0 | F30: =IF($C11<>"Yes",0,IF(AND(F$3>=$B11,F$3<=EOMONTH($B11,119)),INDEX($C$7:$DR$7,1,12*(YEAR(F$3)-YEAR($B11))+MONTH(F$3)-MONTH($B11)+1),0)) -> 0 | G30: =IF($C11<>"Yes",0,IF(AND(G$3>=$B11,G$3<=EOMONTH($B11,119)),INDEX($C$7:$DR$7,1,12*(YEAR(G$3)-YEAR($B11))+MONTH(G$3)-MONTH($B11)+1),0)) -> 0 | H30: =IF($C11<>"Yes",0,IF(AND(H$3>=$B11,H$3<=EOMONTH($B11,119)),INDEX($C$7:$DR$7,1,12*(YEAR(H$3)-YEAR($B11))+MONTH(H$3)-MONTH($B11)+1),0)) -> 0 | I30: =IF($C11<>"Yes",0,IF(AND(I$3>=$B11,I$3<=EOMONTH($B11,119)),INDEX($C$7:$DR$7,1,12*(YEAR(I$3)-YEAR($B11))+MONTH(I$3)-MONTH($B11)+1),0)) -> 0 | J30: =IF($C11<>"Yes",0,IF(AND(J$3>=$B11,J$3<=EOMONTH($B11,119)),INDEX($C$7:$DR$7,1,12*(YEAR(J$3)-YEAR($B11))+MONTH(J$3)-MONTH($B11)+1),0)) -> 0 | ... DR30: =IF($C11<>"Yes",0,IF(AND(DR$3>=$B11,DR$3<=EOMONTH($B11,119)),INDEX($C$7:$DR$7,1,12*(YEAR(DR$3)-YEAR($B11))+MONTH(DR$3)-MONTH($B11)+1),0)) -> 0
A31: P3 DevCF | C31: =IF($C12<>"Yes",0,IF(AND(C$3>=$B12,C$3<=EOMONTH($B12,119)),INDEX($C$5:$DR$5,1,12*(YEAR(C$3)-YEAR($B12))+MONTH(C$3)-MONTH($B12)+1),0)) -> 0 | D31: =IF($C12<>"Yes",0,IF(AND(D$3>=$B12,D$3<=EOMONTH($B12,119)),INDEX($C$5:$DR$5,1,12*(YEAR(D$3)-YEAR($B12))+MONTH(D$3)-MONTH($B12)+1),0)) -> 0 | E31: =IF($C12<>"Yes",0,IF(AND(E$3>=$B12,E$3<=EOMONTH($B12,119)),INDEX($C$5:$DR$5,1,12*(YEAR(E$3)-YEAR($B12))+MONTH(E$3)-MONTH($B12)+1),0)) -> 0 | F31: =IF($C12<>"Yes",0,IF(AND(F$3>=$B12,F$3<=EOMONTH($B12,119)),INDEX($C$5:$DR$5,1,12*(YEAR(F$3)-YEAR($B12))+MONTH(F$3)-MONTH($B12)+1),0)) -> 0 | G31: =IF($C12<>"Yes",0,IF(AND(G$3>=$B12,G$3<=EOMONTH($B12,119)),INDEX($C$5:$DR$5,1,12*(YEAR(G$3)-YEAR($B12))+MONTH(G$3)-MONTH($B12)+1),0)) -> 0 | H31: =IF($C12<>"Yes",0,IF(AND(H$3>=$B12,H$3<=EOMONTH($B12,119)),INDEX($C$5:$DR$5,1,12*(YEAR(H$3)-YEAR($B12))+MONTH(H$3)-MONTH($B12)+1),0)) -> 0 | I31: =IF($C12<>"Yes",0,IF(AND(I$3>=$B12,I$3<=EOMONTH($B12,119)),INDEX($C$5:$DR$5,1,12*(YEAR(I$3)-YEAR($B12))+MONTH(I$3)-MONTH($B12)+1),0)) -> 0 | J31: =IF($C12<>"Yes",0,IF(AND(J$3>=$B12,J$3<=EOMONTH($B12,119)),INDEX($C$5:$DR$5,1,12*(YEAR(J$3)-YEAR($B12))+MONTH(J$3)-MONTH($B12)+1),0)) -> 0 | ... DR31: =IF($C12<>"Yes",0,IF(AND(DR$3>=$B12,DR$3<=EOMONTH($B12,119)),INDEX($C$5:$DR$5,1,12*(YEAR(DR$3)-YEAR($B12))+MONTH(DR$3)-MONTH($B12)+1),0)) -> 0
A32: P3 Sales | C32: =IF($C12<>"Yes",0,IF(AND(C$3>=$B12,C$3<=EOMONTH($B12,119)),INDEX($C$6:$DR$6,1,12*(YEAR(C$3)-YEAR($B12))+MONTH(C$3)-MONTH($B12)+1),0)) -> 0 | D32: =IF($C12<>"Yes",0,IF(AND(D$3>=$B12,D$3<=EOMONTH($B12,119)),INDEX($C$6:$DR$6,1,12*(YEAR(D$3)-YEAR($B12))+MONTH(D$3)-MONTH($B12)+1),0)) -> 0 | E32: =IF($C12<>"Yes",0,IF(AND(E$3>=$B12,E$3<=EOMONTH($B12,119)),INDEX($C$6:$DR$6,1,12*(YEAR(E$3)-YEAR($B12))+MONTH(E$3)-MONTH($B12)+1),0)) -> 0 | F32: =IF($C12<>"Yes",0,IF(AND(F$3>=$B12,F$3<=EOMONTH($B12,119)),INDEX($C$6:$DR$6,1,12*(YEAR(F$3)-YEAR($B12))+MONTH(F$3)-MONTH($B12)+1),0)) -> 0 | G32: =IF($C12<>"Yes",0,IF(AND(G$3>=$B12,G$3<=EOMONTH($B12,119)),INDEX($C$6:$DR$6,1,12*(YEAR(G$3)-YEAR($B12))+MONTH(G$3)-MONTH($B12)+1),0)) -> 0 | H32: =IF($C12<>"Yes",0,IF(AND(H$3>=$B12,H$3<=EOMONTH($B12,119)),INDEX($C$6:$DR$6,1,12*(YEAR(H$3)-YEAR($B12))+MONTH(H$3)-MONTH($B12)+1),0)) -> 0 | I32: =IF($C12<>"Yes",0,IF(AND(I$3>=$B12,I$3<=EOMONTH($B12,119)),INDEX($C$6:$DR$6,1,12*(YEAR(I$3)-YEAR($B12))+MONTH(I$3)-MONTH($B12)+1),0)) -> 0 | J32: =IF($C12<>"Yes",0,IF(AND(J$3>=$B12,J$3<=EOMONTH($B12,119)),INDEX($C$6:$DR$6,1,12*(YEAR(J$3)-YEAR($B12))+MONTH(J$3)-MONTH($B12)+1),0)) -> 0 | ... DR32: =IF($C12<>"Yes",0,IF(AND(DR$3>=$B12,DR$3<=EOMONTH($B12,119)),INDEX($C$6:$DR$6,1,12*(YEAR(DR$3)-YEAR($B12))+MONTH(DR$3)-MONTH($B12)+1),0)) -> 0
A33: P3 ClosingPay | C33: =IF($C12<>"Yes",0,IF(AND(C$3>=$B12,C$3<=EOMONTH($B12,119)),INDEX($C$7:$DR$7,1,12*(YEAR(C$3)-YEAR($B12))+MONTH(C$3)-MONTH($B12)+1),0)) -> 0 | D33: =IF($C12<>"Yes",0,IF(AND(D$3>=$B12,D$3<=EOMONTH($B12,119)),INDEX($C$7:$DR$7,1,12*(YEAR(D$3)-YEAR($B12))+MONTH(D$3)-MONTH($B12)+1),0)) -> 0 | E33: =IF($C12<>"Yes",0,IF(AND(E$3>=$B12,E$3<=EOMONTH($B12,119)),INDEX($C$7:$DR$7,1,12*(YEAR(E$3)-YEAR($B12))+MONTH(E$3)-MONTH($B12)+1),0)) -> 0 | F33: =IF($C12<>"Yes",0,IF(AND(F$3>=$B12,F$3<=EOMONTH($B12,119)),INDEX($C$7:$DR$7,1,12*(YEAR(F$3)-YEAR($B12))+MONTH(F$3)-MONTH($B12)+1),0)) -> 0 | G33: =IF($C12<>"Yes",0,IF(AND(G$3>=$B12,G$3<=EOMONTH($B12,119)),INDEX($C$7:$DR$7,1,12*(YEAR(G$3)-YEAR($B12))+MONTH(G$3)-MONTH($B12)+1),0)) -> 0 | H33: =IF($C12<>"Yes",0,IF(AND(H$3>=$B12,H$3<=EOMONTH($B12,119)),INDEX($C$7:$DR$7,1,12*(YEAR(H$3)-YEAR($B12))+MONTH(H$3)-MONTH($B12)+1),0)) -> 0 | I33: =IF($C12<>"Yes",0,IF(AND(I$3>=$B12,I$3<=EOMONTH($B12,119)),INDEX($C$7:$DR$7,1,12*(YEAR(I$3)-YEAR($B12))+MONTH(I$3)-MONTH($B12)+1),0)) -> 0 | J33: =IF($C12<>"Yes",0,IF(AND(J$3>=$B12,J$3<=EOMONTH($B12,119)),INDEX($C$7:$DR$7,1,12*(YEAR(J$3)-YEAR($B12))+MONTH(J$3)-MONTH($B12)+1),0)) -> 0 | ... DR33: =IF($C12<>"Yes",0,IF(AND(DR$3>=$B12,DR$3<=EOMONTH($B12,119)),INDEX($C$7:$DR$7,1,12*(YEAR(DR$3)-YEAR($B12))+MONTH(DR$3)-MONTH($B12)+1),0)) -> 0
A34: P4 DevCF | C34: =IF($C13<>"Yes",0,IF(AND(C$3>=$B13,C$3<=EOMONTH($B13,119)),INDEX($C$5:$DR$5,1,12*(YEAR(C$3)-YEAR($B13))+MONTH(C$3)-MONTH($B13)+1),0)) -> 0 | D34: =IF($C13<>"Yes",0,IF(AND(D$3>=$B13,D$3<=EOMONTH($B13,119)),INDEX($C$5:$DR$5,1,12*(YEAR(D$3)-YEAR($B13))+MONTH(D$3)-MONTH($B13)+1),0)) -> 0 | E34: =IF($C13<>"Yes",0,IF(AND(E$3>=$B13,E$3<=EOMONTH($B13,119)),INDEX($C$5:$DR$5,1,12*(YEAR(E$3)-YEAR($B13))+MONTH(E$3)-MONTH($B13)+1),0)) -> 0 | F34: =IF($C13<>"Yes",0,IF(AND(F$3>=$B13,F$3<=EOMONTH($B13,119)),INDEX($C$5:$DR$5,1,12*(YEAR(F$3)-YEAR($B13))+MONTH(F$3)-MONTH($B13)+1),0)) -> 0 | G34: =IF($C13<>"Yes",0,IF(AND(G$3>=$B13,G$3<=EOMONTH($B13,119)),INDEX($C$5:$DR$5,1,12*(YEAR(G$3)-YEAR($B13))+MONTH(G$3)-MONTH($B13)+1),0)) -> 0 | H34: =IF($C13<>"Yes",0,IF(AND(H$3>=$B13,H$3<=EOMONTH($B13,119)),INDEX($C$5:$DR$5,1,12*(YEAR(H$3)-YEAR($B13))+MONTH(H$3)-MONTH($B13)+1),0)) -> 0 | I34: =IF($C13<>"Yes",0,IF(AND(I$3>=$B13,I$3<=EOMONTH($B13,119)),INDEX($C$5:$DR$5,1,12*(YEAR(I$3)-YEAR($B13))+MONTH(I$3)-MONTH($B13)+1),0)) -> 0 | J34: =IF($C13<>"Yes",0,IF(AND(J$3>=$B13,J$3<=EOMONTH($B13,119)),INDEX($C$5:$DR$5,1,12*(YEAR(J$3)-YEAR($B13))+MONTH(J$3)-MONTH($B13)+1),0)) -> 0 | ... DR34: =IF($C13<>"Yes",0,IF(AND(DR$3>=$B13,DR$3<=EOMONTH($B13,119)),INDEX($C$5:$DR$5,1,12*(YEAR(DR$3)-YEAR($B13))+MONTH(DR$3)-MONTH($B13)+1),0)) -> 0
A35: P4 Sales | C35: =IF($C13<>"Yes",0,IF(AND(C$3>=$B13,C$3<=EOMONTH($B13,119)),INDEX($C$6:$DR$6,1,12*(YEAR(C$3)-YEAR($B13))+MONTH(C$3)-MONTH($B13)+1),0)) -> 0 | D35: =IF($C13<>"Yes",0,IF(AND(D$3>=$B13,D$3<=EOMONTH($B13,119)),INDEX($C$6:$DR$6,1,12*(YEAR(D$3)-YEAR($B13))+MONTH(D$3)-MONTH($B13)+1),0)) -> 0 | E35: =IF($C13<>"Yes",0,IF(AND(E$3>=$B13,E$3<=EOMONTH($B13,119)),INDEX($C$6:$DR$6,1,12*(YEAR(E$3)-YEAR($B13))+MONTH(E$3)-MONTH($B13)+1),0)) -> 0 | F35: =IF($C13<>"Yes",0,IF(AND(F$3>=$B13,F$3<=EOMONTH($B13,119)),INDEX($C$6:$DR$6,1,12*(YEAR(F$3)-YEAR($B13))+MONTH(F$3)-MONTH($B13)+1),0)) -> 0 | G35: =IF($C13<>"Yes",0,IF(AND(G$3>=$B13,G$3<=EOMONTH($B13,119)),INDEX($C$6:$DR$6,1,12*(YEAR(G$3)-YEAR($B13))+MONTH(G$3)-MONTH($B13)+1),0)) -> 0 | H35: =IF($C13<>"Yes",0,IF(AND(H$3>=$B13,H$3<=EOMONTH($B13,119)),INDEX($C$6:$DR$6,1,12*(YEAR(H$3)-YEAR($B13))+MONTH(H$3)-MONTH($B13)+1),0)) -> 0 | I35: =IF($C13<>"Yes",0,IF(AND(I$3>=$B13,I$3<=EOMONTH($B13,119)),INDEX($C$6:$DR$6,1,12*(YEAR(I$3)-YEAR($B13))+MONTH(I$3)-MONTH($B13)+1),0)) -> 0 | J35: =IF($C13<>"Yes",0,IF(AND(J$3>=$B13,J$3<=EOMONTH($B13,119)),INDEX($C$6:$DR$6,1,12*(YEAR(J$3)-YEAR($B13))+MONTH(J$3)-MONTH($B13)+1),0)) -> 0 | ... DR35: =IF($C13<>"Yes",0,IF(AND(DR$3>=$B13,DR$3<=EOMONTH($B13,119)),INDEX($C$6:$DR$6,1,12*(YEAR(DR$3)-YEAR($B13))+MONTH(DR$3)-MONTH($B13)+1),0)) -> 0
A36: P4 ClosingPay | C36: =IF($C13<>"Yes",0,IF(AND(C$3>=$B13,C$3<=EOMONTH($B13,119)),INDEX($C$7:$DR$7,1,12*(YEAR(C$3)-YEAR($B13))+MONTH(C$3)-MONTH($B13)+1),0)) -> 0 | D36: =IF($C13<>"Yes",0,IF(AND(D$3>=$B13,D$3<=EOMONTH($B13,119)),INDEX($C$7:$DR$7,1,12*(YEAR(D$3)-YEAR($B13))+MONTH(D$3)-MONTH($B13)+1),0)) -> 0 | E36: =IF($C13<>"Yes",0,IF(AND(E$3>=$B13,E$3<=EOMONTH($B13,119)),INDEX($C$7:$DR$7,1,12*(YEAR(E$3)-YEAR($B13))+MONTH(E$3)-MONTH($B13)+1),0)) -> 0 | F36: =IF($C13<>"Yes",0,IF(AND(F$3>=$B13,F$3<=EOMONTH($B13,119)),INDEX($C$7:$DR$7,1,12*(YEAR(F$3)-YEAR($B13))+MONTH(F$3)-MONTH($B13)+1),0)) -> 0 | G36: =IF($C13<>"Yes",0,IF(AND(G$3>=$B13,G$3<=EOMONTH($B13,119)),INDEX($C$7:$DR$7,1,12*(YEAR(G$3)-YEAR($B13))+MONTH(G$3)-MONTH($B13)+1),0)) -> 0 | H36: =IF($C13<>"Yes",0,IF(AND(H$3>=$B13,H$3<=EOMONTH($B13,119)),INDEX($C$7:$DR$7,1,12*(YEAR(H$3)-YEAR($B13))+MONTH(H$3)-MONTH($B13)+1),0)) -> 0 | I36: =IF($C13<>"Yes",0,IF(AND(I$3>=$B13,I$3<=EOMONTH($B13,119)),INDEX($C$7:$DR$7,1,12*(YEAR(I$3)-YEAR($B13))+MONTH(I$3)-MONTH($B13)+1),0)) -> 0 | J36: =IF($C13<>"Yes",0,IF(AND(J$3>=$B13,J$3<=EOMONTH($B13,119)),INDEX($C$7:$DR$7,1,12*(YEAR(J$3)-YEAR($B13))+MONTH(J$3)-MONTH($B13)+1),0)) -> 0 | ... DR36: =IF($C13<>"Yes",0,IF(AND(DR$3>=$B13,DR$3<=EOMONTH($B13,119)),INDEX($C$7:$DR$7,1,12*(YEAR(DR$3)-YEAR($B13))+MONTH(DR$3)-MONTH($B13)+1),0)) -> 0
A37: P5 DevCF | C37: =IF($C14<>"Yes",0,IF(AND(C$3>=$B14,C$3<=EOMONTH($B14,119)),INDEX($C$5:$DR$5,1,12*(YEAR(C$3)-YEAR($B14))+MONTH(C$3)-MONTH($B14)+1),0)) -> 0 | D37: =IF($C14<>"Yes",0,IF(AND(D$3>=$B14,D$3<=EOMONTH($B14,119)),INDEX($C$5:$DR$5,1,12*(YEAR(D$3)-YEAR($B14))+MONTH(D$3)-MONTH($B14)+1),0)) -> 0 | E37: =IF($C14<>"Yes",0,IF(AND(E$3>=$B14,E$3<=EOMONTH($B14,119)),INDEX($C$5:$DR$5,1,12*(YEAR(E$3)-YEAR($B14))+MONTH(E$3)-MONTH($B14)+1),0)) -> 0 | F37: =IF($C14<>"Yes",0,IF(AND(F$3>=$B14,F$3<=EOMONTH($B14,119)),INDEX($C$5:$DR$5,1,12*(YEAR(F$3)-YEAR($B14))+MONTH(F$3)-MONTH($B14)+1),0)) -> 0 | G37: =IF($C14<>"Yes",0,IF(AND(G$3>=$B14,G$3<=EOMONTH($B14,119)),INDEX($C$5:$DR$5,1,12*(YEAR(G$3)-YEAR($B14))+MONTH(G$3)-MONTH($B14)+1),0)) -> 0 | H37: =IF($C14<>"Yes",0,IF(AND(H$3>=$B14,H$3<=EOMONTH($B14,119)),INDEX($C$5:$DR$5,1,12*(YEAR(H$3)-YEAR($B14))+MONTH(H$3)-MONTH($B14)+1),0)) -> 0 | I37: =IF($C14<>"Yes",0,IF(AND(I$3>=$B14,I$3<=EOMONTH($B14,119)),INDEX($C$5:$DR$5,1,12*(YEAR(I$3)-YEAR($B14))+MONTH(I$3)-MONTH($B14)+1),0)) -> 0 | J37: =IF($C14<>"Yes",0,IF(AND(J$3>=$B14,J$3<=EOMONTH($B14,119)),INDEX($C$5:$DR$5,1,12*(YEAR(J$3)-YEAR($B14))+MONTH(J$3)-MONTH($B14)+1),0)) -> 0 | ... DR37: =IF($C14<>"Yes",0,IF(AND(DR$3>=$B14,DR$3<=EOMONTH($B14,119)),INDEX($C$5:$DR$5,1,12*(YEAR(DR$3)-YEAR($B14))+MONTH(DR$3)-MONTH($B14)+1),0)) -> 0
A38: P5 Sales | C38: =IF($C14<>"Yes",0,IF(AND(C$3>=$B14,C$3<=EOMONTH($B14,119)),INDEX($C$6:$DR$6,1,12*(YEAR(C$3)-YEAR($B14))+MONTH(C$3)-MONTH($B14)+1),0)) -> 0 | D38: =IF($C14<>"Yes",0,IF(AND(D$3>=$B14,D$3<=EOMONTH($B14,119)),INDEX($C$6:$DR$6,1,12*(YEAR(D$3)-YEAR($B14))+MONTH(D$3)-MONTH($B14)+1),0)) -> 0 | E38: =IF($C14<>"Yes",0,IF(AND(E$3>=$B14,E$3<=EOMONTH($B14,119)),INDEX($C$6:$DR$6,1,12*(YEAR(E$3)-YEAR($B14))+MONTH(E$3)-MONTH($B14)+1),0)) -> 0 | F38: =IF($C14<>"Yes",0,IF(AND(F$3>=$B14,F$3<=EOMONTH($B14,119)),INDEX($C$6:$DR$6,1,12*(YEAR(F$3)-YEAR($B14))+MONTH(F$3)-MONTH($B14)+1),0)) -> 0 | G38: =IF($C14<>"Yes",0,IF(AND(G$3>=$B14,G$3<=EOMONTH($B14,119)),INDEX($C$6:$DR$6,1,12*(YEAR(G$3)-YEAR($B14))+MONTH(G$3)-MONTH($B14)+1),0)) -> 0 | H38: =IF($C14<>"Yes",0,IF(AND(H$3>=$B14,H$3<=EOMONTH($B14,119)),INDEX($C$6:$DR$6,1,12*(YEAR(H$3)-YEAR($B14))+MONTH(H$3)-MONTH($B14)+1),0)) -> 0 | I38: =IF($C14<>"Yes",0,IF(AND(I$3>=$B14,I$3<=EOMONTH($B14,119)),INDEX($C$6:$DR$6,1,12*(YEAR(I$3)-YEAR($B14))+MONTH(I$3)-MONTH($B14)+1),0)) -> 0 | J38: =IF($C14<>"Yes",0,IF(AND(J$3>=$B14,J$3<=EOMONTH($B14,119)),INDEX($C$6:$DR$6,1,12*(YEAR(J$3)-YEAR($B14))+MONTH(J$3)-MONTH($B14)+1),0)) -> 0 | ... DR38: =IF($C14<>"Yes",0,IF(AND(DR$3>=$B14,DR$3<=EOMONTH($B14,119)),INDEX($C$6:$DR$6,1,12*(YEAR(DR$3)-YEAR($B14))+MONTH(DR$3)-MONTH($B14)+1),0)) -> 0
A39: P5 ClosingPay | C39: =IF($C14<>"Yes",0,IF(AND(C$3>=$B14,C$3<=EOMONTH($B14,119)),INDEX($C$7:$DR$7,1,12*(YEAR(C$3)-YEAR($B14))+MONTH(C$3)-MONTH($B14)+1),0)) -> 0 | D39: =IF($C14<>"Yes",0,IF(AND(D$3>=$B14,D$3<=EOMONTH($B14,119)),INDEX($C$7:$DR$7,1,12*(YEAR(D$3)-YEAR($B14))+MONTH(D$3)-MONTH($B14)+1),0)) -> 0 | E39: =IF($C14<>"Yes",0,IF(AND(E$3>=$B14,E$3<=EOMONTH($B14,119)),INDEX($C$7:$DR$7,1,12*(YEAR(E$3)-YEAR($B14))+MONTH(E$3)-MONTH($B14)+1),0)) -> 0 | F39: =IF($C14<>"Yes",0,IF(AND(F$3>=$B14,F$3<=EOMONTH($B14,119)),INDEX($C$7:$DR$7,1,12*(YEAR(F$3)-YEAR($B14))+MONTH(F$3)-MONTH($B14)+1),0)) -> 0 | G39: =IF($C14<>"Yes",0,IF(AND(G$3>=$B14,G$3<=EOMONTH($B14,119)),INDEX($C$7:$DR$7,1,12*(YEAR(G$3)-YEAR($B14))+MONTH(G$3)-MONTH($B14)+1),0)) -> 0 | H39: =IF($C14<>"Yes",0,IF(AND(H$3>=$B14,H$3<=EOMONTH($B14,119)),INDEX($C$7:$DR$7,1,12*(YEAR(H$3)-YEAR($B14))+MONTH(H$3)-MONTH($B14)+1),0)) -> 0 | I39: =IF($C14<>"Yes",0,IF(AND(I$3>=$B14,I$3<=EOMONTH($B14,119)),INDEX($C$7:$DR$7,1,12*(YEAR(I$3)-YEAR($B14))+MONTH(I$3)-MONTH($B14)+1),0)) -> 0 | J39: =IF($C14<>"Yes",0,IF(AND(J$3>=$B14,J$3<=EOMONTH($B14,119)),INDEX($C$7:$DR$7,1,12*(YEAR(J$3)-YEAR($B14))+MONTH(J$3)-MONTH($B14)+1),0)) -> 0 | ... DR39: =IF($C14<>"Yes",0,IF(AND(DR$3>=$B14,DR$3<=EOMONTH($B14,119)),INDEX($C$7:$DR$7,1,12*(YEAR(DR$3)-YEAR($B14))+MONTH(DR$3)-MONTH($B14)+1),0)) -> 0
A40: P6 DevCF | C40: =IF($C15<>"Yes",0,IF(AND(C$3>=$B15,C$3<=EOMONTH($B15,119)),INDEX($C$5:$DR$5,1,12*(YEAR(C$3)-YEAR($B15))+MONTH(C$3)-MONTH($B15)+1),0)) -> 0 | D40: =IF($C15<>"Yes",0,IF(AND(D$3>=$B15,D$3<=EOMONTH($B15,119)),INDEX($C$5:$DR$5,1,12*(YEAR(D$3)-YEAR($B15))+MONTH(D$3)-MONTH($B15)+1),0)) -> 0 | E40: =IF($C15<>"Yes",0,IF(AND(E$3>=$B15,E$3<=EOMONTH($B15,119)),INDEX($C$5:$DR$5,1,12*(YEAR(E$3)-YEAR($B15))+MONTH(E$3)-MONTH($B15)+1),0)) -> 0 | F40: =IF($C15<>"Yes",0,IF(AND(F$3>=$B15,F$3<=EOMONTH($B15,119)),INDEX($C$5:$DR$5,1,12*(YEAR(F$3)-YEAR($B15))+MONTH(F$3)-MONTH($B15)+1),0)) -> 0 | G40: =IF($C15<>"Yes",0,IF(AND(G$3>=$B15,G$3<=EOMONTH($B15,119)),INDEX($C$5:$DR$5,1,12*(YEAR(G$3)-YEAR($B15))+MONTH(G$3)-MONTH($B15)+1),0)) -> 0 | H40: =IF($C15<>"Yes",0,IF(AND(H$3>=$B15,H$3<=EOMONTH($B15,119)),INDEX($C$5:$DR$5,1,12*(YEAR(H$3)-YEAR($B15))+MONTH(H$3)-MONTH($B15)+1),0)) -> 0 | I40: =IF($C15<>"Yes",0,IF(AND(I$3>=$B15,I$3<=EOMONTH($B15,119)),INDEX($C$5:$DR$5,1,12*(YEAR(I$3)-YEAR($B15))+MONTH(I$3)-MONTH($B15)+1),0)) -> 0 | J40: =IF($C15<>"Yes",0,IF(AND(J$3>=$B15,J$3<=EOMONTH($B15,119)),INDEX($C$5:$DR$5,1,12*(YEAR(J$3)-YEAR($B15))+MONTH(J$3)-MONTH($B15)+1),0)) -> 0 | ... DR40: =IF($C15<>"Yes",0,IF(AND(DR$3>=$B15,DR$3<=EOMONTH($B15,119)),INDEX($C$5:$DR$5,1,12*(YEAR(DR$3)-YEAR($B15))+MONTH(DR$3)-MONTH($B15)+1),0)) -> 0
A41: P6 Sales | C41: =IF($C15<>"Yes",0,IF(AND(C$3>=$B15,C$3<=EOMONTH($B15,119)),INDEX($C$6:$DR$6,1,12*(YEAR(C$3)-YEAR($B15))+MONTH(C$3)-MONTH($B15)+1),0)) -> 0 | D41: =IF($C15<>"Yes",0,IF(AND(D$3>=$B15,D$3<=EOMONTH($B15,119)),INDEX($C$6:$DR$6,1,12*(YEAR(D$3)-YEAR($B15))+MONTH(D$3)-MONTH($B15)+1),0)) -> 0 | E41: =IF($C15<>"Yes",0,IF(AND(E$3>=$B15,E$3<=EOMONTH($B15,119)),INDEX($C$6:$DR$6,1,12*(YEAR(E$3)-YEAR($B15))+MONTH(E$3)-MONTH($B15)+1),0)) -> 0 | F41: =IF($C15<>"Yes",0,IF(AND(F$3>=$B15,F$3<=EOMONTH($B15,119)),INDEX($C$6:$DR$6,1,12*(YEAR(F$3)-YEAR($B15))+MONTH(F$3)-MONTH($B15)+1),0)) -> 0 | G41: =IF($C15<>"Yes",0,IF(AND(G$3>=$B15,G$3<=EOMONTH($B15,119)),INDEX($C$6:$DR$6,1,12*(YEAR(G$3)-YEAR($B15))+MONTH(G$3)-MONTH($B15)+1),0)) -> 0 | H41: =IF($C15<>"Yes",0,IF(AND(H$3>=$B15,H$3<=EOMONTH($B15,119)),INDEX($C$6:$DR$6,1,12*(YEAR(H$3)-YEAR($B15))+MONTH(H$3)-MONTH($B15)+1),0)) -> 0 | I41: =IF($C15<>"Yes",0,IF(AND(I$3>=$B15,I$3<=EOMONTH($B15,119)),INDEX($C$6:$DR$6,1,12*(YEAR(I$3)-YEAR($B15))+MONTH(I$3)-MONTH($B15)+1),0)) -> 0 | J41: =IF($C15<>"Yes",0,IF(AND(J$3>=$B15,J$3<=EOMONTH($B15,119)),INDEX($C$6:$DR$6,1,12*(YEAR(J$3)-YEAR($B15))+MONTH(J$3)-MONTH($B15)+1),0)) -> 0 | ... DR41: =IF($C15<>"Yes",0,IF(AND(DR$3>=$B15,DR$3<=EOMONTH($B15,119)),INDEX($C$6:$DR$6,1,12*(YEAR(DR$3)-YEAR($B15))+MONTH(DR$3)-MONTH($B15)+1),0)) -> 0
A42: P6 ClosingPay | C42: =IF($C15<>"Yes",0,IF(AND(C$3>=$B15,C$3<=EOMONTH($B15,119)),INDEX($C$7:$DR$7,1,12*(YEAR(C$3)-YEAR($B15))+MONTH(C$3)-MONTH($B15)+1),0)) -> 0 | D42: =IF($C15<>"Yes",0,IF(AND(D$3>=$B15,D$3<=EOMONTH($B15,119)),INDEX($C$7:$DR$7,1,12*(YEAR(D$3)-YEAR($B15))+MONTH(D$3)-MONTH($B15)+1),0)) -> 0 | E42: =IF($C15<>"Yes",0,IF(AND(E$3>=$B15,E$3<=EOMONTH($B15,119)),INDEX($C$7:$DR$7,1,12*(YEAR(E$3)-YEAR($B15))+MONTH(E$3)-MONTH($B15)+1),0)) -> 0 | F42: =IF($C15<>"Yes",0,IF(AND(F$3>=$B15,F$3<=EOMONTH($B15,119)),INDEX($C$7:$DR$7,1,12*(YEAR(F$3)-YEAR($B15))+MONTH(F$3)-MONTH($B15)+1),0)) -> 0 | G42: =IF($C15<>"Yes",0,IF(AND(G$3>=$B15,G$3<=EOMONTH($B15,119)),INDEX($C$7:$DR$7,1,12*(YEAR(G$3)-YEAR($B15))+MONTH(G$3)-MONTH($B15)+1),0)) -> 0 | H42: =IF($C15<>"Yes",0,IF(AND(H$3>=$B15,H$3<=EOMONTH($B15,119)),INDEX($C$7:$DR$7,1,12*(YEAR(H$3)-YEAR($B15))+MONTH(H$3)-MONTH($B15)+1),0)) -> 0 | I42: =IF($C15<>"Yes",0,IF(AND(I$3>=$B15,I$3<=EOMONTH($B15,119)),INDEX($C$7:$DR$7,1,12*(YEAR(I$3)-YEAR($B15))+MONTH(I$3)-MONTH($B15)+1),0)) -> 0 | J42: =IF($C15<>"Yes",0,IF(AND(J$3>=$B15,J$3<=EOMONTH($B15,119)),INDEX($C$7:$DR$7,1,12*(YEAR(J$3)-YEAR($B15))+MONTH(J$3)-MONTH($B15)+1),0)) -> 0 | ... DR42: =IF($C15<>"Yes",0,IF(AND(DR$3>=$B15,DR$3<=EOMONTH($B15,119)),INDEX($C$7:$DR$7,1,12*(YEAR(DR$3)-YEAR($B15))+MONTH(DR$3)-MONTH($B15)+1),0)) -> 0
A43: P7 DevCF | C43: =IF($C16<>"Yes",0,IF(AND(C$3>=$B16,C$3<=EOMONTH($B16,119)),INDEX($C$5:$DR$5,1,12*(YEAR(C$3)-YEAR($B16))+MONTH(C$3)-MONTH($B16)+1),0)) -> 0 | D43: =IF($C16<>"Yes",0,IF(AND(D$3>=$B16,D$3<=EOMONTH($B16,119)),INDEX($C$5:$DR$5,1,12*(YEAR(D$3)-YEAR($B16))+MONTH(D$3)-MONTH($B16)+1),0)) -> 0 | E43: =IF($C16<>"Yes",0,IF(AND(E$3>=$B16,E$3<=EOMONTH($B16,119)),INDEX($C$5:$DR$5,1,12*(YEAR(E$3)-YEAR($B16))+MONTH(E$3)-MONTH($B16)+1),0)) -> 0 | F43: =IF($C16<>"Yes",0,IF(AND(F$3>=$B16,F$3<=EOMONTH($B16,119)),INDEX($C$5:$DR$5,1,12*(YEAR(F$3)-YEAR($B16))+MONTH(F$3)-MONTH($B16)+1),0)) -> 0 | G43: =IF($C16<>"Yes",0,IF(AND(G$3>=$B16,G$3<=EOMONTH($B16,119)),INDEX($C$5:$DR$5,1,12*(YEAR(G$3)-YEAR($B16))+MONTH(G$3)-MONTH($B16)+1),0)) -> 0 | H43: =IF($C16<>"Yes",0,IF(AND(H$3>=$B16,H$3<=EOMONTH($B16,119)),INDEX($C$5:$DR$5,1,12*(YEAR(H$3)-YEAR($B16))+MONTH(H$3)-MONTH($B16)+1),0)) -> 0 | I43: =IF($C16<>"Yes",0,IF(AND(I$3>=$B16,I$3<=EOMONTH($B16,119)),INDEX($C$5:$DR$5,1,12*(YEAR(I$3)-YEAR($B16))+MONTH(I$3)-MONTH($B16)+1),0)) -> 0 | J43: =IF($C16<>"Yes",0,IF(AND(J$3>=$B16,J$3<=EOMONTH($B16,119)),INDEX($C$5:$DR$5,1,12*(YEAR(J$3)-YEAR($B16))+MONTH(J$3)-MONTH($B16)+1),0)) -> 0 | ... DR43: =IF($C16<>"Yes",0,IF(AND(DR$3>=$B16,DR$3<=EOMONTH($B16,119)),INDEX($C$5:$DR$5,1,12*(YEAR(DR$3)-YEAR($B16))+MONTH(DR$3)-MONTH($B16)+1),0)) -> 0
A44: P7 Sales | C44: =IF($C16<>"Yes",0,IF(AND(C$3>=$B16,C$3<=EOMONTH($B16,119)),INDEX($C$6:$DR$6,1,12*(YEAR(C$3)-YEAR($B16))+MONTH(C$3)-MONTH($B16)+1),0)) -> 0 | D44: =IF($C16<>"Yes",0,IF(AND(D$3>=$B16,D$3<=EOMONTH($B16,119)),INDEX($C$6:$DR$6,1,12*(YEAR(D$3)-YEAR($B16))+MONTH(D$3)-MONTH($B16)+1),0)) -> 0 | E44: =IF($C16<>"Yes",0,IF(AND(E$3>=$B16,E$3<=EOMONTH($B16,119)),INDEX($C$6:$DR$6,1,12*(YEAR(E$3)-YEAR($B16))+MONTH(E$3)-MONTH($B16)+1),0)) -> 0 | F44: =IF($C16<>"Yes",0,IF(AND(F$3>=$B16,F$3<=EOMONTH($B16,119)),INDEX($C$6:$DR$6,1,12*(YEAR(F$3)-YEAR($B16))+MONTH(F$3)-MONTH($B16)+1),0)) -> 0 | G44: =IF($C16<>"Yes",0,IF(AND(G$3>=$B16,G$3<=EOMONTH($B16,119)),INDEX($C$6:$DR$6,1,12*(YEAR(G$3)-YEAR($B16))+MONTH(G$3)-MONTH($B16)+1),0)) -> 0 | H44: =IF($C16<>"Yes",0,IF(AND(H$3>=$B16,H$3<=EOMONTH($B16,119)),INDEX($C$6:$DR$6,1,12*(YEAR(H$3)-YEAR($B16))+MONTH(H$3)-MONTH($B16)+1),0)) -> 0 | I44: =IF($C16<>"Yes",0,IF(AND(I$3>=$B16,I$3<=EOMONTH($B16,119)),INDEX($C$6:$DR$6,1,12*(YEAR(I$3)-YEAR($B16))+MONTH(I$3)-MONTH($B16)+1),0)) -> 0 | J44: =IF($C16<>"Yes",0,IF(AND(J$3>=$B16,J$3<=EOMONTH($B16,119)),INDEX($C$6:$DR$6,1,12*(YEAR(J$3)-YEAR($B16))+MONTH(J$3)-MONTH($B16)+1),0)) -> 0 | ... DR44: =IF($C16<>"Yes",0,IF(AND(DR$3>=$B16,DR$3<=EOMONTH($B16,119)),INDEX($C$6:$DR$6,1,12*(YEAR(DR$3)-YEAR($B16))+MONTH(DR$3)-MONTH($B16)+1),0)) -> 0
A45: P7 ClosingPay | C45: =IF($C16<>"Yes",0,IF(AND(C$3>=$B16,C$3<=EOMONTH($B16,119)),INDEX($C$7:$DR$7,1,12*(YEAR(C$3)-YEAR($B16))+MONTH(C$3)-MONTH($B16)+1),0)) -> 0 | D45: =IF($C16<>"Yes",0,IF(AND(D$3>=$B16,D$3<=EOMONTH($B16,119)),INDEX($C$7:$DR$7,1,12*(YEAR(D$3)-YEAR($B16))+MONTH(D$3)-MONTH($B16)+1),0)) -> 0 | E45: =IF($C16<>"Yes",0,IF(AND(E$3>=$B16,E$3<=EOMONTH($B16,119)),INDEX($C$7:$DR$7,1,12*(YEAR(E$3)-YEAR($B16))+MONTH(E$3)-MONTH($B16)+1),0)) -> 0 | F45: =IF($C16<>"Yes",0,IF(AND(F$3>=$B16,F$3<=EOMONTH($B16,119)),INDEX($C$7:$DR$7,1,12*(YEAR(F$3)-YEAR($B16))+MONTH(F$3)-MONTH($B16)+1),0)) -> 0 | G45: =IF($C16<>"Yes",0,IF(AND(G$3>=$B16,G$3<=EOMONTH($B16,119)),INDEX($C$7:$DR$7,1,12*(YEAR(G$3)-YEAR($B16))+MONTH(G$3)-MONTH($B16)+1),0)) -> 0 | H45: =IF($C16<>"Yes",0,IF(AND(H$3>=$B16,H$3<=EOMONTH($B16,119)),INDEX($C$7:$DR$7,1,12*(YEAR(H$3)-YEAR($B16))+MONTH(H$3)-MONTH($B16)+1),0)) -> 0 | I45: =IF($C16<>"Yes",0,IF(AND(I$3>=$B16,I$3<=EOMONTH($B16,119)),INDEX($C$7:$DR$7,1,12*(YEAR(I$3)-YEAR($B16))+MONTH(I$3)-MONTH($B16)+1),0)) -> 0 | J45: =IF($C16<>"Yes",0,IF(AND(J$3>=$B16,J$3<=EOMONTH($B16,119)),INDEX($C$7:$DR$7,1,12*(YEAR(J$3)-YEAR($B16))+MONTH(J$3)-MONTH($B16)+1),0)) -> 0 | ... DR45: =IF($C16<>"Yes",0,IF(AND(DR$3>=$B16,DR$3<=EOMONTH($B16,119)),INDEX($C$7:$DR$7,1,12*(YEAR(DR$3)-YEAR($B16))+MONTH(DR$3)-MONTH($B16)+1),0)) -> 0
A46: P8 DevCF | C46: =IF($C17<>"Yes",0,IF(AND(C$3>=$B17,C$3<=EOMONTH($B17,119)),INDEX($C$5:$DR$5,1,12*(YEAR(C$3)-YEAR($B17))+MONTH(C$3)-MONTH($B17)+1),0)) -> 0 | D46: =IF($C17<>"Yes",0,IF(AND(D$3>=$B17,D$3<=EOMONTH($B17,119)),INDEX($C$5:$DR$5,1,12*(YEAR(D$3)-YEAR($B17))+MONTH(D$3)-MONTH($B17)+1),0)) -> 0 | E46: =IF($C17<>"Yes",0,IF(AND(E$3>=$B17,E$3<=EOMONTH($B17,119)),INDEX($C$5:$DR$5,1,12*(YEAR(E$3)-YEAR($B17))+MONTH(E$3)-MONTH($B17)+1),0)) -> 0 | F46: =IF($C17<>"Yes",0,IF(AND(F$3>=$B17,F$3<=EOMONTH($B17,119)),INDEX($C$5:$DR$5,1,12*(YEAR(F$3)-YEAR($B17))+MONTH(F$3)-MONTH($B17)+1),0)) -> 0 | G46: =IF($C17<>"Yes",0,IF(AND(G$3>=$B17,G$3<=EOMONTH($B17,119)),INDEX($C$5:$DR$5,1,12*(YEAR(G$3)-YEAR($B17))+MONTH(G$3)-MONTH($B17)+1),0)) -> 0 | H46: =IF($C17<>"Yes",0,IF(AND(H$3>=$B17,H$3<=EOMONTH($B17,119)),INDEX($C$5:$DR$5,1,12*(YEAR(H$3)-YEAR($B17))+MONTH(H$3)-MONTH($B17)+1),0)) -> 0 | I46: =IF($C17<>"Yes",0,IF(AND(I$3>=$B17,I$3<=EOMONTH($B17,119)),INDEX($C$5:$DR$5,1,12*(YEAR(I$3)-YEAR($B17))+MONTH(I$3)-MONTH($B17)+1),0)) -> 0 | J46: =IF($C17<>"Yes",0,IF(AND(J$3>=$B17,J$3<=EOMONTH($B17,119)),INDEX($C$5:$DR$5,1,12*(YEAR(J$3)-YEAR($B17))+MONTH(J$3)-MONTH($B17)+1),0)) -> 0 | ... DR46: =IF($C17<>"Yes",0,IF(AND(DR$3>=$B17,DR$3<=EOMONTH($B17,119)),INDEX($C$5:$DR$5,1,12*(YEAR(DR$3)-YEAR($B17))+MONTH(DR$3)-MONTH($B17)+1),0)) -> 0
A47: P8 Sales | C47: =IF($C17<>"Yes",0,IF(AND(C$3>=$B17,C$3<=EOMONTH($B17,119)),INDEX($C$6:$DR$6,1,12*(YEAR(C$3)-YEAR($B17))+MONTH(C$3)-MONTH($B17)+1),0)) -> 0 | D47: =IF($C17<>"Yes",0,IF(AND(D$3>=$B17,D$3<=EOMONTH($B17,119)),INDEX($C$6:$DR$6,1,12*(YEAR(D$3)-YEAR($B17))+MONTH(D$3)-MONTH($B17)+1),0)) -> 0 | E47: =IF($C17<>"Yes",0,IF(AND(E$3>=$B17,E$3<=EOMONTH($B17,119)),INDEX($C$6:$DR$6,1,12*(YEAR(E$3)-YEAR($B17))+MONTH(E$3)-MONTH($B17)+1),0)) -> 0 | F47: =IF($C17<>"Yes",0,IF(AND(F$3>=$B17,F$3<=EOMONTH($B17,119)),INDEX($C$6:$DR$6,1,12*(YEAR(F$3)-YEAR($B17))+MONTH(F$3)-MONTH($B17)+1),0)) -> 0 | G47: =IF($C17<>"Yes",0,IF(AND(G$3>=$B17,G$3<=EOMONTH($B17,119)),INDEX($C$6:$DR$6,1,12*(YEAR(G$3)-YEAR($B17))+MONTH(G$3)-MONTH($B17)+1),0)) -> 0 | H47: =IF($C17<>"Yes",0,IF(AND(H$3>=$B17,H$3<=EOMONTH($B17,119)),INDEX($C$6:$DR$6,1,12*(YEAR(H$3)-YEAR($B17))+MONTH(H$3)-MONTH($B17)+1),0)) -> 0 | I47: =IF($C17<>"Yes",0,IF(AND(I$3>=$B17,I$3<=EOMONTH($B17,119)),INDEX($C$6:$DR$6,1,12*(YEAR(I$3)-YEAR($B17))+MONTH(I$3)-MONTH($B17)+1),0)) -> 0 | J47: =IF($C17<>"Yes",0,IF(AND(J$3>=$B17,J$3<=EOMONTH($B17,119)),INDEX($C$6:$DR$6,1,12*(YEAR(J$3)-YEAR($B17))+MONTH(J$3)-MONTH($B17)+1),0)) -> 0 | ... DR47: =IF($C17<>"Yes",0,IF(AND(DR$3>=$B17,DR$3<=EOMONTH($B17,119)),INDEX($C$6:$DR$6,1,12*(YEAR(DR$3)-YEAR($B17))+MONTH(DR$3)-MONTH($B17)+1),0)) -> 0
A48: P8 ClosingPay | C48: =IF($C17<>"Yes",0,IF(AND(C$3>=$B17,C$3<=EOMONTH($B17,119)),INDEX($C$7:$DR$7,1,12*(YEAR(C$3)-YEAR($B17))+MONTH(C$3)-MONTH($B17)+1),0)) -> 0 | D48: =IF($C17<>"Yes",0,IF(AND(D$3>=$B17,D$3<=EOMONTH($B17,119)),INDEX($C$7:$DR$7,1,12*(YEAR(D$3)-YEAR($B17))+MONTH(D$3)-MONTH($B17)+1),0)) -> 0 | E48: =IF($C17<>"Yes",0,IF(AND(E$3>=$B17,E$3<=EOMONTH($B17,119)),INDEX($C$7:$DR$7,1,12*(YEAR(E$3)-YEAR($B17))+MONTH(E$3)-MONTH($B17)+1),0)) -> 0 | F48: =IF($C17<>"Yes",0,IF(AND(F$3>=$B17,F$3<=EOMONTH($B17,119)),INDEX($C$7:$DR$7,1,12*(YEAR(F$3)-YEAR($B17))+MONTH(F$3)-MONTH($B17)+1),0)) -> 0 | G48: =IF($C17<>"Yes",0,IF(AND(G$3>=$B17,G$3<=EOMONTH($B17,119)),INDEX($C$7:$DR$7,1,12*(YEAR(G$3)-YEAR($B17))+MONTH(G$3)-MONTH($B17)+1),0)) -> 0 | H48: =IF($C17<>"Yes",0,IF(AND(H$3>=$B17,H$3<=EOMONTH($B17,119)),INDEX($C$7:$DR$7,1,12*(YEAR(H$3)-YEAR($B17))+MONTH(H$3)-MONTH($B17)+1),0)) -> 0 | I48: =IF($C17<>"Yes",0,IF(AND(I$3>=$B17,I$3<=EOMONTH($B17,119)),INDEX($C$7:$DR$7,1,12*(YEAR(I$3)-YEAR($B17))+MONTH(I$3)-MONTH($B17)+1),0)) -> 0 | J48: =IF($C17<>"Yes",0,IF(AND(J$3>=$B17,J$3<=EOMONTH($B17,119)),INDEX($C$7:$DR$7,1,12*(YEAR(J$3)-YEAR($B17))+MONTH(J$3)-MONTH($B17)+1),0)) -> 0 | ... DR48: =IF($C17<>"Yes",0,IF(AND(DR$3>=$B17,DR$3<=EOMONTH($B17,119)),INDEX($C$7:$DR$7,1,12*(YEAR(DR$3)-YEAR($B17))+MONTH(DR$3)-MONTH($B17)+1),0)) -> 0
A49: P9 DevCF | C49: =IF($C18<>"Yes",0,IF(AND(C$3>=$B18,C$3<=EOMONTH($B18,119)),INDEX($C$5:$DR$5,1,12*(YEAR(C$3)-YEAR($B18))+MONTH(C$3)-MONTH($B18)+1),0)) -> 0 | D49: =IF($C18<>"Yes",0,IF(AND(D$3>=$B18,D$3<=EOMONTH($B18,119)),INDEX($C$5:$DR$5,1,12*(YEAR(D$3)-YEAR($B18))+MONTH(D$3)-MONTH($B18)+1),0)) -> 0 | E49: =IF($C18<>"Yes",0,IF(AND(E$3>=$B18,E$3<=EOMONTH($B18,119)),INDEX($C$5:$DR$5,1,12*(YEAR(E$3)-YEAR($B18))+MONTH(E$3)-MONTH($B18)+1),0)) -> 0 | F49: =IF($C18<>"Yes",0,IF(AND(F$3>=$B18,F$3<=EOMONTH($B18,119)),INDEX($C$5:$DR$5,1,12*(YEAR(F$3)-YEAR($B18))+MONTH(F$3)-MONTH($B18)+1),0)) -> 0 | G49: =IF($C18<>"Yes",0,IF(AND(G$3>=$B18,G$3<=EOMONTH($B18,119)),INDEX($C$5:$DR$5,1,12*(YEAR(G$3)-YEAR($B18))+MONTH(G$3)-MONTH($B18)+1),0)) -> 0 | H49: =IF($C18<>"Yes",0,IF(AND(H$3>=$B18,H$3<=EOMONTH($B18,119)),INDEX($C$5:$DR$5,1,12*(YEAR(H$3)-YEAR($B18))+MONTH(H$3)-MONTH($B18)+1),0)) -> 0 | I49: =IF($C18<>"Yes",0,IF(AND(I$3>=$B18,I$3<=EOMONTH($B18,119)),INDEX($C$5:$DR$5,1,12*(YEAR(I$3)-YEAR($B18))+MONTH(I$3)-MONTH($B18)+1),0)) -> 0 | J49: =IF($C18<>"Yes",0,IF(AND(J$3>=$B18,J$3<=EOMONTH($B18,119)),INDEX($C$5:$DR$5,1,12*(YEAR(J$3)-YEAR($B18))+MONTH(J$3)-MONTH($B18)+1),0)) -> 0 | ... DR49: =IF($C18<>"Yes",0,IF(AND(DR$3>=$B18,DR$3<=EOMONTH($B18,119)),INDEX($C$5:$DR$5,1,12*(YEAR(DR$3)-YEAR($B18))+MONTH(DR$3)-MONTH($B18)+1),0)) -> 0
A50: P9 Sales | C50: =IF($C18<>"Yes",0,IF(AND(C$3>=$B18,C$3<=EOMONTH($B18,119)),INDEX($C$6:$DR$6,1,12*(YEAR(C$3)-YEAR($B18))+MONTH(C$3)-MONTH($B18)+1),0)) -> 0 | D50: =IF($C18<>"Yes",0,IF(AND(D$3>=$B18,D$3<=EOMONTH($B18,119)),INDEX($C$6:$DR$6,1,12*(YEAR(D$3)-YEAR($B18))+MONTH(D$3)-MONTH($B18)+1),0)) -> 0 | E50: =IF($C18<>"Yes",0,IF(AND(E$3>=$B18,E$3<=EOMONTH($B18,119)),INDEX($C$6:$DR$6,1,12*(YEAR(E$3)-YEAR($B18))+MONTH(E$3)-MONTH($B18)+1),0)) -> 0 | F50: =IF($C18<>"Yes",0,IF(AND(F$3>=$B18,F$3<=EOMONTH($B18,119)),INDEX($C$6:$DR$6,1,12*(YEAR(F$3)-YEAR($B18))+MONTH(F$3)-MONTH($B18)+1),0)) -> 0 | G50: =IF($C18<>"Yes",0,IF(AND(G$3>=$B18,G$3<=EOMONTH($B18,119)),INDEX($C$6:$DR$6,1,12*(YEAR(G$3)-YEAR($B18))+MONTH(G$3)-MONTH($B18)+1),0)) -> 0 | H50: =IF($C18<>"Yes",0,IF(AND(H$3>=$B18,H$3<=EOMONTH($B18,119)),INDEX($C$6:$DR$6,1,12*(YEAR(H$3)-YEAR($B18))+MONTH(H$3)-MONTH($B18)+1),0)) -> 0 | I50: =IF($C18<>"Yes",0,IF(AND(I$3>=$B18,I$3<=EOMONTH($B18,119)),INDEX($C$6:$DR$6,1,12*(YEAR(I$3)-YEAR($B18))+MONTH(I$3)-MONTH($B18)+1),0)) -> 0 | J50: =IF($C18<>"Yes",0,IF(AND(J$3>=$B18,J$3<=EOMONTH($B18,119)),INDEX($C$6:$DR$6,1,12*(YEAR(J$3)-YEAR($B18))+MONTH(J$3)-MONTH($B18)+1),0)) -> 0 | ... DR50: =IF($C18<>"Yes",0,IF(AND(DR$3>=$B18,DR$3<=EOMONTH($B18,119)),INDEX($C$6:$DR$6,1,12*(YEAR(DR$3)-YEAR($B18))+MONTH(DR$3)-MONTH($B18)+1),0)) -> 0
A51: P9 ClosingPay | C51: =IF($C18<>"Yes",0,IF(AND(C$3>=$B18,C$3<=EOMONTH($B18,119)),INDEX($C$7:$DR$7,1,12*(YEAR(C$3)-YEAR($B18))+MONTH(C$3)-MONTH($B18)+1),0)) -> 0 | D51: =IF($C18<>"Yes",0,IF(AND(D$3>=$B18,D$3<=EOMONTH($B18,119)),INDEX($C$7:$DR$7,1,12*(YEAR(D$3)-YEAR($B18))+MONTH(D$3)-MONTH($B18)+1),0)) -> 0 | E51: =IF($C18<>"Yes",0,IF(AND(E$3>=$B18,E$3<=EOMONTH($B18,119)),INDEX($C$7:$DR$7,1,12*(YEAR(E$3)-YEAR($B18))+MONTH(E$3)-MONTH($B18)+1),0)) -> 0 | F51: =IF($C18<>"Yes",0,IF(AND(F$3>=$B18,F$3<=EOMONTH($B18,119)),INDEX($C$7:$DR$7,1,12*(YEAR(F$3)-YEAR($B18))+MONTH(F$3)-MONTH($B18)+1),0)) -> 0 | G51: =IF($C18<>"Yes",0,IF(AND(G$3>=$B18,G$3<=EOMONTH($B18,119)),INDEX($C$7:$DR$7,1,12*(YEAR(G$3)-YEAR($B18))+MONTH(G$3)-MONTH($B18)+1),0)) -> 0 | H51: =IF($C18<>"Yes",0,IF(AND(H$3>=$B18,H$3<=EOMONTH($B18,119)),INDEX($C$7:$DR$7,1,12*(YEAR(H$3)-YEAR($B18))+MONTH(H$3)-MONTH($B18)+1),0)) -> 0 | I51: =IF($C18<>"Yes",0,IF(AND(I$3>=$B18,I$3<=EOMONTH($B18,119)),INDEX($C$7:$DR$7,1,12*(YEAR(I$3)-YEAR($B18))+MONTH(I$3)-MONTH($B18)+1),0)) -> 0 | J51: =IF($C18<>"Yes",0,IF(AND(J$3>=$B18,J$3<=EOMONTH($B18,119)),INDEX($C$7:$DR$7,1,12*(YEAR(J$3)-YEAR($B18))+MONTH(J$3)-MONTH($B18)+1),0)) -> 0 | ... DR51: =IF($C18<>"Yes",0,IF(AND(DR$3>=$B18,DR$3<=EOMONTH($B18,119)),INDEX($C$7:$DR$7,1,12*(YEAR(DR$3)-YEAR($B18))+MONTH(DR$3)-MONTH($B18)+1),0)) -> 0
A52: P10 DevCF | C52: =IF($C19<>"Yes",0,IF(AND(C$3>=$B19,C$3<=EOMONTH($B19,119)),INDEX($C$5:$DR$5,1,12*(YEAR(C$3)-YEAR($B19))+MONTH(C$3)-MONTH($B19)+1),0)) -> 0 | D52: =IF($C19<>"Yes",0,IF(AND(D$3>=$B19,D$3<=EOMONTH($B19,119)),INDEX($C$5:$DR$5,1,12*(YEAR(D$3)-YEAR($B19))+MONTH(D$3)-MONTH($B19)+1),0)) -> 0 | E52: =IF($C19<>"Yes",0,IF(AND(E$3>=$B19,E$3<=EOMONTH($B19,119)),INDEX($C$5:$DR$5,1,12*(YEAR(E$3)-YEAR($B19))+MONTH(E$3)-MONTH($B19)+1),0)) -> 0 | F52: =IF($C19<>"Yes",0,IF(AND(F$3>=$B19,F$3<=EOMONTH($B19,119)),INDEX($C$5:$DR$5,1,12*(YEAR(F$3)-YEAR($B19))+MONTH(F$3)-MONTH($B19)+1),0)) -> 0 | G52: =IF($C19<>"Yes",0,IF(AND(G$3>=$B19,G$3<=EOMONTH($B19,119)),INDEX($C$5:$DR$5,1,12*(YEAR(G$3)-YEAR($B19))+MONTH(G$3)-MONTH($B19)+1),0)) -> 0 | H52: =IF($C19<>"Yes",0,IF(AND(H$3>=$B19,H$3<=EOMONTH($B19,119)),INDEX($C$5:$DR$5,1,12*(YEAR(H$3)-YEAR($B19))+MONTH(H$3)-MONTH($B19)+1),0)) -> 0 | I52: =IF($C19<>"Yes",0,IF(AND(I$3>=$B19,I$3<=EOMONTH($B19,119)),INDEX($C$5:$DR$5,1,12*(YEAR(I$3)-YEAR($B19))+MONTH(I$3)-MONTH($B19)+1),0)) -> 0 | J52: =IF($C19<>"Yes",0,IF(AND(J$3>=$B19,J$3<=EOMONTH($B19,119)),INDEX($C$5:$DR$5,1,12*(YEAR(J$3)-YEAR($B19))+MONTH(J$3)-MONTH($B19)+1),0)) -> 0 | ... DR52: =IF($C19<>"Yes",0,IF(AND(DR$3>=$B19,DR$3<=EOMONTH($B19,119)),INDEX($C$5:$DR$5,1,12*(YEAR(DR$3)-YEAR($B19))+MONTH(DR$3)-MONTH($B19)+1),0)) -> 0
A53: P10 Sales | C53: =IF($C19<>"Yes",0,IF(AND(C$3>=$B19,C$3<=EOMONTH($B19,119)),INDEX($C$6:$DR$6,1,12*(YEAR(C$3)-YEAR($B19))+MONTH(C$3)-MONTH($B19)+1),0)) -> 0 | D53: =IF($C19<>"Yes",0,IF(AND(D$3>=$B19,D$3<=EOMONTH($B19,119)),INDEX($C$6:$DR$6,1,12*(YEAR(D$3)-YEAR($B19))+MONTH(D$3)-MONTH($B19)+1),0)) -> 0 | E53: =IF($C19<>"Yes",0,IF(AND(E$3>=$B19,E$3<=EOMONTH($B19,119)),INDEX($C$6:$DR$6,1,12*(YEAR(E$3)-YEAR($B19))+MONTH(E$3)-MONTH($B19)+1),0)) -> 0 | F53: =IF($C19<>"Yes",0,IF(AND(F$3>=$B19,F$3<=EOMONTH($B19,119)),INDEX($C$6:$DR$6,1,12*(YEAR(F$3)-YEAR($B19))+MONTH(F$3)-MONTH($B19)+1),0)) -> 0 | G53: =IF($C19<>"Yes",0,IF(AND(G$3>=$B19,G$3<=EOMONTH($B19,119)),INDEX($C$6:$DR$6,1,12*(YEAR(G$3)-YEAR($B19))+MONTH(G$3)-MONTH($B19)+1),0)) -> 0 | H53: =IF($C19<>"Yes",0,IF(AND(H$3>=$B19,H$3<=EOMONTH($B19,119)),INDEX($C$6:$DR$6,1,12*(YEAR(H$3)-YEAR($B19))+MONTH(H$3)-MONTH($B19)+1),0)) -> 0 | I53: =IF($C19<>"Yes",0,IF(AND(I$3>=$B19,I$3<=EOMONTH($B19,119)),INDEX($C$6:$DR$6,1,12*(YEAR(I$3)-YEAR($B19))+MONTH(I$3)-MONTH($B19)+1),0)) -> 0 | J53: =IF($C19<>"Yes",0,IF(AND(J$3>=$B19,J$3<=EOMONTH($B19,119)),INDEX($C$6:$DR$6,1,12*(YEAR(J$3)-YEAR($B19))+MONTH(J$3)-MONTH($B19)+1),0)) -> 0 | ... DR53: =IF($C19<>"Yes",0,IF(AND(DR$3>=$B19,DR$3<=EOMONTH($B19,119)),INDEX($C$6:$DR$6,1,12*(YEAR(DR$3)-YEAR($B19))+MONTH(DR$3)-MONTH($B19)+1),0)) -> 0
A54: P10 ClosingPay | C54: =IF($C19<>"Yes",0,IF(AND(C$3>=$B19,C$3<=EOMONTH($B19,119)),INDEX($C$7:$DR$7,1,12*(YEAR(C$3)-YEAR($B19))+MONTH(C$3)-MONTH($B19)+1),0)) -> 0 | D54: =IF($C19<>"Yes",0,IF(AND(D$3>=$B19,D$3<=EOMONTH($B19,119)),INDEX($C$7:$DR$7,1,12*(YEAR(D$3)-YEAR($B19))+MONTH(D$3)-MONTH($B19)+1),0)) -> 0 | E54: =IF($C19<>"Yes",0,IF(AND(E$3>=$B19,E$3<=EOMONTH($B19,119)),INDEX($C$7:$DR$7,1,12*(YEAR(E$3)-YEAR($B19))+MONTH(E$3)-MONTH($B19)+1),0)) -> 0 | F54: =IF($C19<>"Yes",0,IF(AND(F$3>=$B19,F$3<=EOMONTH($B19,119)),INDEX($C$7:$DR$7,1,12*(YEAR(F$3)-YEAR($B19))+MONTH(F$3)-MONTH($B19)+1),0)) -> 0 | G54: =IF($C19<>"Yes",0,IF(AND(G$3>=$B19,G$3<=EOMONTH($B19,119)),INDEX($C$7:$DR$7,1,12*(YEAR(G$3)-YEAR($B19))+MONTH(G$3)-MONTH($B19)+1),0)) -> 0 | H54: =IF($C19<>"Yes",0,IF(AND(H$3>=$B19,H$3<=EOMONTH($B19,119)),INDEX($C$7:$DR$7,1,12*(YEAR(H$3)-YEAR($B19))+MONTH(H$3)-MONTH($B19)+1),0)) -> 0 | I54: =IF($C19<>"Yes",0,IF(AND(I$3>=$B19,I$3<=EOMONTH($B19,119)),INDEX($C$7:$DR$7,1,12*(YEAR(I$3)-YEAR($B19))+MONTH(I$3)-MONTH($B19)+1),0)) -> 0 | J54: =IF($C19<>"Yes",0,IF(AND(J$3>=$B19,J$3<=EOMONTH($B19,119)),INDEX($C$7:$DR$7,1,12*(YEAR(J$3)-YEAR($B19))+MONTH(J$3)-MONTH($B19)+1),0)) -> 0 | ... DR54: =IF($C19<>"Yes",0,IF(AND(DR$3>=$B19,DR$3<=EOMONTH($B19,119)),INDEX($C$7:$DR$7,1,12*(YEAR(DR$3)-YEAR($B19))+MONTH(DR$3)-MONTH($B19)+1),0)) -> 0
A55: DevCF_All_Pos | C55: =MAX(C25,0)+MAX(C28,0)+MAX(C31,0)+MAX(C34,0)+MAX(C37,0)+MAX(C40,0)+MAX(C43,0)+MAX(C46,0)+MAX(C49,0)+MAX(C52,0) -> 0 | D55: =MAX(D25,0)+MAX(D28,0)+MAX(D31,0)+MAX(D34,0)+MAX(D37,0)+MAX(D40,0)+MAX(D43,0)+MAX(D46,0)+MAX(D49,0)+MAX(D52,0) -> 0 | E55: =MAX(E25,0)+MAX(E28,0)+MAX(E31,0)+MAX(E34,0)+MAX(E37,0)+MAX(E40,0)+MAX(E43,0)+MAX(E46,0)+MAX(E49,0)+MAX(E52,0) -> 0 | F55: =MAX(F25,0)+MAX(F28,0)+MAX(F31,0)+MAX(F34,0)+MAX(F37,0)+MAX(F40,0)+MAX(F43,0)+MAX(F46,0)+MAX(F49,0)+MAX(F52,0) -> 0 | G55: =MAX(G25,0)+MAX(G28,0)+MAX(G31,0)+MAX(G34,0)+MAX(G37,0)+MAX(G40,0)+MAX(G43,0)+MAX(G46,0)+MAX(G49,0)+MAX(G52,0) -> 0 | H55: =MAX(H25,0)+MAX(H28,0)+MAX(H31,0)+MAX(H34,0)+MAX(H37,0)+MAX(H40,0)+MAX(H43,0)+MAX(H46,0)+MAX(H49,0)+MAX(H52,0) -> 0 | I55: =MAX(I25,0)+MAX(I28,0)+MAX(I31,0)+MAX(I34,0)+MAX(I37,0)+MAX(I40,0)+MAX(I43,0)+MAX(I46,0)+MAX(I49,0)+MAX(I52,0) -> 0 | J55: =MAX(J25,0)+MAX(J28,0)+MAX(J31,0)+MAX(J34,0)+MAX(J37,0)+MAX(J40,0)+MAX(J43,0)+MAX(J46,0)+MAX(J49,0)+MAX(J52,0) -> 0 | ... DR55: =MAX(DR25,0)+MAX(DR28,0)+MAX(DR31,0)+MAX(DR34,0)+MAX(DR37,0)+MAX(DR40,0)+MAX(DR43,0)+MAX(DR46,0)+MAX(DR49,0)+MAX(DR52,0) -> 0
A56: DevCF_All_Neg | C56: =MAX(-C25,0)+MAX(-C28,0)+MAX(-C31,0)+MAX(-C34,0)+MAX(-C37,0)+MAX(-C40,0)+MAX(-C43,0)+MAX(-C46,0)+MAX(-C49,0)+MAX(-C52,0) -> 0 | D56: =MAX(-D25,0)+MAX(-D28,0)+MAX(-D31,0)+MAX(-D34,0)+MAX(-D37,0)+MAX(-D40,0)+MAX(-D43,0)+MAX(-D46,0)+MAX(-D49,0)+MAX(-D52,0) -> 0 | E56: =MAX(-E25,0)+MAX(-E28,0)+MAX(-E31,0)+MAX(-E34,0)+MAX(-E37,0)+MAX(-E40,0)+MAX(-E43,0)+MAX(-E46,0)+MAX(-E49,0)+MAX(-E52,0) -> 0 | F56: =MAX(-F25,0)+MAX(-F28,0)+MAX(-F31,0)+MAX(-F34,0)+MAX(-F37,0)+MAX(-F40,0)+MAX(-F43,0)+MAX(-F46,0)+MAX(-F49,0)+MAX(-F52,0) -> 0 | G56: =MAX(-G25,0)+MAX(-G28,0)+MAX(-G31,0)+MAX(-G34,0)+MAX(-G37,0)+MAX(-G40,0)+MAX(-G43,0)+MAX(-G46,0)+MAX(-G49,0)+MAX(-G52,0) -> 0 | H56: =MAX(-H25,0)+MAX(-H28,0)+MAX(-H31,0)+MAX(-H34,0)+MAX(-H37,0)+MAX(-H40,0)+MAX(-H43,0)+MAX(-H46,0)+MAX(-H49,0)+MAX(-H52,0) -> 0 | I56: =MAX(-I25,0)+MAX(-I28,0)+MAX(-I31,0)+MAX(-I34,0)+MAX(-I37,0)+MAX(-I40,0)+MAX(-I43,0)+MAX(-I46,0)+MAX(-I49,0)+MAX(-I52,0) -> 0 | J56: =MAX(-J25,0)+MAX(-J28,0)+MAX(-J31,0)+MAX(-J34,0)+MAX(-J37,0)+MAX(-J40,0)+MAX(-J43,0)+MAX(-J46,0)+MAX(-J49,0)+MAX(-J52,0) -> 0 | ... DR56: =MAX(-DR25,0)+MAX(-DR28,0)+MAX(-DR31,0)+MAX(-DR34,0)+MAX(-DR37,0)+MAX(-DR40,0)+MAX(-DR43,0)+MAX(-DR46,0)+MAX(-DR49,0)+MAX(-DR52,0) -> 0
A57: DevCF_All | C57: =C25+C28+C31+C34+C37+C40+C43+C46+C49+C52 -> 0 | D57: =D25+D28+D31+D34+D37+D40+D43+D46+D49+D52 -> 0 | E57: =E25+E28+E31+E34+E37+E40+E43+E46+E49+E52 -> 0 | F57: =F25+F28+F31+F34+F37+F40+F43+F46+F49+F52 -> 0 | G57: =G25+G28+G31+G34+G37+G40+G43+G46+G49+G52 -> 0 | H57: =H25+H28+H31+H34+H37+H40+H43+H46+H49+H52 -> 0 | I57: =I25+I28+I31+I34+I37+I40+I43+I46+I49+I52 -> 0 | J57: =J25+J28+J31+J34+J37+J40+J43+J46+J49+J52 -> 0 | ... DR57: =DR25+DR28+DR31+DR34+DR37+DR40+DR43+DR46+DR49+DR52 -> 0
A58: DevCF_P1 | C58: =C25 -> 0 | D58: =D25 -> 0 | E58: =E25 -> 0 | F58: =F25 -> 0 | G58: =G25 -> 0 | H58: =H25 -> 0 | I58: =I25 -> 0 | J58: =J25 -> 0 | ... DR58: =DR25 -> 0
A59: DevCF_P2Plus | C59: =C28+C31+C34+C37+C40+C43+C46+C49+C52 -> 0 | D59: =D28+D31+D34+D37+D40+D43+D46+D49+D52 -> 0 | E59: =E28+E31+E34+E37+E40+E43+E46+E49+E52 -> 0 | F59: =F28+F31+F34+F37+F40+F43+F46+F49+F52 -> 0 | G59: =G28+G31+G34+G37+G40+G43+G46+G49+G52 -> 0 | H59: =H28+H31+H34+H37+H40+H43+H46+H49+H52 -> 0 | I59: =I28+I31+I34+I37+I40+I43+I46+I49+I52 -> 0 | J59: =J28+J31+J34+J37+J40+J43+J46+J49+J52 -> 0 | ... DR59: =DR28+DR31+DR34+DR37+DR40+DR43+DR46+DR49+DR52 -> 0
A60: Sales_All | C60: =C26+C29+C32+C35+C38+C41+C44+C47+C50+C53 -> 0 | D60: =D26+D29+D32+D35+D38+D41+D44+D47+D50+D53 -> 0 | E60: =E26+E29+E32+E35+E38+E41+E44+E47+E50+E53 -> 0 | F60: =F26+F29+F32+F35+F38+F41+F44+F47+F50+F53 -> 0 | G60: =G26+G29+G32+G35+G38+G41+G44+G47+G50+G53 -> 0 | H60: =H26+H29+H32+H35+H38+H41+H44+H47+H50+H53 -> 0 | I60: =I26+I29+I32+I35+I38+I41+I44+I47+I50+I53 -> 0 | J60: =J26+J29+J32+J35+J38+J41+J44+J47+J50+J53 -> 0 | ... DR60: =DR26+DR29+DR32+DR35+DR38+DR41+DR44+DR47+DR50+DR53 -> 0
A61: Sales_P1 | C61: =C26 -> 0 | D61: =D26 -> 0 | E61: =E26 -> 0 | F61: =F26 -> 0 | G61: =G26 -> 0 | H61: =H26 -> 0 | I61: =I26 -> 0 | J61: =J26 -> 0 | ... DR61: =DR26 -> 0
A62: Sales_P2Plus | C62: =C29+C32+C35+C38+C41+C44+C47+C50+C53 -> 0 | D62: =D29+D32+D35+D38+D41+D44+D47+D50+D53 -> 0 | E62: =E29+E32+E35+E38+E41+E44+E47+E50+E53 -> 0 | F62: =F29+F32+F35+F38+F41+F44+F47+F50+F53 -> 0 | G62: =G29+G32+G35+G38+G41+G44+G47+G50+G53 -> 0 | H62: =H29+H32+H35+H38+H41+H44+H47+H50+H53 -> 0 | I62: =I29+I32+I35+I38+I41+I44+I47+I50+I53 -> 0 | J62: =J29+J32+J35+J38+J41+J44+J47+J50+J53 -> 0 | ... DR62: =DR29+DR32+DR35+DR38+DR41+DR44+DR47+DR50+DR53 -> 0
A63: Closing_All | C63: =C27+C30+C33+C36+C39+C42+C45+C48+C51+C54 -> 0 | D63: =D27+D30+D33+D36+D39+D42+D45+D48+D51+D54 -> 0 | E63: =E27+E30+E33+E36+E39+E42+E45+E48+E51+E54 -> 0 | F63: =F27+F30+F33+F36+F39+F42+F45+F48+F51+F54 -> 0 | G63: =G27+G30+G33+G36+G39+G42+G45+G48+G51+G54 -> 0 | H63: =H27+H30+H33+H36+H39+H42+H45+H48+H51+H54 -> 0 | I63: =I27+I30+I33+I36+I39+I42+I45+I48+I51+I54 -> 0 | J63: =J27+J30+J33+J36+J39+J42+J45+J48+J51+J54 -> 0 | ... DR63: =DR27+DR30+DR33+DR36+DR39+DR42+DR45+DR48+DR51+DR54 -> 0
A64: Closing_P1 | C64: =C27 -> 0 | D64: =D27 -> 0 | E64: =E27 -> 0 | F64: =F27 -> 0 | G64: =G27 -> 0 | H64: =H27 -> 0 | I64: =I27 -> 0 | J64: =J27 -> 0 | ... DR64: =DR27 -> 0
A65: Closing_P2Plus | C65: =C30+C33+C36+C39+C42+C45+C48+C51+C54 -> 0 | D65: =D30+D33+D36+D39+D42+D45+D48+D51+D54 -> 0 | E65: =E30+E33+E36+E39+E42+E45+E48+E51+E54 -> 0 | F65: =F30+F33+F36+F39+F42+F45+F48+F51+F54 -> 0 | G65: =G30+G33+G36+G39+G42+G45+G48+G51+G54 -> 0 | H65: =H30+H33+H36+H39+H42+H45+H48+H51+H54 -> 0 | I65: =I30+I33+I36+I39+I42+I45+I48+I51+I54 -> 0 | J65: =J30+J33+J36+J39+J42+J45+J48+J51+J54 -> 0 | ... DR65: =DR30+DR33+DR36+DR39+DR42+DR45+DR48+DR51+DR54 -> 0
A67: Manual include (1/0) from Results_10yr | C67: =IF(Results_10yr!B17="Yes",1,0) -> 0 | D67: =IF(Results_10yr!C17="Yes",1,0) -> 1 | E67: =IF(Results_10yr!D17="Yes",1,0) -> 1 | F67: =IF(Results_10yr!E17="Yes",1,0) -> 1 | G67: =IF(Results_10yr!F17="Yes",1,0) -> 1 | H67: =IF(Results_10yr!G17="Yes",1,0) -> 1 | I67: =IF(Results_10yr!H17="Yes",1,0) -> 1 | J67: =IF(Results_10yr!I17="Yes",1,0) -> 1 | ... L67: =IF(Results_10yr!K17="Yes",1,0) -> 1
A69: Sales_ManualSelected | C69: =$C$67*C26+$D$67*C29+$E$67*C32+$F$67*C35+$G$67*C38+$H$67*C41+$I$67*C44+$J$67*C47+$K$67*C50+$L$67*C53 -> 0 | D69: =$C$67*D26+$D$67*D29+$E$67*D32+$F$67*D35+$G$67*D38+$H$67*D41+$I$67*D44+$J$67*D47+$K$67*D50+$L$67*D53 -> 0 | E69: =$C$67*E26+$D$67*E29+$E$67*E32+$F$67*E35+$G$67*E38+$H$67*E41+$I$67*E44+$J$67*E47+$K$67*E50+$L$67*E53 -> 0 | F69: =$C$67*F26+$D$67*F29+$E$67*F32+$F$67*F35+$G$67*F38+$H$67*F41+$I$67*F44+$J$67*F47+$K$67*F50+$L$67*F53 -> 0 | G69: =$C$67*G26+$D$67*G29+$E$67*G32+$F$67*G35+$G$67*G38+$H$67*G41+$I$67*G44+$J$67*G47+$K$67*G50+$L$67*G53 -> 0 | H69: =$C$67*H26+$D$67*H29+$E$67*H32+$F$67*H35+$G$67*H38+$H$67*H41+$I$67*H44+$J$67*H47+$K$67*H50+$L$67*H53 -> 0 | I69: =$C$67*I26+$D$67*I29+$E$67*I32+$F$67*I35+$G$67*I38+$H$67*I41+$I$67*I44+$J$67*I47+$K$67*I50+$L$67*I53 -> 0 | J69: =$C$67*J26+$D$67*J29+$E$67*J32+$F$67*J35+$G$67*J38+$H$67*J41+$I$67*J44+$J$67*J47+$K$67*J50+$L$67*J53 -> 0 | ... DR69: =$C$67*DR26+$D$67*DR29+$E$67*DR32+$F$67*DR35+$G$67*DR38+$H$67*DR41+$I$67*DR44+$J$67*DR47+$K$67*DR50+$L$67*DR53 -> 0
A70: Sales_Selected (per royalty dropdown) | C70: =IF(Results_10yr!B15="All projects",C60,IF(Results_10yr!B15="Projects 2+",C62,C69)) -> 0 | D70: =IF(Results_10yr!B15="All projects",D60,IF(Results_10yr!B15="Projects 2+",D62,D69)) -> 0 | E70: =IF(Results_10yr!B15="All projects",E60,IF(Results_10yr!B15="Projects 2+",E62,E69)) -> 0 | F70: =IF(Results_10yr!B15="All projects",F60,IF(Results_10yr!B15="Projects 2+",F62,F69)) -> 0 | G70: =IF(Results_10yr!B15="All projects",G60,IF(Results_10yr!B15="Projects 2+",G62,G69)) -> 0 | H70: =IF(Results_10yr!B15="All projects",H60,IF(Results_10yr!B15="Projects 2+",H62,H69)) -> 0 | I70: =IF(Results_10yr!B15="All projects",I60,IF(Results_10yr!B15="Projects 2+",I62,I69)) -> 0 | J70: =IF(Results_10yr!B15="All projects",J60,IF(Results_10yr!B15="Projects 2+",J62,J69)) -> 0 | K70: =IF(Results_10yr!B15="All projects",K60,IF(Results_10yr!B15="Projects 2+",K62,K69)) -> 0 | L70: =IF(Results_10yr!B15="All projects",L60,IF(Results_10yr!B15="Projects 2+",L62,L69)) -> 0 | M70: =IF(Results_10yr!B15="All projects",M60,IF(Results_10yr!B15="Projects 2+",M62,M69)) -> 0 | N70: =IF(Results_10yr!B15="All projects",N60,IF(Results_10yr!B15="Projects 2+",N62,N69)) -> 0 | O70: =IF(Results_10yr!B15="All projects",O60,IF(Results_10yr!B15="Projects 2+",O62,O69)) -> 0 | P70: =IF(Results_10yr!B15="All projects",P60,IF(Results_10yr!B15="Projects 2+",P62,P69)) -> 0 | Q70: =IF(Results_10yr!B15="All projects",Q60,IF(Results_10yr!B15="Projects 2+",Q62,Q69)) -> 0 | R70: =IF(Results_10yr!B15="All projects",R60,IF(Results_10yr!B15="Projects 2+",R62,R69)) -> 0 | S70: =IF(Results_10yr!B15="All projects",S60,IF(Results_10yr!B15="Projects 2+",S62,S69)) -> 0 | T70: =IF(Results_10yr!B15="All projects",T60,IF(Results_10yr!B15="Projects 2+",T62,T69)) -> 0 | U70: =IF(Results_10yr!B15="All projects",U60,IF(Results_10yr!B15="Projects 2+",U62,U69)) -> 0 | V70: =IF(Results_10yr!B15="All projects",V60,IF(Results_10yr!B15="Projects 2+",V62,V69)) -> 0 | W70: =IF(Results_10yr!B15="All projects",W60,IF(Results_10yr!B15="Projects 2+",W62,W69)) -> 0 | X70: =IF(Results_10yr!B15="All projects",X60,IF(Results_10yr!B15="Projects 2+",X62,X69)) -> 0 | Y70: =IF(Results_10yr!B15="All projects",Y60,IF(Results_10yr!B15="Projects 2+",Y62,Y69)) -> 0 | Z70: =IF(Results_10yr!B15="All projects",Z60,IF(Results_10yr!B15="Projects 2+",Z62,Z69)) -> 0 | AA70: =IF(Results_10yr!B15="All projects",AA60,IF(Results_10yr!B15="Projects 2+",AA62,AA69)) -> 0 | AB70: =IF(Results_10yr!B15="All projects",AB60,IF(Results_10yr!B15="Projects 2+",AB62,AB69)) -> 0 | AC70: =IF(Results_10yr!B15="All projects",AC60,IF(Results_10yr!B15="Projects 2+",AC62,AC69)) -> 0 | AD70: =IF(Results_10yr!B15="All projects",AD60,IF(Results_10yr!B15="Projects 2+",AD62,AD69)) -> 0 | AE70: =IF(Results_10yr!B15="All projects",AE60,IF(Results_10yr!B15="Projects 2+",AE62,AE69)) -> 0 | AF70: =IF(Results_10yr!B15="All projects",AF60,IF(Results_10yr!B15="Projects 2+",AF62,AF69)) -> 0 | AG70: =IF(Results_10yr!B15="All projects",AG60,IF(Results_10yr!B15="Projects 2+",AG62,AG69)) -> 0 | AH70: =IF(Results_10yr!B15="All projects",AH60,IF(Results_10yr!B15="Projects 2+",AH62,AH69)) -> 0 | AI70: =IF(Results_10yr!B15="All projects",AI60,IF(Results_10yr!B15="Projects 2+",AI62,AI69)) -> 0 | AJ70: =IF(Results_10yr!B15="All projects",AJ60,IF(Results_10yr!B15="Projects 2+",AJ62,AJ69)) -> 0 | AK70: =IF(Results_10yr!B15="All projects",AK60,IF(Results_10yr!B15="Projects 2+",AK62,AK69)) -> 0 | AL70: =IF(Results_10yr!B15="All projects",AL60,IF(Results_10yr!B15="Projects 2+",AL62,AL69)) -> 0 | AM70: =IF(Results_10yr!B15="All projects",AM60,IF(Results_10yr!B15="Projects 2+",AM62,AM69)) -> 0 | AN70: =IF(Results_10yr!B15="All projects",AN60,IF(Results_10yr!B15="Projects 2+",AN62,AN69)) -> 0 | AO70: =IF(Results_10yr!B15="All projects",AO60,IF(Results_10yr!B15="Projects 2+",AO62,AO69)) -> 0 | AP70: =IF(Results_10yr!B15="All projects",AP60,IF(Results_10yr!B15="Projects 2+",AP62,AP69)) -> 0 | AQ70: =IF(Results_10yr!B15="All projects",AQ60,IF(Results_10yr!B15="Projects 2+",AQ62,AQ69)) -> 0 | AR70: =IF(Results_10yr!B15="All projects",AR60,IF(Results_10yr!B15="Projects 2+",AR62,AR69)) -> 0 | AS70: =IF(Results_10yr!B15="All projects",AS60,IF(Results_10yr!B15="Projects 2+",AS62,AS69)) -> 0 | AT70: =IF(Results_10yr!B15="All projects",AT60,IF(Results_10yr!B15="Projects 2+",AT62,AT69)) -> 0 | AU70: =IF(Results_10yr!B15="All projects",AU60,IF(Results_10yr!B15="Projects 2+",AU62,AU69)) -> 0 | AV70: =IF(Results_10yr!B15="All projects",AV60,IF(Results_10yr!B15="Projects 2+",AV62,AV69)) -> 0 | AW70: =IF(Results_10yr!B15="All projects",AW60,IF(Results_10yr!B15="Projects 2+",AW62,AW69)) -> 0 | AX70: =IF(Results_10yr!B15="All projects",AX60,IF(Results_10yr!B15="Projects 2+",AX62,AX69)) -> 0 | AY70: =IF(Results_10yr!B15="All projects",AY60,IF(Results_10yr!B15="Projects 2+",AY62,AY69)) -> 0 | AZ70: =IF(Results_10yr!B15="All projects",AZ60,IF(Results_10yr!B15="Projects 2+",AZ62,AZ69)) -> 0 | BA70: =IF(Results_10yr!B15="All projects",BA60,IF(Results_10yr!B15="Projects 2+",BA62,BA69)) -> 0 | BB70: =IF(Results_10yr!B15="All projects",BB60,IF(Results_10yr!B15="Projects 2+",BB62,BB69)) -> 1875000 | BC70: =IF(Results_10yr!B15="All projects",BC60,IF(Results_10yr!B15="Projects 2+",BC62,BC69)) -> 1875000 | BD70: =IF(Results_10yr!B15="All projects",BD60,IF(Results_10yr!B15="Projects 2+",BD62,BD69)) -> 1875000 | BE70: =IF(Results_10yr!B15="All projects",BE60,IF(Results_10yr!B15="Projects 2+",BE62,BE69)) -> 1875000 | BF70: =IF(Results_10yr!B15="All projects",BF60,IF(Results_10yr!B15="Projects 2+",BF62,BF69)) -> 1875000 | BG70: =IF(Results_10yr!B15="All projects",BG60,IF(Results_10yr!B15="Projects 2+",BG62,BG69)) -> 1875000 | BH70: =IF(Results_10yr!B15="All projects",BH60,IF(Results_10yr!B15="Projects 2+",BH62,BH69)) -> 78125000 | BI70: =IF(Results_10yr!B15="All projects",BI60,IF(Results_10yr!B15="Projects 2+",BI62,BI69)) -> 14375000 | BJ70: =IF(Results_10yr!B15="All projects",BJ60,IF(Results_10yr!B15="Projects 2+",BJ62,BJ69)) -> 14375000 | BK70: =IF(Results_10yr!B15="All projects",BK60,IF(Results_10yr!B15="Projects 2+",BK62,BK69)) -> 14375000 | BL70: =IF(Results_10yr!B15="All projects",BL60,IF(Results_10yr!B15="Projects 2+",BL62,BL69)) -> 14375000 | BM70: =IF(Results_10yr!B15="All projects",BM60,IF(Results_10yr!B15="Projects 2+",BM62,BM69)) -> 14375000 | BN70: =IF(Results_10yr!B15="All projects",BN60,IF(Results_10yr!B15="Projects 2+",BN62,BN69)) -> 90625000 | BO70: =IF(Results_10yr!B15="All projects",BO60,IF(Results_10yr!B15="Projects 2+",BO62,BO69)) -> 26875000 | BP70: =IF(Results_10yr!B15="All projects",BP60,IF(Results_10yr!B15="Projects 2+",BP62,BP69)) -> 26875000 | BQ70: =IF(Results_10yr!B15="All projects",BQ60,IF(Results_10yr!B15="Projects 2+",BQ62,BQ69)) -> 26875000 | BR70: =IF(Results_10yr!B15="All projects",BR60,IF(Results_10yr!B15="Projects 2+",BR62,BR69)) -> 26875000 | BS70: =IF(Results_10yr!B15="All projects",BS60,IF(Results_10yr!B15="Projects 2+",BS62,BS69)) -> 26875000 | BT70: =IF(Results_10yr!B15="All projects",BT60,IF(Results_10yr!B15="Projects 2+",BT62,BT69)) -> 90625000 | BU70: =IF(Results_10yr!B15="All projects",BU60,IF(Results_10yr!B15="Projects 2+",BU62,BU69)) -> 26875000 | BV70: =IF(Results_10yr!B15="All projects",BV60,IF(Results_10yr!B15="Projects 2+",BV62,BV69)) -> 26875000 | BW70: =IF(Results_10yr!B15="All projects",BW60,IF(Results_10yr!B15="Projects 2+",BW62,BW69)) -> 26875000 | BX70: =IF(Results_10yr!B15="All projects",BX60,IF(Results_10yr!B15="Projects 2+",BX62,BX69)) -> 26875000 | BY70: =IF(Results_10yr!B15="All projects",BY60,IF(Results_10yr!B15="Projects 2+",BY62,BY69)) -> 26875000 | BZ70: =IF(Results_10yr!B15="All projects",BZ60,IF(Results_10yr!B15="Projects 2+",BZ62,BZ69)) -> 88750000 | CA70: =IF(Results_10yr!B15="All projects",CA60,IF(Results_10yr!B15="Projects 2+",CA62,CA69)) -> 25000000 | CB70: =IF(Results_10yr!B15="All projects",CB60,IF(Results_10yr!B15="Projects 2+",CB62,CB69)) -> 25000000 | CC70: =IF(Results_10yr!B15="All projects",CC60,IF(Results_10yr!B15="Projects 2+",CC62,CC69)) -> 25000000 | CD70: =IF(Results_10yr!B15="All projects",CD60,IF(Results_10yr!B15="Projects 2+",CD62,CD69)) -> 25000000 | CE70: =IF(Results_10yr!B15="All projects",CE60,IF(Results_10yr!B15="Projects 2+",CE62,CE69)) -> 25000000 | CF70: =IF(Results_10yr!B15="All projects",CF60,IF(Results_10yr!B15="Projects 2+",CF62,CF69)) -> 12500000 | CG70: =IF(Results_10yr!B15="All projects",CG60,IF(Results_10yr!B15="Projects 2+",CG62,CG69)) -> 12500000 | CH70: =IF(Results_10yr!B15="All projects",CH60,IF(Results_10yr!B15="Projects 2+",CH62,CH69)) -> 12500000 | CI70: =IF(Results_10yr!B15="All projects",CI60,IF(Results_10yr!B15="Projects 2+",CI62,CI69)) -> 12500000 | CJ70: =IF(Results_10yr!B15="All projects",CJ60,IF(Results_10yr!B15="Projects 2+",CJ62,CJ69)) -> 12500000 | CK70: =IF(Results_10yr!B15="All projects",CK60,IF(Results_10yr!B15="Projects 2+",CK62,CK69)) -> 12500000 | CL70: =IF(Results_10yr!B15="All projects",CL60,IF(Results_10yr!B15="Projects 2+",CL62,CL69)) -> 0 | CM70: =IF(Results_10yr!B15="All projects",CM60,IF(Results_10yr!B15="Projects 2+",CM62,CM69)) -> 0 | CN70: =IF(Results_10yr!B15="All projects",CN60,IF(Results_10yr!B15="Projects 2+",CN62,CN69)) -> 0 | CO70: =IF(Results_10yr!B15="All projects",CO60,IF(Results_10yr!B15="Projects 2+",CO62,CO69)) -> 0 | CP70: =IF(Results_10yr!B15="All projects",CP60,IF(Results_10yr!B15="Projects 2+",CP62,CP69)) -> 0 | CQ70: =IF(Results_10yr!B15="All projects",CQ60,IF(Results_10yr!B15="Projects 2+",CQ62,CQ69)) -> 0 | CR70: =IF(Results_10yr!B15="All projects",CR60,IF(Results_10yr!B15="Projects 2+",CR62,CR69)) -> 0 | CS70: =IF(Results_10yr!B15="All projects",CS60,IF(Results_10yr!B15="Projects 2+",CS62,CS69)) -> 0 | CT70: =IF(Results_10yr!B15="All projects",CT60,IF(Results_10yr!B15="Projects 2+",CT62,CT69)) -> 0 | CU70: =IF(Results_10yr!B15="All projects",CU60,IF(Results_10yr!B15="Projects 2+",CU62,CU69)) -> 0 | CV70: =IF(Results_10yr!B15="All projects",CV60,IF(Results_10yr!B15="Projects 2+",CV62,CV69)) -> 0 | CW70: =IF(Results_10yr!B15="All projects",CW60,IF(Results_10yr!B15="Projects 2+",CW62,CW69)) -> 0 | CX70: =IF(Results_10yr!B15="All projects",CX60,IF(Results_10yr!B15="Projects 2+",CX62,CX69)) -> 0 | CY70: =IF(Results_10yr!B15="All projects",CY60,IF(Results_10yr!B15="Projects 2+",CY62,CY69)) -> 0 | CZ70: =IF(Results_10yr!B15="All projects",CZ60,IF(Results_10yr!B15="Projects 2+",CZ62,CZ69)) -> 0 | DA70: =IF(Results_10yr!B15="All projects",DA60,IF(Results_10yr!B15="Projects 2+",DA62,DA69)) -> 0 | DB70: =IF(Results_10yr!B15="All projects",DB60,IF(Results_10yr!B15="Projects 2+",DB62,DB69)) -> 0 | DC70: =IF(Results_10yr!B15="All projects",DC60,IF(Results_10yr!B15="Projects 2+",DC62,DC69)) -> 0 | DD70: =IF(Results_10yr!B15="All projects",DD60,IF(Results_10yr!B15="Projects 2+",DD62,DD69)) -> 0 | DE70: =IF(Results_10yr!B15="All projects",DE60,IF(Results_10yr!B15="Projects 2+",DE62,DE69)) -> 0 | DF70: =IF(Results_10yr!B15="All projects",DF60,IF(Results_10yr!B15="Projects 2+",DF62,DF69)) -> 0 | DG70: =IF(Results_10yr!B15="All projects",DG60,IF(Results_10yr!B15="Projects 2+",DG62,DG69)) -> 0 | DH70: =IF(Results_10yr!B15="All projects",DH60,IF(Results_10yr!B15="Projects 2+",DH62,DH69)) -> 0 | DI70: =IF(Results_10yr!B15="All projects",DI60,IF(Results_10yr!B15="Projects 2+",DI62,DI69)) -> 0 | DJ70: =IF(Results_10yr!B15="All projects",DJ60,IF(Results_10yr!B15="Projects 2+",DJ62,DJ69)) -> 0 | DK70: =IF(Results_10yr!B15="All projects",DK60,IF(Results_10yr!B15="Projects 2+",DK62,DK69)) -> 0 | DL70: =IF(Results_10yr!B15="All projects",DL60,IF(Results_10yr!B15="Projects 2+",DL62,DL69)) -> 0 | DM70: =IF(Results_10yr!B15="All projects",DM60,IF(Results_10yr!B15="Projects 2+",DM62,DM69)) -> 0 | DN70: =IF(Results_10yr!B15="All projects",DN60,IF(Results_10yr!B15="Projects 2+",DN62,DN69)) -> 0 | DO70: =IF(Results_10yr!B15="All projects",DO60,IF(Results_10yr!B15="Projects 2+",DO62,DO69)) -> 0 | DP70: =IF(Results_10yr!B15="All projects",DP60,IF(Results_10yr!B15="Projects 2+",DP62,DP69)) -> 0 | DQ70: =IF(Results_10yr!B15="All projects",DQ60,IF(Results_10yr!B15="Projects 2+",DQ62,DQ69)) -> 0 | DR70: =IF(Results_10yr!B15="All projects",DR60,IF(Results_10yr!B15="Projects 2+",DR62,DR69)) -> 0
A71: Closing_ManualSelected | C71: =$C$67*C27+$D$67*C30+$E$67*C33+$F$67*C36+$G$67*C39+$H$67*C42+$I$67*C45+$J$67*C48+$K$67*C51+$L$67*C54 -> 0 | D71: =$C$67*D27+$D$67*D30+$E$67*D33+$F$67*D36+$G$67*D39+$H$67*D42+$I$67*D45+$J$67*D48+$K$67*D51+$L$67*D54 -> 0 | E71: =$C$67*E27+$D$67*E30+$E$67*E33+$F$67*E36+$G$67*E39+$H$67*E42+$I$67*E45+$J$67*E48+$K$67*E51+$L$67*E54 -> 0 | F71: =$C$67*F27+$D$67*F30+$E$67*F33+$F$67*F36+$G$67*F39+$H$67*F42+$I$67*F45+$J$67*F48+$K$67*F51+$L$67*F54 -> 0 | G71: =$C$67*G27+$D$67*G30+$E$67*G33+$F$67*G36+$G$67*G39+$H$67*G42+$I$67*G45+$J$67*G48+$K$67*G51+$L$67*G54 -> 0 | H71: =$C$67*H27+$D$67*H30+$E$67*H33+$F$67*H36+$G$67*H39+$H$67*H42+$I$67*H45+$J$67*H48+$K$67*H51+$L$67*H54 -> 0 | I71: =$C$67*I27+$D$67*I30+$E$67*I33+$F$67*I36+$G$67*I39+$H$67*I42+$I$67*I45+$J$67*I48+$K$67*I51+$L$67*I54 -> 0 | J71: =$C$67*J27+$D$67*J30+$E$67*J33+$F$67*J36+$G$67*J39+$H$67*J42+$I$67*J45+$J$67*J48+$K$67*J51+$L$67*J54 -> 0 | ... DR71: =$C$67*DR27+$D$67*DR30+$E$67*DR33+$F$67*DR36+$G$67*DR39+$H$67*DR42+$I$67*DR45+$J$67*DR48+$K$67*DR51+$L$67*DR54 -> 0
A72: DevCF_Selected (per broker scope dropdown) | C72: =IF(Results_10yr!B12="All projects",C57,C58) -> 0 | D72: =IF(Results_10yr!B12="All projects",D57,D58) -> 0 | E72: =IF(Results_10yr!B12="All projects",E57,E58) -> 0 | F72: =IF(Results_10yr!B12="All projects",F57,F58) -> 0 | G72: =IF(Results_10yr!B12="All projects",G57,G58) -> 0 | H72: =IF(Results_10yr!B12="All projects",H57,H58) -> 0 | I72: =IF(Results_10yr!B12="All projects",I57,I58) -> 0 | J72: =IF(Results_10yr!B12="All projects",J57,J58) -> 0 | K72: =IF(Results_10yr!B12="All projects",K57,K58) -> 0 | L72: =IF(Results_10yr!B12="All projects",L57,L58) -> 0 | M72: =IF(Results_10yr!B12="All projects",M57,M58) -> 0 | N72: =IF(Results_10yr!B12="All projects",N57,N58) -> 0 | O72: =IF(Results_10yr!B12="All projects",O57,O58) -> 0 | P72: =IF(Results_10yr!B12="All projects",P57,P58) -> 0 | Q72: =IF(Results_10yr!B12="All projects",Q57,Q58) -> 0 | R72: =IF(Results_10yr!B12="All projects",R57,R58) -> 0 | S72: =IF(Results_10yr!B12="All projects",S57,S58) -> 0 | T72: =IF(Results_10yr!B12="All projects",T57,T58) -> 0 | U72: =IF(Results_10yr!B12="All projects",U57,U58) -> 0 | V72: =IF(Results_10yr!B12="All projects",V57,V58) -> 0 | W72: =IF(Results_10yr!B12="All projects",W57,W58) -> 0 | X72: =IF(Results_10yr!B12="All projects",X57,X58) -> 0 | Y72: =IF(Results_10yr!B12="All projects",Y57,Y58) -> 0 | Z72: =IF(Results_10yr!B12="All projects",Z57,Z58) -> 0 | AA72: =IF(Results_10yr!B12="All projects",AA57,AA58) -> -7959375 | AB72: =IF(Results_10yr!B12="All projects",AB57,AB58) -> 0 | AC72: =IF(Results_10yr!B12="All projects",AC57,AC58) -> 0 | AD72: =IF(Results_10yr!B12="All projects",AD57,AD58) -> -6583997.1 | AE72: =IF(Results_10yr!B12="All projects",AE57,AE58) -> -6583997.1 | AF72: =IF(Results_10yr!B12="All projects",AF57,AF58) -> -6583997.1 | AG72: =IF(Results_10yr!B12="All projects",AG57,AG58) -> -14543372 | AH72: =IF(Results_10yr!B12="All projects",AH57,AH58) -> -6583997.1 | AI72: =IF(Results_10yr!B12="All projects",AI57,AI58) -> -6583997.1 | AJ72: =IF(Results_10yr!B12="All projects",AJ57,AJ58) -> -13167994 | AK72: =IF(Results_10yr!B12="All projects",AK57,AK58) -> -13167994 | AL72: =IF(Results_10yr!B12="All projects",AL57,AL58) -> -13167994 | AM72: =IF(Results_10yr!B12="All projects",AM57,AM58) -> -21127369 | AN72: =IF(Results_10yr!B12="All projects",AN57,AN58) -> -13167994 | AO72: =IF(Results_10yr!B12="All projects",AO57,AO58) -> -13167994 | AP72: =IF(Results_10yr!B12="All projects",AP57,AP58) -> -19751991 | AQ72: =IF(Results_10yr!B12="All projects",AQ57,AQ58) -> -19751991 | AR72: =IF(Results_10yr!B12="All projects",AR57,AR58) -> -19751991 | AS72: =IF(Results_10yr!B12="All projects",AS57,AS58) -> -27711366 | AT72: =IF(Results_10yr!B12="All projects",AT57,AT58) -> -19751991 | AU72: =IF(Results_10yr!B12="All projects",AU57,AU58) -> -19751991 | AV72: =IF(Results_10yr!B12="All projects",AV57,AV58) -> -24483357 | AW72: =IF(Results_10yr!B12="All projects",AW57,AW58) -> -24483357 | AX72: =IF(Results_10yr!B12="All projects",AX57,AX58) -> -24483357 | AY72: =IF(Results_10yr!B12="All projects",AY57,AY58) -> -32442732 | AZ72: =IF(Results_10yr!B12="All projects",AZ57,AZ58) -> -24483357 | BA72: =IF(Results_10yr!B12="All projects",BA57,BA58) -> -24483357 | BB72: =IF(Results_10yr!B12="All projects",BB57,BB58) -> 50856985 | BC72: =IF(Results_10yr!B12="All projects",BC57,BC58) -> -12132481 | BD72: =IF(Results_10yr!B12="All projects",BD57,BD58) -> -12132481 | BE72: =IF(Results_10yr!B12="All projects",BE57,BE58) -> -12132481 | BF72: =IF(Results_10yr!B12="All projects",BF57,BF58) -> -12132481 | BG72: =IF(Results_10yr!B12="All projects",BG57,BG58) -> -12132481 | BH72: =IF(Results_10yr!B12="All projects",BH57,BH58) -> 69791857 | BI72: =IF(Results_10yr!B12="All projects",BI57,BI58) -> 6802391.4 | BJ72: =IF(Results_10yr!B12="All projects",BJ57,BJ58) -> 6802391.4 | BK72: =IF(Results_10yr!B12="All projects",BK57,BK58) -> 6802391.4 | BL72: =IF(Results_10yr!B12="All projects",BL57,BL58) -> 6802391.4 | BM72: =IF(Results_10yr!B12="All projects",BM57,BM58) -> 6802391.4 | BN72: =IF(Results_10yr!B12="All projects",BN57,BN58) -> 76375854 | BO72: =IF(Results_10yr!B12="All projects",BO57,BO58) -> 13386388 | BP72: =IF(Results_10yr!B12="All projects",BP57,BP58) -> 13386388 | BQ72: =IF(Results_10yr!B12="All projects",BQ57,BQ58) -> 13386388 | BR72: =IF(Results_10yr!B12="All projects",BR57,BR58) -> 13386388 | BS72: =IF(Results_10yr!B12="All projects",BS57,BS58) -> 13386388 | BT72: =IF(Results_10yr!B12="All projects",BT57,BT58) -> 82959851 | BU72: =IF(Results_10yr!B12="All projects",BU57,BU58) -> 19970386 | BV72: =IF(Results_10yr!B12="All projects",BV57,BV58) -> 19970386 | BW72: =IF(Results_10yr!B12="All projects",BW57,BW58) -> 19970386 | BX72: =IF(Results_10yr!B12="All projects",BX57,BX58) -> 19970386 | BY72: =IF(Results_10yr!B12="All projects",BY57,BY58) -> 19970386 | BZ72: =IF(Results_10yr!B12="All projects",BZ57,BZ58) -> 87691217 | CA72: =IF(Results_10yr!B12="All projects",CA57,CA58) -> 24701751 | CB72: =IF(Results_10yr!B12="All projects",CB57,CB58) -> 24701751 | CC72: =IF(Results_10yr!B12="All projects",CC57,CC58) -> 24701751 | CD72: =IF(Results_10yr!B12="All projects",CD57,CD58) -> 24701751 | CE72: =IF(Results_10yr!B12="All projects",CE57,CE58) -> 24701751 | CF72: =IF(Results_10yr!B12="All projects",CF57,CF58) -> 12350876 | CG72: =IF(Results_10yr!B12="All projects",CG57,CG58) -> 12350876 | CH72: =IF(Results_10yr!B12="All projects",CH57,CH58) -> 12350876 | CI72: =IF(Results_10yr!B12="All projects",CI57,CI58) -> 12350876 | CJ72: =IF(Results_10yr!B12="All projects",CJ57,CJ58) -> 12350876 | CK72: =IF(Results_10yr!B12="All projects",CK57,CK58) -> 12350876 | CL72: =IF(Results_10yr!B12="All projects",CL57,CL58) -> 0 | CM72: =IF(Results_10yr!B12="All projects",CM57,CM58) -> 0 | CN72: =IF(Results_10yr!B12="All projects",CN57,CN58) -> 0 | CO72: =IF(Results_10yr!B12="All projects",CO57,CO58) -> 0 | CP72: =IF(Results_10yr!B12="All projects",CP57,CP58) -> 0 | CQ72: =IF(Results_10yr!B12="All projects",CQ57,CQ58) -> 0 | CR72: =IF(Results_10yr!B12="All projects",CR57,CR58) -> 0 | CS72: =IF(Results_10yr!B12="All projects",CS57,CS58) -> 0 | CT72: =IF(Results_10yr!B12="All projects",CT57,CT58) -> 0 | CU72: =IF(Results_10yr!B12="All projects",CU57,CU58) -> 0 | CV72: =IF(Results_10yr!B12="All projects",CV57,CV58) -> 0 | CW72: =IF(Results_10yr!B12="All projects",CW57,CW58) -> 0 | CX72: =IF(Results_10yr!B12="All projects",CX57,CX58) -> 0 | CY72: =IF(Results_10yr!B12="All projects",CY57,CY58) -> 0 | CZ72: =IF(Results_10yr!B12="All projects",CZ57,CZ58) -> 0 | DA72: =IF(Results_10yr!B12="All projects",DA57,DA58) -> 0 | DB72: =IF(Results_10yr!B12="All projects",DB57,DB58) -> 0 | DC72: =IF(Results_10yr!B12="All projects",DC57,DC58) -> 0 | DD72: =IF(Results_10yr!B12="All projects",DD57,DD58) -> 0 | DE72: =IF(Results_10yr!B12="All projects",DE57,DE58) -> 0 | DF72: =IF(Results_10yr!B12="All projects",DF57,DF58) -> 0 | DG72: =IF(Results_10yr!B12="All projects",DG57,DG58) -> 0 | DH72: =IF(Results_10yr!B12="All projects",DH57,DH58) -> 0 | DI72: =IF(Results_10yr!B12="All projects",DI57,DI58) -> 0 | DJ72: =IF(Results_10yr!B12="All projects",DJ57,DJ58) -> 0 | DK72: =IF(Results_10yr!B12="All projects",DK57,DK58) -> 0 | DL72: =IF(Results_10yr!B12="All projects",DL57,DL58) -> 0 | DM72: =IF(Results_10yr!B12="All projects",DM57,DM58) -> 0 | DN72: =IF(Results_10yr!B12="All projects",DN57,DN58) -> 0 | DO72: =IF(Results_10yr!B12="All projects",DO57,DO58) -> 0 | DP72: =IF(Results_10yr!B12="All projects",DP57,DP58) -> 0 | DQ72: =IF(Results_10yr!B12="All projects",DQ57,DQ58) -> 0 | DR72: =IF(Results_10yr!B12="All projects",DR57,DR58) -> 0
A73: Closing_Selected (per lending dropdown) | C73: =IF(Results_10yr!$B$35="All projects",C63,IF(Results_10yr!$B$35="Projects 2+",C65,C71)) -> 0 | D73: =IF(Results_10yr!$B$35="All projects",D63,IF(Results_10yr!$B$35="Projects 2+",D65,D71)) -> 0 | E73: =IF(Results_10yr!$B$35="All projects",E63,IF(Results_10yr!$B$35="Projects 2+",E65,E71)) -> 0 | F73: =IF(Results_10yr!$B$35="All projects",F63,IF(Results_10yr!$B$35="Projects 2+",F65,F71)) -> 0 | G73: =IF(Results_10yr!$B$35="All projects",G63,IF(Results_10yr!$B$35="Projects 2+",G65,G71)) -> 0 | H73: =IF(Results_10yr!$B$35="All projects",H63,IF(Results_10yr!$B$35="Projects 2+",H65,H71)) -> 0 | I73: =IF(Results_10yr!$B$35="All projects",I63,IF(Results_10yr!$B$35="Projects 2+",I65,I71)) -> 0 | J73: =IF(Results_10yr!$B$35="All projects",J63,IF(Results_10yr!$B$35="Projects 2+",J65,J71)) -> 0 | ... DR73: =IF(Results_10yr!$B$35="All projects",DR63,IF(Results_10yr!$B$35="Projects 2+",DR65,DR71)) -> 0
A74: Sales_BrokerSelected (per broker scope dropdown) | C74: =IF(Results_10yr!$B$12="All projects",C60,C61) -> 0 | D74: =IF(Results_10yr!$B$12="All projects",D60,D61) -> 0 | E74: =IF(Results_10yr!$B$12="All projects",E60,E61) -> 0 | F74: =IF(Results_10yr!$B$12="All projects",F60,F61) -> 0 | G74: =IF(Results_10yr!$B$12="All projects",G60,G61) -> 0 | H74: =IF(Results_10yr!$B$12="All projects",H60,H61) -> 0 | I74: =IF(Results_10yr!$B$12="All projects",I60,I61) -> 0 | J74: =IF(Results_10yr!$B$12="All projects",J60,J61) -> 0 | ... DR74: =IF(Results_10yr!$B$12="All projects",DR60,DR61) -> 0
A82: Annual lender schedule (Years 1-10) — derived from Closing_Selected_120 (selected projects for lending)
A83: Year | C83: 1 | D83: 2 | E83: 3 | F83: 4 | G83: 5 | H83: 6 | I83: 7 | J83: 8 | K83: 9 | L83: 10
A84: Unit closings (count, est.) | C84: =IFERROR(SUM(INDEX(Closing_Selected_120,1,1):INDEX(Closing_Selected_120,1,12))/(Avg_Sale_Price-Deposit_Per_Unit),0) -> 0 | D84: =IFERROR(SUM(INDEX(Closing_Selected_120,1,13):INDEX(Closing_Selected_120,1,24))/(Avg_Sale_Price-Deposit_Per_Unit),0) -> 0 | E84: =IFERROR(SUM(INDEX(Closing_Selected_120,1,25):INDEX(Closing_Selected_120,1,36))/(Avg_Sale_Price-Deposit_Per_Unit),0) -> 0 | F84: =IFERROR(SUM(INDEX(Closing_Selected_120,1,37):INDEX(Closing_Selected_120,1,48))/(Avg_Sale_Price-Deposit_Per_Unit),0) -> 0 | G84: =IFERROR(SUM(INDEX(Closing_Selected_120,1,49):INDEX(Closing_Selected_120,1,60))/(Avg_Sale_Price-Deposit_Per_Unit),0) -> 200 | H84: =IFERROR(SUM(INDEX(Closing_Selected_120,1,61):INDEX(Closing_Selected_120,1,72))/(Avg_Sale_Price-Deposit_Per_Unit),0) -> 300 | I84: =IFERROR(SUM(INDEX(Closing_Selected_120,1,73):INDEX(Closing_Selected_120,1,84))/(Avg_Sale_Price-Deposit_Per_Unit),0) -> 225 | J84: =IFERROR(SUM(INDEX(Closing_Selected_120,1,85):INDEX(Closing_Selected_120,1,96))/(Avg_Sale_Price-Deposit_Per_Unit),0) -> 25 | K84: =IFERROR(SUM(INDEX(Closing_Selected_120,1,97):INDEX(Closing_Selected_120,1,108))/(Avg_Sale_Price-Deposit_Per_Unit),0) -> 0 | L84: =IFERROR(SUM(INDEX(Closing_Selected_120,1,109):INDEX(Closing_Selected_120,1,120))/(Avg_Sale_Price-Deposit_Per_Unit),0) -> 0
A85: Principal originated | C85: =C84*Avg_Sale_Price*Results_10yr!B30*Results_10yr!B31 -> 0 | D85: =D84*Avg_Sale_Price*Results_10yr!B30*Results_10yr!B31 -> 0 | E85: =E84*Avg_Sale_Price*Results_10yr!B30*Results_10yr!B31 -> 0 | F85: =F84*Avg_Sale_Price*Results_10yr!B30*Results_10yr!B31 -> 0 | G85: =G84*Avg_Sale_Price*Results_10yr!B30*Results_10yr!B31 -> 1.2e+08 | H85: =H84*Avg_Sale_Price*Results_10yr!B30*Results_10yr!B31 -> 180000000 | I85: =I84*Avg_Sale_Price*Results_10yr!B30*Results_10yr!B31 -> 135000000 | J85: =J84*Avg_Sale_Price*Results_10yr!B30*Results_10yr!B31 -> 15000000 | K85: =K84*Avg_Sale_Price*Results_10yr!B30*Results_10yr!B31 -> 0 | L85: =L84*Avg_Sale_Price*Results_10yr!B30*Results_10yr!B31 -> 0
A86: Origination fee income | C86: =C85*Results_10yr!B32 -> 0 | D86: =D85*Results_10yr!B32 -> 0 | E86: =E85*Results_10yr!B32 -> 0 | F86: =F85*Results_10yr!B32 -> 0 | G86: =G85*Results_10yr!B32 -> 1200000 | H86: =H85*Results_10yr!B32 -> 1800000 | I86: =I85*Results_10yr!B32 -> 1350000 | J86: =J85*Results_10yr!B32 -> 150000 | K86: =K85*Results_10yr!B32 -> 0 | L86: =L85*Results_10yr!B32 -> 0
A88: Cohort amortization (each cohort = loans originated in that year)
A89: C1 BeginBal | B89: =IF(C85=0,0,-PMT(Results_10yr!B29,Results_10yr!B28,C85)) -> 0 | C89: =IF(AND(1>=1,1<=1+Results_10yr!B28-1),IF(C85=0,0,C85),0) -> 0 | D89: =IF(AND(2>=1,2<=1+Results_10yr!B28-1),IF(C85=0,0,C92),0) -> 0 | E89: =IF(AND(3>=1,3<=1+Results_10yr!B28-1),IF(C85=0,0,D92),0) -> 0 | F89: =IF(AND(4>=1,4<=1+Results_10yr!B28-1),IF(C85=0,0,E92),0) -> 0 | G89: =IF(AND(5>=1,5<=1+Results_10yr!B28-1),IF(C85=0,0,F92),0) -> 0 | H89: =IF(AND(6>=1,6<=1+Results_10yr!B28-1),IF(C85=0,0,G92),0) -> 0 | I89: =IF(AND(7>=1,7<=1+Results_10yr!B28-1),IF(C85=0,0,H92),0) -> 0 | J89: =IF(AND(8>=1,8<=1+Results_10yr!B28-1),IF(C85=0,0,I92),0) -> 0 | K89: =IF(AND(9>=1,9<=1+Results_10yr!B28-1),IF(C85=0,0,J92),0) -> 0 | L89: =IF(AND(10>=1,10<=1+Results_10yr!B28-1),IF(C85=0,0,K92),0) -> 0
A90: C1 Interest | B90: =IF(C83="",0,0) -> 0 | C90: =IF(AND(1>=1,1<=1+Results_10yr!B28-1),Results_10yr!B29*C89*(1-Results_10yr!B33),0) -> 0 | D90: =IF(AND(2>=1,2<=1+Results_10yr!B28-1),Results_10yr!B29*D89*(1-Results_10yr!B33),0) -> 0 | E90: =IF(AND(3>=1,3<=1+Results_10yr!B28-1),Results_10yr!B29*E89*(1-Results_10yr!B33),0) -> 0 | F90: =IF(AND(4>=1,4<=1+Results_10yr!B28-1),Results_10yr!B29*F89*(1-Results_10yr!B33),0) -> 0 | G90: =IF(AND(5>=1,5<=1+Results_10yr!B28-1),Results_10yr!B29*G89*(1-Results_10yr!B33),0) -> 0 | H90: =IF(AND(6>=1,6<=1+Results_10yr!B28-1),Results_10yr!B29*H89*(1-Results_10yr!B33),0) -> 0 | I90: =IF(AND(7>=1,7<=1+Results_10yr!B28-1),Results_10yr!B29*I89*(1-Results_10yr!B33),0) -> 0 | J90: =IF(AND(8>=1,8<=1+Results_10yr!B28-1),Results_10yr!B29*J89*(1-Results_10yr!B33),0) -> 0 | K90: =IF(AND(9>=1,9<=1+Results_10yr!B28-1),Results_10yr!B29*K89*(1-Results_10yr!B33),0) -> 0 | L90: =IF(AND(10>=1,10<=1+Results_10yr!B28-1),Results_10yr!B29*L89*(1-Results_10yr!B33),0) -> 0
A91: C1 Principal | C91: =IF(AND(1>=1,1<=1+Results_10yr!B28-1),(B89-Results_10yr!B29*C89)*(1-Results_10yr!B33),0) -> 0 | D91: =IF(AND(2>=1,2<=1+Results_10yr!B28-1),(B89-Results_10yr!B29*D89)*(1-Results_10yr!B33),0) -> 0 | E91: =IF(AND(3>=1,3<=1+Results_10yr!B28-1),(B89-Results_10yr!B29*E89)*(1-Results_10yr!B33),0) -> 0 | F91: =IF(AND(4>=1,4<=1+Results_10yr!B28-1),(B89-Results_10yr!B29*F89)*(1-Results_10yr!B33),0) -> 0 | G91: =IF(AND(5>=1,5<=1+Results_10yr!B28-1),(B89-Results_10yr!B29*G89)*(1-Results_10yr!B33),0) -> 0 | H91: =IF(AND(6>=1,6<=1+Results_10yr!B28-1),(B89-Results_10yr!B29*H89)*(1-Results_10yr!B33),0) -> 0 | I91: =IF(AND(7>=1,7<=1+Results_10yr!B28-1),(B89-Results_10yr!B29*I89)*(1-Results_10yr!B33),0) -> 0 | J91: =IF(AND(8>=1,8<=1+Results_10yr!B28-1),(B89-Results_10yr!B29*J89)*(1-Results_10yr!B33),0) -> 0 | K91: =IF(AND(9>=1,9<=1+Results_10yr!B28-1),(B89-Results_10yr!B29*K89)*(1-Results_10yr!B33),0) -> 0 | L91: =IF(AND(10>=1,10<=1+Results_10yr!B28-1),(B89-Results_10yr!B29*L89)*(1-Results_10yr!B33),0) -> 0
A92: C1 EndBal | C92: =IF(AND(1>=1,1<=1+Results_10yr!B28-1),C89-(B89-Results_10yr!B29*C89),0) -> 0 | D92: =IF(AND(2>=1,2<=1+Results_10yr!B28-1),D89-(B89-Results_10yr!B29*D89),0) -> 0 | E92: =IF(AND(3>=1,3<=1+Results_10yr!B28-1),E89-(B89-Results_10yr!B29*E89),0) -> 0 | F92: =IF(AND(4>=1,4<=1+Results_10yr!B28-1),F89-(B89-Results_10yr!B29*F89),0) -> 0 | G92: =IF(AND(5>=1,5<=1+Results_10yr!B28-1),G89-(B89-Results_10yr!B29*G89),0) -> 0 | H92: =IF(AND(6>=1,6<=1+Results_10yr!B28-1),H89-(B89-Results_10yr!B29*H89),0) -> 0 | I92: =IF(AND(7>=1,7<=1+Results_10yr!B28-1),I89-(B89-Results_10yr!B29*I89),0) -> 0 | J92: =IF(AND(8>=1,8<=1+Results_10yr!B28-1),J89-(B89-Results_10yr!B29*J89),0) -> 0 | K92: =IF(AND(9>=1,9<=1+Results_10yr!B28-1),K89-(B89-Results_10yr!B29*K89),0) -> 0 | L92: =IF(AND(10>=1,10<=1+Results_10yr!B28-1),L89-(B89-Results_10yr!B29*L89),0) -> 0
A93: C2 BeginBal | B93: =IF(D85=0,0,-PMT(Results_10yr!B29,Results_10yr!B28,D85)) -> 0 | C93: =IF(AND(1>=2,1<=2+Results_10yr!B28-1),IF(D85=0,0,B96),0) -> 0 | D93: =IF(AND(2>=2,2<=2+Results_10yr!B28-1),IF(D85=0,0,D85),0) -> 0 | E93: =IF(AND(3>=2,3<=2+Results_10yr!B28-1),IF(D85=0,0,D96),0) -> 0 | F93: =IF(AND(4>=2,4<=2+Results_10yr!B28-1),IF(D85=0,0,E96),0) -> 0 | G93: =IF(AND(5>=2,5<=2+Results_10yr!B28-1),IF(D85=0,0,F96),0) -> 0 | H93: =IF(AND(6>=2,6<=2+Results_10yr!B28-1),IF(D85=0,0,G96),0) -> 0 | I93: =IF(AND(7>=2,7<=2+Results_10yr!B28-1),IF(D85=0,0,H96),0) -> 0 | J93: =IF(AND(8>=2,8<=2+Results_10yr!B28-1),IF(D85=0,0,I96),0) -> 0 | K93: =IF(AND(9>=2,9<=2+Results_10yr!B28-1),IF(D85=0,0,J96),0) -> 0 | L93: =IF(AND(10>=2,10<=2+Results_10yr!B28-1),IF(D85=0,0,K96),0) -> 0
A94: C2 Interest | B94: =IF(C83="",0,0) -> 0 | C94: =IF(AND(1>=2,1<=2+Results_10yr!B28-1),Results_10yr!B29*C93*(1-Results_10yr!B33),0) -> 0 | D94: =IF(AND(2>=2,2<=2+Results_10yr!B28-1),Results_10yr!B29*D93*(1-Results_10yr!B33),0) -> 0 | E94: =IF(AND(3>=2,3<=2+Results_10yr!B28-1),Results_10yr!B29*E93*(1-Results_10yr!B33),0) -> 0 | F94: =IF(AND(4>=2,4<=2+Results_10yr!B28-1),Results_10yr!B29*F93*(1-Results_10yr!B33),0) -> 0 | G94: =IF(AND(5>=2,5<=2+Results_10yr!B28-1),Results_10yr!B29*G93*(1-Results_10yr!B33),0) -> 0 | H94: =IF(AND(6>=2,6<=2+Results_10yr!B28-1),Results_10yr!B29*H93*(1-Results_10yr!B33),0) -> 0 | I94: =IF(AND(7>=2,7<=2+Results_10yr!B28-1),Results_10yr!B29*I93*(1-Results_10yr!B33),0) -> 0 | J94: =IF(AND(8>=2,8<=2+Results_10yr!B28-1),Results_10yr!B29*J93*(1-Results_10yr!B33),0) -> 0 | K94: =IF(AND(9>=2,9<=2+Results_10yr!B28-1),Results_10yr!B29*K93*(1-Results_10yr!B33),0) -> 0 | L94: =IF(AND(10>=2,10<=2+Results_10yr!B28-1),Results_10yr!B29*L93*(1-Results_10yr!B33),0) -> 0
A95: C2 Principal | C95: =IF(AND(1>=2,1<=2+Results_10yr!B28-1),(B93-Results_10yr!B29*C93)*(1-Results_10yr!B33),0) -> 0 | D95: =IF(AND(2>=2,2<=2+Results_10yr!B28-1),(B93-Results_10yr!B29*D93)*(1-Results_10yr!B33),0) -> 0 | E95: =IF(AND(3>=2,3<=2+Results_10yr!B28-1),(B93-Results_10yr!B29*E93)*(1-Results_10yr!B33),0) -> 0 | F95: =IF(AND(4>=2,4<=2+Results_10yr!B28-1),(B93-Results_10yr!B29*F93)*(1-Results_10yr!B33),0) -> 0 | G95: =IF(AND(5>=2,5<=2+Results_10yr!B28-1),(B93-Results_10yr!B29*G93)*(1-Results_10yr!B33),0) -> 0 | H95: =IF(AND(6>=2,6<=2+Results_10yr!B28-1),(B93-Results_10yr!B29*H93)*(1-Results_10yr!B33),0) -> 0 | I95: =IF(AND(7>=2,7<=2+Results_10yr!B28-1),(B93-Results_10yr!B29*I93)*(1-Results_10yr!B33),0) -> 0 | J95: =IF(AND(8>=2,8<=2+Results_10yr!B28-1),(B93-Results_10yr!B29*J93)*(1-Results_10yr!B33),0) -> 0 | K95: =IF(AND(9>=2,9<=2+Results_10yr!B28-1),(B93-Results_10yr!B29*K93)*(1-Results_10yr!B33),0) -> 0 | L95: =IF(AND(10>=2,10<=2+Results_10yr!B28-1),(B93-Results_10yr!B29*L93)*(1-Results_10yr!B33),0) -> 0
A96: C2 EndBal | C96: =IF(AND(1>=2,1<=2+Results_10yr!B28-1),C93-(B93-Results_10yr!B29*C93),0) -> 0 | D96: =IF(AND(2>=2,2<=2+Results_10yr!B28-1),D93-(B93-Results_10yr!B29*D93),0) -> 0 | E96: =IF(AND(3>=2,3<=2+Results_10yr!B28-1),E93-(B93-Results_10yr!B29*E93),0) -> 0 | F96: =IF(AND(4>=2,4<=2+Results_10yr!B28-1),F93-(B93-Results_10yr!B29*F93),0) -> 0 | G96: =IF(AND(5>=2,5<=2+Results_10yr!B28-1),G93-(B93-Results_10yr!B29*G93),0) -> 0 | H96: =IF(AND(6>=2,6<=2+Results_10yr!B28-1),H93-(B93-Results_10yr!B29*H93),0) -> 0 | I96: =IF(AND(7>=2,7<=2+Results_10yr!B28-1),I93-(B93-Results_10yr!B29*I93),0) -> 0 | J96: =IF(AND(8>=2,8<=2+Results_10yr!B28-1),J93-(B93-Results_10yr!B29*J93),0) -> 0 | K96: =IF(AND(9>=2,9<=2+Results_10yr!B28-1),K93-(B93-Results_10yr!B29*K93),0) -> 0 | L96: =IF(AND(10>=2,10<=2+Results_10yr!B28-1),L93-(B93-Results_10yr!B29*L93),0) -> 0
A97: C3 BeginBal | B97: =IF(E85=0,0,-PMT(Results_10yr!B29,Results_10yr!B28,E85)) -> 0 | C97: =IF(AND(1>=3,1<=3+Results_10yr!B28-1),IF(E85=0,0,B100),0) -> 0 | D97: =IF(AND(2>=3,2<=3+Results_10yr!B28-1),IF(E85=0,0,C100),0) -> 0 | E97: =IF(AND(3>=3,3<=3+Results_10yr!B28-1),IF(E85=0,0,E85),0) -> 0 | F97: =IF(AND(4>=3,4<=3+Results_10yr!B28-1),IF(E85=0,0,E100),0) -> 0 | G97: =IF(AND(5>=3,5<=3+Results_10yr!B28-1),IF(E85=0,0,F100),0) -> 0 | H97: =IF(AND(6>=3,6<=3+Results_10yr!B28-1),IF(E85=0,0,G100),0) -> 0 | I97: =IF(AND(7>=3,7<=3+Results_10yr!B28-1),IF(E85=0,0,H100),0) -> 0 | J97: =IF(AND(8>=3,8<=3+Results_10yr!B28-1),IF(E85=0,0,I100),0) -> 0 | K97: =IF(AND(9>=3,9<=3+Results_10yr!B28-1),IF(E85=0,0,J100),0) -> 0 | L97: =IF(AND(10>=3,10<=3+Results_10yr!B28-1),IF(E85=0,0,K100),0) -> 0
A98: C3 Interest | B98: =IF(C83="",0,0) -> 0 | C98: =IF(AND(1>=3,1<=3+Results_10yr!B28-1),Results_10yr!B29*C97*(1-Results_10yr!B33),0) -> 0 | D98: =IF(AND(2>=3,2<=3+Results_10yr!B28-1),Results_10yr!B29*D97*(1-Results_10yr!B33),0) -> 0 | E98: =IF(AND(3>=3,3<=3+Results_10yr!B28-1),Results_10yr!B29*E97*(1-Results_10yr!B33),0) -> 0 | F98: =IF(AND(4>=3,4<=3+Results_10yr!B28-1),Results_10yr!B29*F97*(1-Results_10yr!B33),0) -> 0 | G98: =IF(AND(5>=3,5<=3+Results_10yr!B28-1),Results_10yr!B29*G97*(1-Results_10yr!B33),0) -> 0 | H98: =IF(AND(6>=3,6<=3+Results_10yr!B28-1),Results_10yr!B29*H97*(1-Results_10yr!B33),0) -> 0 | I98: =IF(AND(7>=3,7<=3+Results_10yr!B28-1),Results_10yr!B29*I97*(1-Results_10yr!B33),0) -> 0 | J98: =IF(AND(8>=3,8<=3+Results_10yr!B28-1),Results_10yr!B29*J97*(1-Results_10yr!B33),0) -> 0 | K98: =IF(AND(9>=3,9<=3+Results_10yr!B28-1),Results_10yr!B29*K97*(1-Results_10yr!B33),0) -> 0 | L98: =IF(AND(10>=3,10<=3+Results_10yr!B28-1),Results_10yr!B29*L97*(1-Results_10yr!B33),0) -> 0
A99: C3 Principal | C99: =IF(AND(1>=3,1<=3+Results_10yr!B28-1),(B97-Results_10yr!B29*C97)*(1-Results_10yr!B33),0) -> 0 | D99: =IF(AND(2>=3,2<=3+Results_10yr!B28-1),(B97-Results_10yr!B29*D97)*(1-Results_10yr!B33),0) -> 0 | E99: =IF(AND(3>=3,3<=3+Results_10yr!B28-1),(B97-Results_10yr!B29*E97)*(1-Results_10yr!B33),0) -> 0 | F99: =IF(AND(4>=3,4<=3+Results_10yr!B28-1),(B97-Results_10yr!B29*F97)*(1-Results_10yr!B33),0) -> 0 | G99: =IF(AND(5>=3,5<=3+Results_10yr!B28-1),(B97-Results_10yr!B29*G97)*(1-Results_10yr!B33),0) -> 0 | H99: =IF(AND(6>=3,6<=3+Results_10yr!B28-1),(B97-Results_10yr!B29*H97)*(1-Results_10yr!B33),0) -> 0 | I99: =IF(AND(7>=3,7<=3+Results_10yr!B28-1),(B97-Results_10yr!B29*I97)*(1-Results_10yr!B33),0) -> 0 | J99: =IF(AND(8>=3,8<=3+Results_10yr!B28-1),(B97-Results_10yr!B29*J97)*(1-Results_10yr!B33),0) -> 0 | K99: =IF(AND(9>=3,9<=3+Results_10yr!B28-1),(B97-Results_10yr!B29*K97)*(1-Results_10yr!B33),0) -> 0 | L99: =IF(AND(10>=3,10<=3+Results_10yr!B28-1),(B97-Results_10yr!B29*L97)*(1-Results_10yr!B33),0) -> 0
A100: C3 EndBal | C100: =IF(AND(1>=3,1<=3+Results_10yr!B28-1),C97-(B97-Results_10yr!B29*C97),0) -> 0 | D100: =IF(AND(2>=3,2<=3+Results_10yr!B28-1),D97-(B97-Results_10yr!B29*D97),0) -> 0 | E100: =IF(AND(3>=3,3<=3+Results_10yr!B28-1),E97-(B97-Results_10yr!B29*E97),0) -> 0 | F100: =IF(AND(4>=3,4<=3+Results_10yr!B28-1),F97-(B97-Results_10yr!B29*F97),0) -> 0 | G100: =IF(AND(5>=3,5<=3+Results_10yr!B28-1),G97-(B97-Results_10yr!B29*G97),0) -> 0 | H100: =IF(AND(6>=3,6<=3+Results_10yr!B28-1),H97-(B97-Results_10yr!B29*H97),0) -> 0 | I100: =IF(AND(7>=3,7<=3+Results_10yr!B28-1),I97-(B97-Results_10yr!B29*I97),0) -> 0 | J100: =IF(AND(8>=3,8<=3+Results_10yr!B28-1),J97-(B97-Results_10yr!B29*J97),0) -> 0 | K100: =IF(AND(9>=3,9<=3+Results_10yr!B28-1),K97-(B97-Results_10yr!B29*K97),0) -> 0 | L100: =IF(AND(10>=3,10<=3+Results_10yr!B28-1),L97-(B97-Results_10yr!B29*L97),0) -> 0
A101: C4 BeginBal | B101: =IF(F85=0,0,-PMT(Results_10yr!B29,Results_10yr!B28,F85)) -> 0 | C101: =IF(AND(1>=4,1<=4+Results_10yr!B28-1),IF(F85=0,0,B104),0) -> 0 | D101: =IF(AND(2>=4,2<=4+Results_10yr!B28-1),IF(F85=0,0,C104),0) -> 0 | E101: =IF(AND(3>=4,3<=4+Results_10yr!B28-1),IF(F85=0,0,D104),0) -> 0 | F101: =IF(AND(4>=4,4<=4+Results_10yr!B28-1),IF(F85=0,0,F85),0) -> 0 | G101: =IF(AND(5>=4,5<=4+Results_10yr!B28-1),IF(F85=0,0,F104),0) -> 0 | H101: =IF(AND(6>=4,6<=4+Results_10yr!B28-1),IF(F85=0,0,G104),0) -> 0 | I101: =IF(AND(7>=4,7<=4+Results_10yr!B28-1),IF(F85=0,0,H104),0) -> 0 | J101: =IF(AND(8>=4,8<=4+Results_10yr!B28-1),IF(F85=0,0,I104),0) -> 0 | K101: =IF(AND(9>=4,9<=4+Results_10yr!B28-1),IF(F85=0,0,J104),0) -> 0 | L101: =IF(AND(10>=4,10<=4+Results_10yr!B28-1),IF(F85=0,0,K104),0) -> 0
A102: C4 Interest | B102: =IF(C83="",0,0) -> 0 | C102: =IF(AND(1>=4,1<=4+Results_10yr!B28-1),Results_10yr!B29*C101*(1-Results_10yr!B33),0) -> 0 | D102: =IF(AND(2>=4,2<=4+Results_10yr!B28-1),Results_10yr!B29*D101*(1-Results_10yr!B33),0) -> 0 | E102: =IF(AND(3>=4,3<=4+Results_10yr!B28-1),Results_10yr!B29*E101*(1-Results_10yr!B33),0) -> 0 | F102: =IF(AND(4>=4,4<=4+Results_10yr!B28-1),Results_10yr!B29*F101*(1-Results_10yr!B33),0) -> 0 | G102: =IF(AND(5>=4,5<=4+Results_10yr!B28-1),Results_10yr!B29*G101*(1-Results_10yr!B33),0) -> 0 | H102: =IF(AND(6>=4,6<=4+Results_10yr!B28-1),Results_10yr!B29*H101*(1-Results_10yr!B33),0) -> 0 | I102: =IF(AND(7>=4,7<=4+Results_10yr!B28-1),Results_10yr!B29*I101*(1-Results_10yr!B33),0) -> 0 | J102: =IF(AND(8>=4,8<=4+Results_10yr!B28-1),Results_10yr!B29*J101*(1-Results_10yr!B33),0) -> 0 | K102: =IF(AND(9>=4,9<=4+Results_10yr!B28-1),Results_10yr!B29*K101*(1-Results_10yr!B33),0) -> 0 | L102: =IF(AND(10>=4,10<=4+Results_10yr!B28-1),Results_10yr!B29*L101*(1-Results_10yr!B33),0) -> 0
A103: C4 Principal | C103: =IF(AND(1>=4,1<=4+Results_10yr!B28-1),(B101-Results_10yr!B29*C101)*(1-Results_10yr!B33),0) -> 0 | D103: =IF(AND(2>=4,2<=4+Results_10yr!B28-1),(B101-Results_10yr!B29*D101)*(1-Results_10yr!B33),0) -> 0 | E103: =IF(AND(3>=4,3<=4+Results_10yr!B28-1),(B101-Results_10yr!B29*E101)*(1-Results_10yr!B33),0) -> 0 | F103: =IF(AND(4>=4,4<=4+Results_10yr!B28-1),(B101-Results_10yr!B29*F101)*(1-Results_10yr!B33),0) -> 0 | G103: =IF(AND(5>=4,5<=4+Results_10yr!B28-1),(B101-Results_10yr!B29*G101)*(1-Results_10yr!B33),0) -> 0 | H103: =IF(AND(6>=4,6<=4+Results_10yr!B28-1),(B101-Results_10yr!B29*H101)*(1-Results_10yr!B33),0) -> 0 | I103: =IF(AND(7>=4,7<=4+Results_10yr!B28-1),(B101-Results_10yr!B29*I101)*(1-Results_10yr!B33),0) -> 0 | J103: =IF(AND(8>=4,8<=4+Results_10yr!B28-1),(B101-Results_10yr!B29*J101)*(1-Results_10yr!B33),0) -> 0 | K103: =IF(AND(9>=4,9<=4+Results_10yr!B28-1),(B101-Results_10yr!B29*K101)*(1-Results_10yr!B33),0) -> 0 | L103: =IF(AND(10>=4,10<=4+Results_10yr!B28-1),(B101-Results_10yr!B29*L101)*(1-Results_10yr!B33),0) -> 0
A104: C4 EndBal | C104: =IF(AND(1>=4,1<=4+Results_10yr!B28-1),C101-(B101-Results_10yr!B29*C101),0) -> 0 | D104: =IF(AND(2>=4,2<=4+Results_10yr!B28-1),D101-(B101-Results_10yr!B29*D101),0) -> 0 | E104: =IF(AND(3>=4,3<=4+Results_10yr!B28-1),E101-(B101-Results_10yr!B29*E101),0) -> 0 | F104: =IF(AND(4>=4,4<=4+Results_10yr!B28-1),F101-(B101-Results_10yr!B29*F101),0) -> 0 | G104: =IF(AND(5>=4,5<=4+Results_10yr!B28-1),G101-(B101-Results_10yr!B29*G101),0) -> 0 | H104: =IF(AND(6>=4,6<=4+Results_10yr!B28-1),H101-(B101-Results_10yr!B29*H101),0) -> 0 | I104: =IF(AND(7>=4,7<=4+Results_10yr!B28-1),I101-(B101-Results_10yr!B29*I101),0) -> 0 | J104: =IF(AND(8>=4,8<=4+Results_10yr!B28-1),J101-(B101-Results_10yr!B29*J101),0) -> 0 | K104: =IF(AND(9>=4,9<=4+Results_10yr!B28-1),K101-(B101-Results_10yr!B29*K101),0) -> 0 | L104: =IF(AND(10>=4,10<=4+Results_10yr!B28-1),L101-(B101-Results_10yr!B29*L101),0) -> 0
A105: C5 BeginBal | B105: =IF(G85=0,0,-PMT(Results_10yr!B29,Results_10yr!B28,G85)) -> 18698411 | C105: =IF(AND(1>=5,1<=5+Results_10yr!B28-1),IF(G85=0,0,B108),0) -> 0 | D105: =IF(AND(2>=5,2<=5+Results_10yr!B28-1),IF(G85=0,0,C108),0) -> 0 | E105: =IF(AND(3>=5,3<=5+Results_10yr!B28-1),IF(G85=0,0,D108),0) -> 0 | F105: =IF(AND(4>=5,4<=5+Results_10yr!B28-1),IF(G85=0,0,E108),0) -> 0 | G105: =IF(AND(5>=5,5<=5+Results_10yr!B28-1),IF(G85=0,0,G85),0) -> 1.2e+08 | H105: =IF(AND(6>=5,6<=5+Results_10yr!B28-1),IF(G85=0,0,G108),0) -> 1.1210159e+08 | I105: =IF(AND(7>=5,7<=5+Results_10yr!B28-1),IF(G85=0,0,H108),0) -> 1.0349232e+08 | J105: =IF(AND(8>=5,8<=5+Results_10yr!B28-1),IF(G85=0,0,I108),0) -> 94108220 | K105: =IF(AND(9>=5,9<=5+Results_10yr!B28-1),IF(G85=0,0,J108),0) -> 83879549 | L105: =IF(AND(10>=5,10<=5+Results_10yr!B28-1),IF(G85=0,0,K108),0) -> 72730297
A106: C5 Interest | B106: =IF(C83="",0,0) -> 0 | C106: =IF(AND(1>=5,1<=5+Results_10yr!B28-1),Results_10yr!B29*C105*(1-Results_10yr!B33),0) -> 0 | D106: =IF(AND(2>=5,2<=5+Results_10yr!B28-1),Results_10yr!B29*D105*(1-Results_10yr!B33),0) -> 0 | E106: =IF(AND(3>=5,3<=5+Results_10yr!B28-1),Results_10yr!B29*E105*(1-Results_10yr!B33),0) -> 0 | F106: =IF(AND(4>=5,4<=5+Results_10yr!B28-1),Results_10yr!B29*F105*(1-Results_10yr!B33),0) -> 0 | G106: =IF(AND(5>=5,5<=5+Results_10yr!B28-1),Results_10yr!B29*G105*(1-Results_10yr!B33),0) -> 10800000 | H106: =IF(AND(6>=5,6<=5+Results_10yr!B28-1),Results_10yr!B29*H105*(1-Results_10yr!B33),0) -> 10089143 | I106: =IF(AND(7>=5,7<=5+Results_10yr!B28-1),Results_10yr!B29*I105*(1-Results_10yr!B33),0) -> 9314308.9 | J106: =IF(AND(8>=5,8<=5+Results_10yr!B28-1),Results_10yr!B29*J105*(1-Results_10yr!B33),0) -> 8469739.8 | K106: =IF(AND(9>=5,9<=5+Results_10yr!B28-1),Results_10yr!B29*K105*(1-Results_10yr!B33),0) -> 7549159.4 | L106: =IF(AND(10>=5,10<=5+Results_10yr!B28-1),Results_10yr!B29*L105*(1-Results_10yr!B33),0) -> 6545726.7
A107: C5 Principal | C107: =IF(AND(1>=5,1<=5+Results_10yr!B28-1),(B105-Results_10yr!B29*C105)*(1-Results_10yr!B33),0) -> 0 | D107: =IF(AND(2>=5,2<=5+Results_10yr!B28-1),(B105-Results_10yr!B29*D105)*(1-Results_10yr!B33),0) -> 0 | E107: =IF(AND(3>=5,3<=5+Results_10yr!B28-1),(B105-Results_10yr!B29*E105)*(1-Results_10yr!B33),0) -> 0 | F107: =IF(AND(4>=5,4<=5+Results_10yr!B28-1),(B105-Results_10yr!B29*F105)*(1-Results_10yr!B33),0) -> 0 | G107: =IF(AND(5>=5,5<=5+Results_10yr!B28-1),(B105-Results_10yr!B29*G105)*(1-Results_10yr!B33),0) -> 7898410.8 | H107: =IF(AND(6>=5,6<=5+Results_10yr!B28-1),(B105-Results_10yr!B29*H105)*(1-Results_10yr!B33),0) -> 8609267.8 | I107: =IF(AND(7>=5,7<=5+Results_10yr!B28-1),(B105-Results_10yr!B29*I105)*(1-Results_10yr!B33),0) -> 9384101.9 | J107: =IF(AND(8>=5,8<=5+Results_10yr!B28-1),(B105-Results_10yr!B29*J105)*(1-Results_10yr!B33),0) -> 10228671 | K107: =IF(AND(9>=5,9<=5+Results_10yr!B28-1),(B105-Results_10yr!B29*K105)*(1-Results_10yr!B33),0) -> 11149251 | L107: =IF(AND(10>=5,10<=5+Results_10yr!B28-1),(B105-Results_10yr!B29*L105)*(1-Results_10yr!B33),0) -> 12152684
A108: C5 EndBal | C108: =IF(AND(1>=5,1<=5+Results_10yr!B28-1),C105-(B105-Results_10yr!B29*C105),0) -> 0 | D108: =IF(AND(2>=5,2<=5+Results_10yr!B28-1),D105-(B105-Results_10yr!B29*D105),0) -> 0 | E108: =IF(AND(3>=5,3<=5+Results_10yr!B28-1),E105-(B105-Results_10yr!B29*E105),0) -> 0 | F108: =IF(AND(4>=5,4<=5+Results_10yr!B28-1),F105-(B105-Results_10yr!B29*F105),0) -> 0 | G108: =IF(AND(5>=5,5<=5+Results_10yr!B28-1),G105-(B105-Results_10yr!B29*G105),0) -> 1.1210159e+08 | H108: =IF(AND(6>=5,6<=5+Results_10yr!B28-1),H105-(B105-Results_10yr!B29*H105),0) -> 1.0349232e+08 | I108: =IF(AND(7>=5,7<=5+Results_10yr!B28-1),I105-(B105-Results_10yr!B29*I105),0) -> 94108220 | J108: =IF(AND(8>=5,8<=5+Results_10yr!B28-1),J105-(B105-Results_10yr!B29*J105),0) -> 83879549 | K108: =IF(AND(9>=5,9<=5+Results_10yr!B28-1),K105-(B105-Results_10yr!B29*K105),0) -> 72730297 | L108: =IF(AND(10>=5,10<=5+Results_10yr!B28-1),L105-(B105-Results_10yr!B29*L105),0) -> 60577613
A109: C6 BeginBal | B109: =IF(H85=0,0,-PMT(Results_10yr!B29,Results_10yr!B28,H85)) -> 28047616 | C109: =IF(AND(1>=6,1<=6+Results_10yr!B28-1),IF(H85=0,0,B112),0) -> 0 | D109: =IF(AND(2>=6,2<=6+Results_10yr!B28-1),IF(H85=0,0,C112),0) -> 0 | E109: =IF(AND(3>=6,3<=6+Results_10yr!B28-1),IF(H85=0,0,D112),0) -> 0 | F109: =IF(AND(4>=6,4<=6+Results_10yr!B28-1),IF(H85=0,0,E112),0) -> 0 | G109: =IF(AND(5>=6,5<=6+Results_10yr!B28-1),IF(H85=0,0,F112),0) -> 0 | H109: =IF(AND(6>=6,6<=6+Results_10yr!B28-1),IF(H85=0,0,H85),0) -> 180000000 | I109: =IF(AND(7>=6,7<=6+Results_10yr!B28-1),IF(H85=0,0,H112),0) -> 1.6815238e+08 | J109: =IF(AND(8>=6,8<=6+Results_10yr!B28-1),IF(H85=0,0,I112),0) -> 1.5523848e+08 | K109: =IF(AND(9>=6,9<=6+Results_10yr!B28-1),IF(H85=0,0,J112),0) -> 1.4116233e+08 | L109: =IF(AND(10>=6,10<=6+Results_10yr!B28-1),IF(H85=0,0,K112),0) -> 1.2581932e+08
A110: C6 Interest | B110: =IF(C83="",0,0) -> 0 | C110: =IF(AND(1>=6,1<=6+Results_10yr!B28-1),Results_10yr!B29*C109*(1-Results_10yr!B33),0) -> 0 | D110: =IF(AND(2>=6,2<=6+Results_10yr!B28-1),Results_10yr!B29*D109*(1-Results_10yr!B33),0) -> 0 | E110: =IF(AND(3>=6,3<=6+Results_10yr!B28-1),Results_10yr!B29*E109*(1-Results_10yr!B33),0) -> 0 | F110: =IF(AND(4>=6,4<=6+Results_10yr!B28-1),Results_10yr!B29*F109*(1-Results_10yr!B33),0) -> 0 | G110: =IF(AND(5>=6,5<=6+Results_10yr!B28-1),Results_10yr!B29*G109*(1-Results_10yr!B33),0) -> 0 | H110: =IF(AND(6>=6,6<=6+Results_10yr!B28-1),Results_10yr!B29*H109*(1-Results_10yr!B33),0) -> 16200000 | I110: =IF(AND(7>=6,7<=6+Results_10yr!B28-1),Results_10yr!B29*I109*(1-Results_10yr!B33),0) -> 15133715 | J110: =IF(AND(8>=6,8<=6+Results_10yr!B28-1),Results_10yr!B29*J109*(1-Results_10yr!B33),0) -> 13971463 | K110: =IF(AND(9>=6,9<=6+Results_10yr!B28-1),Results_10yr!B29*K109*(1-Results_10yr!B33),0) -> 12704610 | L110: =IF(AND(10>=6,10<=6+Results_10yr!B28-1),Results_10yr!B29*L109*(1-Results_10yr!B33),0) -> 11323739
A111: C6 Principal | C111: =IF(AND(1>=6,1<=6+Results_10yr!B28-1),(B109-Results_10yr!B29*C109)*(1-Results_10yr!B33),0) -> 0 | D111: =IF(AND(2>=6,2<=6+Results_10yr!B28-1),(B109-Results_10yr!B29*D109)*(1-Results_10yr!B33),0) -> 0 | E111: =IF(AND(3>=6,3<=6+Results_10yr!B28-1),(B109-Results_10yr!B29*E109)*(1-Results_10yr!B33),0) -> 0 | F111: =IF(AND(4>=6,4<=6+Results_10yr!B28-1),(B109-Results_10yr!B29*F109)*(1-Results_10yr!B33),0) -> 0 | G111: =IF(AND(5>=6,5<=6+Results_10yr!B28-1),(B109-Results_10yr!B29*G109)*(1-Results_10yr!B33),0) -> 0 | H111: =IF(AND(6>=6,6<=6+Results_10yr!B28-1),(B109-Results_10yr!B29*H109)*(1-Results_10yr!B33),0) -> 11847616 | I111: =IF(AND(7>=6,7<=6+Results_10yr!B28-1),(B109-Results_10yr!B29*I109)*(1-Results_10yr!B33),0) -> 12913902 | J111: =IF(AND(8>=6,8<=6+Results_10yr!B28-1),(B109-Results_10yr!B29*J109)*(1-Results_10yr!B33),0) -> 14076153 | K111: =IF(AND(9>=6,9<=6+Results_10yr!B28-1),(B109-Results_10yr!B29*K109)*(1-Results_10yr!B33),0) -> 15343007 | L111: =IF(AND(10>=6,10<=6+Results_10yr!B28-1),(B109-Results_10yr!B29*L109)*(1-Results_10yr!B33),0) -> 16723877
A112: C6 EndBal | C112: =IF(AND(1>=6,1<=6+Results_10yr!B28-1),C109-(B109-Results_10yr!B29*C109),0) -> 0 | D112: =IF(AND(2>=6,2<=6+Results_10yr!B28-1),D109-(B109-Results_10yr!B29*D109),0) -> 0 | E112: =IF(AND(3>=6,3<=6+Results_10yr!B28-1),E109-(B109-Results_10yr!B29*E109),0) -> 0 | F112: =IF(AND(4>=6,4<=6+Results_10yr!B28-1),F109-(B109-Results_10yr!B29*F109),0) -> 0 | G112: =IF(AND(5>=6,5<=6+Results_10yr!B28-1),G109-(B109-Results_10yr!B29*G109),0) -> 0 | H112: =IF(AND(6>=6,6<=6+Results_10yr!B28-1),H109-(B109-Results_10yr!B29*H109),0) -> 1.6815238e+08 | I112: =IF(AND(7>=6,7<=6+Results_10yr!B28-1),I109-(B109-Results_10yr!B29*I109),0) -> 1.5523848e+08 | J112: =IF(AND(8>=6,8<=6+Results_10yr!B28-1),J109-(B109-Results_10yr!B29*J109),0) -> 1.4116233e+08 | K112: =IF(AND(9>=6,9<=6+Results_10yr!B28-1),K109-(B109-Results_10yr!B29*K109),0) -> 1.2581932e+08 | L112: =IF(AND(10>=6,10<=6+Results_10yr!B28-1),L109-(B109-Results_10yr!B29*L109),0) -> 1.0909545e+08
